Workbook

Sheet 00_PORTADA
A1: REGISTRO MAESTRO PROGRAMAS Y FICHAS DE COMUNICACIÓN Y SUSTENTABILIDAD SOCIAL
A2: Libro reorganizado para gestión, análisis y control de calidad de los programas sociales de PARACEL. Conserva las hojas originales y agrega capas ejecutivas, normalizadas y de verificación.
A4: Objetivo del libro | B4: Centralizar la trazabilidad documental, la estructura programática, los targets, los indicadores y las alertas de calidad del registro maestro.
A6: 01 | B6: 01_RESUMEN | C6: Vista ejecutiva con KPI, presupuesto consolidado y seguimiento por programa | E6: Indicadores de control
A7: 02 | B7: 02_MATRIZ_EJECUTIVA | C7: Matriz limpia de targets con campos derivados, presupuesto normalizado y semáforo de calidad | E7: Programas vigentes | F7: =COUNTIF('Programas Vigentes'!$J$2:$J$1000,"Vigente") -> 14
A8: 03 | B8: 03_INDICADORES_NORMALIZADOS | C8: Indicadores separados en filas para explotación analítica | E8: Programas con ficha | F8: =COUNTIF('Programas Vigentes'!$I$2:$I$1000,"Sí") -> 12
A9: 04 | B9: 04_CRONOGRAMA_TARGETS | C9: Calendario mensual de activación por target | E9: Programs sin ficha | F9: =COUNTIF('Programas Vigentes'!$I$2:$I$1000,"No") -> 2
A10: 06 | B10: 06_DICCIONARIO | C10: Definición de hojas, campos y criterios de mantenimiento | E10: Indicadores normalizados | F10: =COUNTA('03_INDICADORES_NORMALIZADOS'!$A$2:$A$5000) -> 228
A11: RAW | B11: Programas Vigentes | C11: Hoja original, catálogo de programas vigentes | E11: Alertas críticas | F11: =COUNTIF('02_MATRIZ_EJECUTIVA'!$AG$2:$AG$1000,"Crítico") -> 31
A12: RAW | B12: Historial Versiones | C12: Hoja original, historial documental
A13: RAW | B13: Fichas Técnicas | C13: Hoja original, consolidado de fichas
A14: RAW | B14: Targets por Ficha | C14: Hoja original, targets por ficha
A15: RAW | B15: Indicadores | C15: Hoja original, indicadores agregados
A16: RAW | B16: MATRIZ CONSOLIDADA | C16: Hoja original, matriz histórica consolidada

Sheet 01_RESUMEN
A1: 01. RESUMEN EJECUTIVO
A2: Síntesis del portafolio social, cobertura documental y calidad del registro maestro.
A4: Total programas | D4: Programas vigentes | G4: Programas con ficha | J4: Programas sin ficha
A5: =COUNTA('Programas Vigentes'!$A$2:$A$1000) -> 14 | D5: =COUNTIF('Programas Vigentes'!$J$2:$J$1000,"Vigente") -> 14 | G5: =COUNTIF('Programas Vigentes'!$I$2:$I$1000,"Sí") -> 12 | J5: =COUNTIF('Programas Vigentes'!$I$2:$I$1000,"No") -> 2
A7: Targets | D7: Indicadores individualizados | G7: Documentos en historial | J7: Presupuesto total normalizado
A8: =COUNTA('Targets por Ficha'!$A$2:$A$1000) -> 31 | D8: =COUNTA('03_INDICADORES_NORMALIZADOS'!$A$2:$A$5000) -> 228 | G8: =COUNTA('Historial Versiones'!$A$2:$A$2000) -> 100 | J8: =SUM('02_MATRIZ_EJECUTIVA'!$AC$5:$AC$1000) -> 414615
A11: Seguimiento por programa | K11: Hallazgos clave
A12: Código | B12: Programa | C12: Estado | D12: Tiene Ficha | E12: Targets | F12: Versiones | G12: Presupuesto (USD) | H12: Completitud Prom. | I12: Críticos | K12: La matriz ejecutiva contiene 31 registros de target.
A13: PR-SS-AAE | B13: Programa de Manejo Interno por Afectación de Tierras y Riesgos por Agentes Externos | C13: Vigente | D13: Sí | E13: =COUNTIF('02_MATRIZ_EJECUTIVA'!$B$5:$B$1000,A13) -> 2 | F13: 4 | G13: =SUMIF('02_MATRIZ_EJECUTIVA'!$B$5:$B$1000,A13,'02_MATRIZ_EJECUTIVA'!$AC$5:$AC$1000) -> 0 | H13: =IFERROR(AVERAGEIF('02_MATRIZ_EJECUTIVA'!$B$5:$B$1000,A13,'02_MATRIZ_EJECUTIVA'!$AE$5:$AE$1000),"") -> 0.588 | I13: =COUNTIFS('02_MATRIZ_EJECUTIVA'!$B$5:$B$1000,A13,'02_MATRIZ_EJECUTIVA'!$AG$5:$AG$1000,"Crítico") -> 2 | K13: Existen 2 programas vigentes sin ficha técnica explícita en el catálogo.
A14: PR-SS-CON | B14: Programa de Sensibilización y Seguimiento a Contratistas y Trabajadores | C14: Vigente | D14: Sí | E14: =COUNTIF('02_MATRIZ_EJECUTIVA'!$B$5:$B$1000,A14) -> 2 | F14: 4 | G14: =SUMIF('02_MATRIZ_EJECUTIVA'!$B$5:$B$1000,A14,'02_MATRIZ_EJECUTIVA'!$AC$5:$AC$1000) -> 0 | H14: =IFERROR(AVERAGEIF('02_MATRIZ_EJECUTIVA'!$B$5:$B$1000,A14,'02_MATRIZ_EJECUTIVA'!$AE$5:$AE$1000),"") -> 0.6175 | I14: =COUNTIFS('02_MATRIZ_EJECUTIVA'!$B$5:$B$1000,A14,'02_MATRIZ_EJECUTIVA'!$AG$5:$AG$1000,"Crítico") -> 2 | K14: Los campos de fórmula, fuente, periodicidad, responsable y evidencia se encuentran ampliamente incompletos en los targets.
A15: PR-SS-EMU | B15: Programa de Empoderamiento de la Mujer | C15: Vigente | D15: Sí | E15: =COUNTIF('02_MATRIZ_EJECUTIVA'!$B$5:$B$1000,A15) -> 2 | F15: 4 | G15: =SUMIF('02_MATRIZ_EJECUTIVA'!$B$5:$B$1000,A15,'02_MATRIZ_EJECUTIVA'!$AC$5:$AC$1000) -> 0 | H15: =IFERROR(AVERAGEIF('02_MATRIZ_EJECUTIVA'!$B$5:$B$1000,A15,'02_MATRIZ_EJECUTIVA'!$AE$5:$AE$1000),"") -> 0.647 | I15: =COUNTIFS('02_MATRIZ_EJECUTIVA'!$B$5:$B$1000,A15,'02_MATRIZ_EJECUTIVA'!$AG$5:$AG$1000,"Crítico") -> 2 | K15: La normalización de indicadores permite trabajar el seguimiento a nivel de indicador individual.
A16: PR-SS-MDO | B16: Programa de Desarrollo y Vinculación de Mano de Obra Local | C16: Vigente | D16: Sí | E16: =COUNTIF('02_MATRIZ_EJECUTIVA'!$B$5:$B$1000,A16) -> 2 | F16: 4 | G16: =SUMIF('02_MATRIZ_EJECUTIVA'!$B$5:$B$1000,A16,'02_MATRIZ_EJECUTIVA'!$AC$5:$AC$1000) -> 14851 | H16: =IFERROR(AVERAGEIF('02_MATRIZ_EJECUTIVA'!$B$5:$B$1000,A16,'02_MATRIZ_EJECUTIVA'!$AE$5:$AE$1000),"") -> 0.6175 | I16: =COUNTIFS('02_MATRIZ_EJECUTIVA'!$B$5:$B$1000,A16,'02_MATRIZ_EJECUTIVA'!$AG$5:$AG$1000,"Crítico") -> 2
A17: PR-SS-MSC | B17: Programa de Manejo Social | C17: Vigente | D17: Sí | E17: =COUNTIF('02_MATRIZ_EJECUTIVA'!$B$5:$B$1000,A17) -> 2 | F17: 4 | G17: =SUMIF('02_MATRIZ_EJECUTIVA'!$B$5:$B$1000,A17,'02_MATRIZ_EJECUTIVA'!$AC$5:$AC$1000) -> 14486 | H17: =IFERROR(AVERAGEIF('02_MATRIZ_EJECUTIVA'!$B$5:$B$1000,A17,'02_MATRIZ_EJECUTIVA'!$AE$5:$AE$1000),"") -> 0.647 | I17: =COUNTIFS('02_MATRIZ_EJECUTIVA'!$B$5:$B$1000,A17,'02_MATRIZ_EJECUTIVA'!$AG$5:$AG$1000,"Crítico") -> 2
A18: PR-SS-MSO | B18: Programa de Monitoreo Social | C18: Vigente | D18: No | E18: =COUNTIF('02_MATRIZ_EJECUTIVA'!$B$5:$B$1000,A18) -> 0 | F18: 4 | G18: =SUMIF('02_MATRIZ_EJECUTIVA'!$B$5:$B$1000,A18,'02_MATRIZ_EJECUTIVA'!$AC$5:$AC$1000) -> 0 | H18: =IFERROR(AVERAGEIF('02_MATRIZ_EJECUTIVA'!$B$5:$B$1000,A18,'02_MATRIZ_EJECUTIVA'!$AE$5:$AE$1000),"") | I18: =COUNTIFS('02_MATRIZ_EJECUTIVA'!$B$5:$B$1000,A18,'02_MATRIZ_EJECUTIVA'!$AG$5:$AG$1000,"Crítico") -> 0
A19: PR-SS-PCS | B19: Programa de Prevención y Gestión de Contingencias Sociales | C19: Vigente | D19: Sí | E19: =COUNTIF('02_MATRIZ_EJECUTIVA'!$B$5:$B$1000,A19) -> 2 | F19: 4 | G19: =SUMIF('02_MATRIZ_EJECUTIVA'!$B$5:$B$1000,A19,'02_MATRIZ_EJECUTIVA'!$AC$5:$AC$1000) -> 6708 | H19: =IFERROR(AVERAGEIF('02_MATRIZ_EJECUTIVA'!$B$5:$B$1000,A19,'02_MATRIZ_EJECUTIVA'!$AE$5:$AE$1000),"") -> 0.647 | I19: =COUNTIFS('02_MATRIZ_EJECUTIVA'!$B$5:$B$1000,A19,'02_MATRIZ_EJECUTIVA'!$AG$5:$AG$1000,"Crítico") -> 2
A20: PR-SS-PCU | B20: Programa de Gestión del Patrimonio Cultural | C20: Vigente | D20: Sí | E20: =COUNTIF('02_MATRIZ_EJECUTIVA'!$B$5:$B$1000,A20) -> 2 | F20: 4 | G20: =SUMIF('02_MATRIZ_EJECUTIVA'!$B$5:$B$1000,A20,'02_MATRIZ_EJECUTIVA'!$AC$5:$AC$1000) -> 0 | H20: =IFERROR(AVERAGEIF('02_MATRIZ_EJECUTIVA'!$B$5:$B$1000,A20,'02_MATRIZ_EJECUTIVA'!$AE$5:$AE$1000),"") -> 0.647 | I20: =COUNTIFS('02_MATRIZ_EJECUTIVA'!$B$5:$B$1000,A20,'02_MATRIZ_EJECUTIVA'!$AG$5:$AG$1000,"Crítico") -> 2
A21: PR-SS-PDP | B21: Programa de Promoción y Desarrollo de Empresas Proveedoras Locales | C21: Vigente | D21: Sí | E21: =COUNTIF('02_MATRIZ_EJECUTIVA'!$B$5:$B$1000,A21) -> 3 | F21: 4 | G21: =SUMIF('02_MATRIZ_EJECUTIVA'!$B$5:$B$1000,A21,'02_MATRIZ_EJECUTIVA'!$AC$5:$AC$1000) -> 0 | H21: =IFERROR(AVERAGEIF('02_MATRIZ_EJECUTIVA'!$B$5:$B$1000,A21,'02_MATRIZ_EJECUTIVA'!$AE$5:$AE$1000),"") -> 0.588 | I21: =COUNTIFS('02_MATRIZ_EJECUTIVA'!$B$5:$B$1000,A21,'02_MATRIZ_EJECUTIVA'!$AG$5:$AG$1000,"Crítico") -> 3
A22: PR-SS-QRI | B22: Programa de Gestión de Quejas, Consultas y Sugerencias | C22: Vigente | D22: Sí | E22: =COUNTIF('02_MATRIZ_EJECUTIVA'!$B$5:$B$1000,A22) -> 2 | F22: 4 | G22: =SUMIF('02_MATRIZ_EJECUTIVA'!$B$5:$B$1000,A22,'02_MATRIZ_EJECUTIVA'!$AC$5:$AC$1000) -> 0 | H22: =IFERROR(AVERAGEIF('02_MATRIZ_EJECUTIVA'!$B$5:$B$1000,A22,'02_MATRIZ_EJECUTIVA'!$AE$5:$AE$1000),"") -> 0.588 | I22: =COUNTIFS('02_MATRIZ_EJECUTIVA'!$B$5:$B$1000,A22,'02_MATRIZ_EJECUTIVA'!$AG$5:$AG$1000,"Crítico") -> 2
A23: PR-SS-RCI | B23: Programa de Relacionamiento con Comunidades e Inversión Social | C23: Vigente | D23: Sí | E23: =COUNTIF('02_MATRIZ_EJECUTIVA'!$B$5:$B$1000,A23) -> 2 | F23: 4 | G23: =SUMIF('02_MATRIZ_EJECUTIVA'!$B$5:$B$1000,A23,'02_MATRIZ_EJECUTIVA'!$AC$5:$AC$1000) -> 275831 | H23: =IFERROR(AVERAGEIF('02_MATRIZ_EJECUTIVA'!$B$5:$B$1000,A23,'02_MATRIZ_EJECUTIVA'!$AE$5:$AE$1000),"") -> 0.588 | I23: =COUNTIFS('02_MATRIZ_EJECUTIVA'!$B$5:$B$1000,A23,'02_MATRIZ_EJECUTIVA'!$AG$5:$AG$1000,"Crítico") -> 2
A24: PR-SS-RPI | B24: Programa de Relacionamiento con Comunidades Indígenas | C24: Vigente | D24: Sí | E24: =COUNTIF('02_MATRIZ_EJECUTIVA'!$B$5:$B$1000,A24) -> 6 | F24: 4 | G24: =SUMIF('02_MATRIZ_EJECUTIVA'!$B$5:$B$1000,A24,'02_MATRIZ_EJECUTIVA'!$AC$5:$AC$1000) -> 34350 | H24: =IFERROR(AVERAGEIF('02_MATRIZ_EJECUTIVA'!$B$5:$B$1000,A24,'02_MATRIZ_EJECUTIVA'!$AE$5:$AE$1000),"") -> 0.529 | I24: =COUNTIFS('02_MATRIZ_EJECUTIVA'!$B$5:$B$1000,A24,'02_MATRIZ_EJECUTIVA'!$AG$5:$AG$1000,"Crítico") -> 6
A25: PR-SS-SEV | B25: Programa de Seguridad Vial | C25: Vigente | D25: No | E25: =COUNTIF('02_MATRIZ_EJECUTIVA'!$B$5:$B$1000,A25) -> 0 | F25: 5 | G25: =SUMIF('02_MATRIZ_EJECUTIVA'!$B$5:$B$1000,A25,'02_MATRIZ_EJECUTIVA'!$AC$5:$AC$1000) -> 0 | H25: =IFERROR(AVERAGEIF('02_MATRIZ_EJECUTIVA'!$B$5:$B$1000,A25,'02_MATRIZ_EJECUTIVA'!$AE$5:$AE$1000),"") | I25: =COUNTIFS('02_MATRIZ_EJECUTIVA'!$B$5:$B$1000,A25,'02_MATRIZ_EJECUTIVA'!$AG$5:$AG$1000,"Crítico") -> 0
A26: PR-SS-SSC | B26: Programa de Salud y Seguridad Comunitaria | C26: Vigente | D26: Sí | E26: =COUNTIF('02_MATRIZ_EJECUTIVA'!$B$5:$B$1000,A26) -> 4 | F26: 5 | G26: =SUMIF('02_MATRIZ_EJECUTIVA'!$B$5:$B$1000,A26,'02_MATRIZ_EJECUTIVA'!$AC$5:$AC$1000) -> 68389 | H26: =IFERROR(AVERAGEIF('02_MATRIZ_EJECUTIVA'!$B$5:$B$1000,A26,'02_MATRIZ_EJECUTIVA'!$AE$5:$AE$1000),"") -> 0.647 | I26: =COUNTIFS('02_MATRIZ_EJECUTIVA'!$B$5:$B$1000,A26,'02_MATRIZ_EJECUTIVA'!$AG$5:$AG$1000,"Crítico") -> 4

Sheet 02_MATRIZ_EJECUTIVA
A1: 02. MATRIZ EJECUTIVA DE TARGETS
A2: Versión depurada de la matriz consolidada, se excluye el anexo histórico embebido y se agregan campos derivados para análisis y control.
A4: N° | B4: CÓDIGO PROGRAMA | C4: NOMBRE PROGRAMA | D4: VERSIÓN PROG. | E4: ESTADO | F4: NOMBRE FICHA | G4: VERSIÓN FICHA | H4: FECHA FICHA | I4: TARGET N° | J4: DESCRIPCIÓN TARGET | K4: ACTIVIDADES | L4: INDICADOR | M4: FÓRMULA DE CÁLCULO | N4: FUENTE DE VERIFICACIÓN | O4: PERIODICIDAD | P4: RESPONSABLE | Q4: EVIDENCIA | R4: PRODUCTOS | S4: RESULTADO ESPERADO | T4: PRESUPUESTO (USD) | U4: MESES ACTIVOS | V4: PROPÓSITO FICHA | W4: NECESIDAD | X4: OBJETIVO PROGRAMA | Y4: ALCANCE PROGRAMA | Z4: MARCO LEGAL | AA4: ID REGISTRO | AB4: AÑO FICHA | AC4: PRESUPUESTO NORMALIZADO (USD) | AD4: N° MESES ACTIVOS | AE4: % COMPLETITUD OPERATIVA | AF4: INCIDENCIAS | AG4: ESTADO CALIDAD
A5: 1 | B5: PR-SS-MDO | C5: Desarrollo y Vinculación de Mano de Obra Local | D5: v05 | E5: Vigente | F5: PROGRAMA DE DESARROLLO Y VINCULACIÓN CON LA MANO DE OBRA LOCAL | G5: v01 | H5: 45812 | I5: 1 | J5: Contribuir para aumentar el número de jóvenes y adultos con competencias técnicas y profesionales, para acceder al empleo (el trabajo decente) a través del desarrollo de [10] cursos de capacitación, y [8] jornadas de certificación laboral por competencias, en los componentes Forestal Industrial e I | K5: 1. Selección de organizaciones aliadas para el desarrollo de las capacitaciones y las certificaciones. 2. Suscribir convenios con instituciones educativas locales y nacionales con el fin de acordar un marco de cooperación para la formación y capacitación laboral del capital humano local y nacional. | L5: - Indicadores de Educación - Indicadores de Empleo | R5: 1 - Convenios / acuerdos. 2 - Curso de capacitación 3 - Jornadas de certificación. 4 - Base de datos de personas que culminaron los cursos y certificaciones. 4- Informe de línea de base. 5- Proyecto | S5: - Aumento del número de jóvenes y adultos con competencias técnicas y profesionales para acceder al empleo (trabajo decente). - Profesionales certificados para acceder al empleo (trabajo decente o | U5: May, Jun, Jul, Ago, Sep, Oct, Nov, Dic | V5: Desarrollar e instalar competencias y capacidades técnicas y profesionales en el área de influencia de Paracel | W5: - Falta de competencias técnicas y profesionales en la mano de obra local y departamental. - Centralización en la ciudad Concepción de los servicios de educación técnico y profesional. - Población | X5: Promover la generación de empleo local a través de la vinculación de mano de obra calificada y no calificada, [además del desarrollo e instalación de capacidades, en el área de influencia de Paracel]. | Y5: DEFINICIONES Área de Influencia Directa (AID) del componente industrial: incluyen 5 distritos cercanos al sitio de la Planta Industrial, incluyendo a 18 comunidades que se encuentran en un radio de 13 | AA5: =B5&"-T"&TEXT(I5,"00") -> PR-SS-MDO-T01 | AB5: =IF(H5="","",VALUE(LEFT(TEXT(H5,"yyyy-mm-dd"),4))) -> 2025 | AC5: 0 | AD5: =IF(U5="","",LEN(U5)-LEN(SUBSTITUTE(U5,",",""))+1) -> 8 | AE5: =ROUND((COUNTIF(J5,"<>") + COUNTIF(K5,"<>") + COUNTIF(L5,"<>") + COUNTIF(M5,"<>") + COUNTIF(N5,"<>") + COUNTIF(O5,"<>") + COUNTIF(P5,"<>") + COUNTIF(Q5,"<>") + COUNTIF(R5,"<>") + COUNTIF(S5,"<>") + COUNTIF(T5,"<>") + COUNTIF(U5,"<>") + COUNTIF(V5,"<>") + COUNTIF(W5,"<>") + COUNTIF(X5,"<>") + COUNTIF(Y5,"<>") + COUNTIF(Z5,"<>"))/17,3) -> 0.588 | AF5: =COUNTBLANK(M5:Q5)+IF(OR(T5="",T5="----"),1,0)+IF(U5="",1,0) -> 6 | AG5: =IF(AF5=0,"Completo",IF(AF5<=2,"Parcial","Crítico")) -> Crítico
A6: 2 | B6: PR-SS-MDO | C6: Desarrollo y Vinculación de Mano de Obra Local | D6: v05 | E6: Vigente | F6: PROGRAMA DE DESARROLLO Y VINCULACIÓN CON LA MANO DE OBRA LOCAL | G6: v01 | H6: 45812 | I6: 2 | J6: Becar a jóvenes de las comunidades del área e influencia de Paracel: - 10 jóvenes para educación en Bachiller Técnico. - 11 jóvenes para educación Terciaria. | K6: 1 - Seleccionar a las personas jóvenes conforme a criterios de elegibilidad. 2 - Medición de la línea de base. 3 - Buscar aliados estratégicos para la implementación del proyecto de becas (si aplica). 4 - Firma de carta compromiso. 5- Llamado interno para contar con voluntarios/as para el acompaña | L6: 1. Indicadores socioeconómicos. 2. Número de personas beneficiadas clasificadas por edad, sexo, comunidad, etnía. 3. Nivel academico alcanzado por los padres/tutores - hermanos/as mayores. 4. Número de instituciones alidas y especialidades. 5. Inversión mensual (seguimiento del presupuesto). 6. Horas al mes destinada por parte de padrinos/madrinas en el acompañamiento de las personas. 7. Reporte de calificaciones por período académico y por estudiante. | R6: Jóvenes con estudios técnicos y terciarios finalizados. | S6: Jóvenes con estudios técnicos y terciarios finalizados. | T6: 14.851 | U6: Feb, Mar, Abr, May, Jun, Jul, Ago, Sep, Oct, Nov, Dic | V6: Desarrollar e instalar competencias y capacidades técnicas y profesionales en el área de influencia de Paracel | W6: - Falta de competencias técnicas y profesionales en la mano de obra local y departamental. - Centralización en la ciudad Concepción de los servicios de educación técnico y profesional. - Población | X6: Promover la generación de empleo local a través de la vinculación de mano de obra calificada y no calificada, [además del desarrollo e instalación de capacidades, en el área de influencia de Paracel]. | Y6: DEFINICIONES Área de Influencia Directa (AID) del componente industrial: incluyen 5 distritos cercanos al sitio de la Planta Industrial, incluyendo a 18 comunidades que se encuentran en un radio de 13 | AA6: =B6&"-T"&TEXT(I6,"00") -> PR-SS-MDO-T02 | AB6: =IF(H6="","",VALUE(LEFT(TEXT(H6,"yyyy-mm-dd"),4))) -> 2025 | AC6: 14851 | AD6: =IF(U6="","",LEN(U6)-LEN(SUBSTITUTE(U6,",",""))+1) -> 11 | AE6: =ROUND((COUNTIF(J6,"<>") + COUNTIF(K6,"<>") + COUNTIF(L6,"<>") + COUNTIF(M6,"<>") + COUNTIF(N6,"<>") + COUNTIF(O6,"<>") + COUNTIF(P6,"<>") + COUNTIF(Q6,"<>") + COUNTIF(R6,"<>") + COUNTIF(S6,"<>") + COUNTIF(T6,"<>") + COUNTIF(U6,"<>") + COUNTIF(V6,"<>") + COUNTIF(W6,"<>") + COUNTIF(X6,"<>") + COUNTIF(Y6,"<>") + COUNTIF(Z6,"<>"))/17,3) -> 0.647 | AF6: =COUNTBLANK(M6:Q6)+IF(OR(T6="",T6="----"),1,0)+IF(U6="",1,0) -> 5 | AG6: =IF(AF6=0,"Completo",IF(AF6<=2,"Parcial","Crítico")) -> Crítico
A7: 3 | B7: PR-SS-EMU | C7: Empoderamiento de la Mujer | D7: v04 | E7: Vigente | F7: EMPODERAMIENTO DE LA MUJER | G7: v01 | H7: 45812 | I7: 1 | J7: Difundir la Ruta de Auxilio desarrollada en el año 2024 con foco en los siguientes municipios: Concepción, Paso Barreto, Sargento José Felix López, Paso Horqueta, alcanzando como mínimo al 80% de las comunidades del área de influencia de Paracel. | K7: 1. Selección de las áreas geográficas a ser intervenidas (componentes) y comunidades alcanzadas. 2. Difusión de los materiales. 3. Desarrollo del informe final. | L7: - Número de personas alcanzadas clasificadas sexo, edad, etnia, comunidad, institución, etc. - N° de materiales desarrollados y difundidos. | R7: 1. Materiales difundidos. 2. Informe final. | S7: Personas de las comunidades del área de influencia de Paracel con información la ruta de auxilio ante casos de violencia hacia las mujeres. | T7: 0 | U7: Jun, Jul, Oct, Nov, Dic | V7: Empoderar a las mujeres para acortar las brechas de desigualdad étnicas y de género. | W7: Las mujeres no participan plenamente de todos los sectores y todos los niveles de la actividad económica, y por ende no se construyen economías fuertes, y esto conlleva a no cumplir los objetivos de | X7: Empoderar a las mujeres para acortar las brechas de desigualdad étnicas y de género. | [FSC-STD-PRY-01-2022] Normas de Desempeño IFC REGISTROS Y/O ANEXO [Registro del Plan de Comunicación [Registro de | Y7: El programa de Empoderamiento de la Mujer tiene el siguiente alcance: DEFINICIONES Área de Influencia Directa (AID) del componente indígena: está compuesta por las comunidades indígenas ubicadas entr | AA7: =B7&"-T"&TEXT(I7,"00") -> PR-SS-EMU-T01 | AB7: =IF(H7="","",VALUE(LEFT(TEXT(H7,"yyyy-mm-dd"),4))) -> 2025 | AC7: 0 | AD7: =IF(U7="","",LEN(U7)-LEN(SUBSTITUTE(U7,",",""))+1) -> 5 | AE7: =ROUND((COUNTIF(J7,"<>") + COUNTIF(K7,"<>") + COUNTIF(L7,"<>") + COUNTIF(M7,"<>") + COUNTIF(N7,"<>") + COUNTIF(O7,"<>") + COUNTIF(P7,"<>") + COUNTIF(Q7,"<>") + COUNTIF(R7,"<>") + COUNTIF(S7,"<>") + COUNTIF(T7,"<>") + COUNTIF(U7,"<>") + COUNTIF(V7,"<>") + COUNTIF(W7,"<>") + COUNTIF(X7,"<>") + COUNTIF(Y7,"<>") + COUNTIF(Z7,"<>"))/17,3) -> 0.647 | AF7: =COUNTBLANK(M7:Q7)+IF(OR(T7="",T7="----"),1,0)+IF(U7="",1,0) -> 5 | AG7: =IF(AF7=0,"Completo",IF(AF7<=2,"Parcial","Crítico")) -> Crítico
A8: 4 | B8: PR-SS-EMU | C8: Empoderamiento de la Mujer | D8: v04 | E8: Vigente | F8: EMPODERAMIENTO DE LA MUJER | G8: v01 | H8: 45812 | I8: 2 | J8: Fortalecer la red de apoyo para las mujeres de la Región de Concepción desarrollando como mínimo 3 espacios. | K8: 1. Propiciar espacios de intercambio de conocimientos, experiencias y aprendizajes con la red de mujeres y referentes invitadas por Paracel. 2. Desarrollo del informe final. | L8: - Número de personas que participaron de los espacios desagregadas por sexo, edad, etnia, organización, etc. - Número de horas de los espacios. - Número de espacios propociados. - Número de temas abordados. - Número de personas invitadas. - Número de personas vinculadas al proyecto externas a Paracel (por actividad). - Inversión. - Conocimiento de las personas antes y despues de la participación de los espacios. | R8: 1. Informe final. | S8: Mujeres de la red de apoyo con mayor conocimiento para afrontar los desafíos de las mujeres en la sociedad. | T8: 0 | U8: Jul, Sep, Nov, Dic | V8: Empoderar a las mujeres para acortar las brechas de desigualdad étnicas y de género. | W8: Las mujeres no participan plenamente de todos los sectores y todos los niveles de la actividad económica, y por ende no se construyen economías fuertes, y esto conlleva a no cumplir los objetivos de | X8: Empoderar a las mujeres para acortar las brechas de desigualdad étnicas y de género. | [FSC-STD-PRY-01-2022] Normas de Desempeño IFC REGISTROS Y/O ANEXO [Registro del Plan de Comunicación [Registro de | Y8: El programa de Empoderamiento de la Mujer tiene el siguiente alcance: DEFINICIONES Área de Influencia Directa (AID) del componente indígena: está compuesta por las comunidades indígenas ubicadas entr | AA8: =B8&"-T"&TEXT(I8,"00") -> PR-SS-EMU-T02 | AB8: =IF(H8="","",VALUE(LEFT(TEXT(H8,"yyyy-mm-dd"),4))) -> 2025 | AC8: 0 | AD8: =IF(U8="","",LEN(U8)-LEN(SUBSTITUTE(U8,",",""))+1) -> 4 | AE8: =ROUND((COUNTIF(J8,"<>") + COUNTIF(K8,"<>") + COUNTIF(L8,"<>") + COUNTIF(M8,"<>") + COUNTIF(N8,"<>") + COUNTIF(O8,"<>") + COUNTIF(P8,"<>") + COUNTIF(Q8,"<>") + COUNTIF(R8,"<>") + COUNTIF(S8,"<>") + COUNTIF(T8,"<>") + COUNTIF(U8,"<>") + COUNTIF(V8,"<>") + COUNTIF(W8,"<>") + COUNTIF(X8,"<>") + COUNTIF(Y8,"<>") + COUNTIF(Z8,"<>"))/17,3) -> 0.647 | AF8: =COUNTBLANK(M8:Q8)+IF(OR(T8="",T8="----"),1,0)+IF(U8="",1,0) -> 5 | AG8: =IF(AF8=0,"Completo",IF(AF8<=2,"Parcial","Crítico")) -> Crítico
A9: 5 | B9: PR-SS-CON | C9: Sensibilización y Seguimiento a Contratistas y Trabajadores | D9: v05 | E9: Vigente | F9: GESTIÓN DE EMPRESAS CONTRATISTAS | G9: v00 | H9: 45812 | I9: 1 | J9: Auditar de forma trimestral a empresas contratistas del componente Forestal e Industrial (si aplica) en materia de sustentabilidad social considerando las normativas nacionales e internacionales adoptadas por Paracel, en el marco del respeto de los derechos de los pueblos indígenas y comunidades rur | K9: 1. Selección de empresas contratistas a ser auditadas (el número de empresas puede aumentar dependiendo de los hallazgos de No Conformidades). 2. Desarrollo de las auditorías trimestrales. 3. Acompañamiento mensual para la revisión de los planes de acciones correctivas para el cierre de los hallazgo | L9: - Número de empresas auditadas. - Proporción de empresas auditadas con relación al número total de empresas. - Número total de hallazgos. - Número total de observaciones y oportunidades de mejora. - Porcentaje de cierre de los hallazgos y de manera general. - Porcentaje de cumplimiento de plazos de cierre de los hallazgos y de manera general. - Cantidad de acompañamientos. | R9: Informes de Auditoría Manual de Buenas Prácticas de Manufactura. | S9: - Cumplimiento de las normativas nacionales e internaciones. - Respeto en la vinculación con comunidades indígenas y rurales. | T9: ---- | U9: Ene, Feb, Mar, Abr, May, Jun, Jul, Ago, Sep, Oct, Nov, Dic | V9: Acompañar y monitorear a [empresas contratistas y trabajadores/as] para asegurar el cumplimiento de las normativas nacionales y [estándares de sostenibilidad internacionales en materia social]. Monito | W9: Incumplimiento de normativas nacionales e estándares internacionales, y de los requisitos establecidos por Paracel a las empresas proveedoras por falta de conocimineto y experiencia por parte de empre | X9: Acompañar y monitorear a [empresas contratistas y trabajadores/as] para asegurar el cumplimiento de las normativas nacionales y [estándares de sostenibilidad internacionales en materia social]. Monito | Y9: [Este programa tiene el siguiente alcance]: DEFINICIONES Área de Influencia Directa (AID) del componente forestal: incluye a [6] distritos en los que se localizan las áreas de las plantaciones foresta | AA9: =B9&"-T"&TEXT(I9,"00") -> PR-SS-CON-T01 | AB9: =IF(H9="","",VALUE(LEFT(TEXT(H9,"yyyy-mm-dd"),4))) -> 2025 | AC9: 0 | AD9: =IF(U9="","",LEN(U9)-LEN(SUBSTITUTE(U9,",",""))+1) -> 12 | AE9: =ROUND((COUNTIF(J9,"<>") + COUNTIF(K9,"<>") + COUNTIF(L9,"<>") + COUNTIF(M9,"<>") + COUNTIF(N9,"<>") + COUNTIF(O9,"<>") + COUNTIF(P9,"<>") + COUNTIF(Q9,"<>") + COUNTIF(R9,"<>") + COUNTIF(S9,"<>") + COUNTIF(T9,"<>") + COUNTIF(U9,"<>") + COUNTIF(V9,"<>") + COUNTIF(W9,"<>") + COUNTIF(X9,"<>") + COUNTIF(Y9,"<>") + COUNTIF(Z9,"<>"))/17,3) -> 0.647 | AF9: =COUNTBLANK(M9:Q9)+IF(OR(T9="",T9="----"),1,0)+IF(U9="",1,0) -> 6 | AG9: =IF(AF9=0,"Completo",IF(AF9<=2,"Parcial","Crítico")) -> Crítico
A10: 6 | B10: PR-SS-CON | C10: Sensibilización y Seguimiento a Contratistas y Trabajadores | D10: v05 | E10: Vigente | F10: GESTIÓN DE EMPRESAS CONTRATISTAS | G10: v00 | H10: 45812 | I10: 2 | J10: Sensibilizar al 100% de las empresas contratistas del componente forestal e industrial [(si aplica)] en temas relacionados [a las normas nacionales, estándares internacionales y procesos documentales adoptados de Paracel]. | K10: 1. Desarrollar un plan de capacitación para las áreas administrativas de las empresas contratistas, sobre principios establecidos en los estándares y procesos documentales adoptados por Paracel. 2. Implementar las capacitaciones conforme al plan de capacitación. 3. Identificar en campo, situacion | L10: - Número de personas participantes clasificados por organización, cargo, rango etario, sexo, comunidad, etnia. - Número de horas de capacitación. - Número de temas desarrollados. - Datos sobre conocimiento del tema antes de iniciar los talleres y conocimientos adquiridos posterior a los talleres. - Porcentaje de participación con relación al número total de empresas y trabajadores/as. - Porcentaje de uso del presupuesto de manera mensual. | R10: Plan de Capacitación Capacitaciones | S10: Empresas más sensibilizadas y con conocimiento. | U10: Mar, Jun, Jul, Ago, Sep, Nov, Dic | V10: Acompañar y monitorear a [empresas contratistas y trabajadores/as] para asegurar el cumplimiento de las normativas nacionales y [estándares de sostenibilidad internacionales en materia social]. Monito | W10: Incumplimiento de normativas nacionales e estándares internacionales, y de los requisitos establecidos por Paracel a las empresas proveedoras por falta de conocimineto y experiencia por parte de empre | X10: Acompañar y monitorear a [empresas contratistas y trabajadores/as] para asegurar el cumplimiento de las normativas nacionales y [estándares de sostenibilidad internacionales en materia social]. Monito | Y10: [Este programa tiene el siguiente alcance]: DEFINICIONES Área de Influencia Directa (AID) del componente forestal: incluye a [6] distritos en los que se localizan las áreas de las plantaciones foresta | AA10: =B10&"-T"&TEXT(I10,"00") -> PR-SS-CON-T02 | AB10: =IF(H10="","",VALUE(LEFT(TEXT(H10,"yyyy-mm-dd"),4))) -> 2025 | AC10: 0 | AD10: =IF(U10="","",LEN(U10)-LEN(SUBSTITUTE(U10,",",""))+1) -> 7 | AE10: =ROUND((COUNTIF(J10,"<>") + COUNTIF(K10,"<>") + COUNTIF(L10,"<>") + COUNTIF(M10,"<>") + COUNTIF(N10,"<>") + COUNTIF(O10,"<>") + COUNTIF(P10,"<>") + COUNTIF(Q10,"<>") + COUNTIF(R10,"<>") + COUNTIF(S10,"<>") + COUNTIF(T10,"<>") + COUNTIF(U10,"<>") + COUNTIF(V10,"<>") + COUNTIF(W10,"<>") + COUNTIF(X10,"<>") + COUNTIF(Y10,"<>") + COUNTIF(Z10,"<>"))/17,3) -> 0.588 | AF10: =COUNTBLANK(M10:Q10)+IF(OR(T10="",T10="----"),1,0)+IF(U10="",1,0) -> 6 | AG10: =IF(AF10=0,"Completo",IF(AF10<=2,"Parcial","Crítico")) -> Crítico
A11: 7 | B11: PR-SS-SSC | C11: Salud y Seguridad Comunitaria | D11: v06 | E11: Vigente | F11: SALUD Y SEGURIDAD COMUNITARIA | G11: v01 | H11: 45812 | I11: 1 | J11: Posibilitar la asistencia médica a aproximadamente 1.500 personas de comunidades del área de influencia de Paracel reduciendo la brecha de acceso a los programas y servicios nacionales de salud en el período 2025. | K11: 1.Lograr una vinculación cercana con las Unidades de Salud Familiar y los Centros de Salud del ADA y AID y con el Ministerio de Salud Pública y Bienestar Social, [a través de las regionales de salud de Concepción y Amambay]. 2.Selección de las comunidades a ser beneficiadas con las asistencias médic | L11: - Número de alianzas firmadas. - Número de personas que participaron de las asistencia desagregadas por sexo, edad, etnia, comunidad, etc. - Número de USF intervenidas. - Número de especialidades médicas por asistencia. - Número de personas vinculadas al programa externas a Paracel (por actividad). - Monto de inversión directa o indirecta por parte de las organizaciones aliadas (por actividad). - Porcentaje de uso del presupuesto mensual. | R11: 1. Convenios 2. Informe de línea de base. 3. Registros de servicios. 4. Informe final. | S11: 1.500 personas asistidas | T11: . 16.585 | U11: Ene, Feb, Mar, Abr, May, Jun, Jul, Ago, Sep, Oct, Nov, Dic | V11: Implementar un programa eficiente para promover el cuidado de la higiene, la seguridad y la salud de la población con énfasis en la prevención de enfermedades que pudieran relacionarse con el aumento | W11: Poco acceso a servicios de salud por parte de los miembros de las comunidades y falta de conocimiento sobre planificación familiar y ETS. | X11: Implementar un programa eficiente para promover el cuidado de la higiene, la seguridad y la salud de la población con énfasis en la prevención de enfermedades que pudieran relacionarse con el aumento | Y11: El programa de Salud y Seguridad Comunitaria tiene el siguiente alcance: DEFINICIONES Área de Influencia Directa (AID) del componente industrial: incluyen 5 distritos cercanos al sitio de la Planta In | AA11: =B11&"-T"&TEXT(I11,"00") -> PR-SS-SSC-T01 | AB11: =IF(H11="","",VALUE(LEFT(TEXT(H11,"yyyy-mm-dd"),4))) -> 2025 | AC11: 16585 | AD11: =IF(U11="","",LEN(U11)-LEN(SUBSTITUTE(U11,",",""))+1) -> 12 | AE11: =ROUND((COUNTIF(J11,"<>") + COUNTIF(K11,"<>") + COUNTIF(L11,"<>") + COUNTIF(M11,"<>") + COUNTIF(N11,"<>") + COUNTIF(O11,"<>") + COUNTIF(P11,"<>") + COUNTIF(Q11,"<>") + COUNTIF(R11,"<>") + COUNTIF(S11,"<>") + COUNTIF(T11,"<>") + COUNTIF(U11,"<>") + COUNTIF(V11,"<>") + COUNTIF(W11,"<>") + COUNTIF(X11,"<>") + COUNTIF(Y11,"<>") + COUNTIF(Z11,"<>"))/17,3) -> 0.647 | AF11: =COUNTBLANK(M11:Q11)+IF(OR(T11="",T11="----"),1,0)+IF(U11="",1,0) -> 5 | AG11: =IF(AF11=0,"Completo",IF(AF11<=2,"Parcial","Crítico")) -> Crítico
A12: 8 | B12: PR-SS-SSC | C12: Salud y Seguridad Comunitaria | D12: v06 | E12: Vigente | F12: SALUD Y SEGURIDAD COMUNITARIA | G12: v01 | H12: 45812 | I12: 2 | J12: Distribuir 10.000 kilos de leche del Programa Alimentario Nutricional Integral (PANI) con un alcance de 5.000 personas en el período 2025. | K12: 1. Generar alianzas con la Primera Región Sanitaria. 2. Seleccionar las USF a ser intervenidas (PANI). 3. Distribución y entrega de las leches en las USF seleccionadas. 4. Selección de las USF a ser intervenidas (PAI). 5. Jornadas de inmunización en comunidades de la zona de influencia de Paracel. | L12: - Número de alianzas firmadas. - Número de personas alcanzadas en la distribución de leche desagregadas por sexo, edad, etnia, comunidad, etc. - Número de personas alcanzadas en jornadas de inmunización. - Número de USF intervenidas. - Número de personas vinculadas al programa externas a Paracel (por actividad). - Monto de inversión directa o indirecta por parte de las organizaciones aliadas (por actividad). - Porcentaje de uso del presupuesto mensual. | R12: 1. Convenios 2. Informe de línea de base. 3. Registros de servicios. 4. Informe final. | S12: 5.000 personas beneficiadas. | T12: 11.155 = 6.494 + 4.661 | U12: Ene, Feb, Mar, Abr, May, Jun, Jul, Ago, Sep, Oct, Nov, Dic | V12: Implementar un programa eficiente para promover el cuidado de la higiene, la seguridad y la salud de la población con énfasis en la prevención de enfermedades que pudieran relacionarse con el aumento | W12: Poco acceso a servicios de salud por parte de los miembros de las comunidades y falta de conocimiento sobre planificación familiar y ETS. | X12: Implementar un programa eficiente para promover el cuidado de la higiene, la seguridad y la salud de la población con énfasis en la prevención de enfermedades que pudieran relacionarse con el aumento | Y12: El programa de Salud y Seguridad Comunitaria tiene el siguiente alcance: DEFINICIONES Área de Influencia Directa (AID) del componente industrial: incluyen 5 distritos cercanos al sitio de la Planta In | AA12: =B12&"-T"&TEXT(I12,"00") -> PR-SS-SSC-T02 | AB12: =IF(H12="","",VALUE(LEFT(TEXT(H12,"yyyy-mm-dd"),4))) -> 2025 | AC12: 11155 | AD12: =IF(U12="","",LEN(U12)-LEN(SUBSTITUTE(U12,",",""))+1) -> 12 | AE12: =ROUND((COUNTIF(J12,"<>") + COUNTIF(K12,"<>") + COUNTIF(L12,"<>") + COUNTIF(M12,"<>") + COUNTIF(N12,"<>") + COUNTIF(O12,"<>") + COUNTIF(P12,"<>") + COUNTIF(Q12,"<>") + COUNTIF(R12,"<>") + COUNTIF(S12,"<>") + COUNTIF(T12,"<>") + COUNTIF(U12,"<>") + COUNTIF(V12,"<>") + COUNTIF(W12,"<>") + COUNTIF(X12,"<>") + COUNTIF(Y12,"<>") + COUNTIF(Z12,"<>"))/17,3) -> 0.647 | AF12: =COUNTBLANK(M12:Q12)+IF(OR(T12="",T12="----"),1,0)+IF(U12="",1,0) -> 5 | AG12: =IF(AF12=0,"Completo",IF(AF12<=2,"Parcial","Crítico")) -> Crítico
A13: 9 | B13: PR-SS-SSC | C13: Salud y Seguridad Comunitaria | D13: v06 | E13: Vigente | F13: SALUD Y SEGURIDAD COMUNITARIA | G13: v01 | H13: 45812 | I13: 3 | J13: Sensibilizar a miembros de las comunidades de la zona de influencia de Paracel sobre educación sexual, planificación familiar y prevención de VIH/SIDA, a través de talleres, entrega de insumos, la aplicación de las pruebas de detección de VIH y la vinculación con el sistema de salud local. | K13: 1. Generar alianzas con la Cruz Roja Paraguaya, la Primera Región Sanitaria y el PRONASIDA. 2. Desarrollar capacitaciones / talleres sobre salud sexual y reproductiva, incluidos los de planificación familiar. Ayudar a tomar conciencia acerca de enfermedades y su prevención, por ejemplo, según las ci | L13: - Número de alianzas generadas. - Número comunidades abordadas. - Número de personas beneficiadas desagregadas por sexo, edad, etnia, comunidad, etc. - Número de personas vinculadas al programa externas a Paracel (por actividad). - Monto de inversión directa o indirecta por parte de las organizaciones aliadas (por actividad). - Porcentaje de uso del presupuesto mensual. - Número de testeos realizados. - Número de colaboradores/as de empresas contratistas abordados/as. | R13: 1. Convenio 2. Sistematización de los talleres (materiales, contenido, etc.). 3. Informe final. | S13: Comunidades sensibilizadas en temas relacionados a Prevención de VIH|SIDA, Planificación Familiar y testeos. | T13: . 10.649 | U13: Mar, Abr, May, Jun, Jul, Ago, Sep, Oct, Nov, Dic | V13: Implementar un programa eficiente para promover el cuidado de la higiene, la seguridad y la salud de la población con énfasis en la prevención de enfermedades que pudieran relacionarse con el aumento | W13: Poco acceso a servicios de salud por parte de los miembros de las comunidades y falta de conocimiento sobre planificación familiar y ETS. | X13: Implementar un programa eficiente para promover el cuidado de la higiene, la seguridad y la salud de la población con énfasis en la prevención de enfermedades que pudieran relacionarse con el aumento | Y13: El programa de Salud y Seguridad Comunitaria tiene el siguiente alcance: DEFINICIONES Área de Influencia Directa (AID) del componente industrial: incluyen 5 distritos cercanos al sitio de la Planta In | AA13: =B13&"-T"&TEXT(I13,"00") -> PR-SS-SSC-T03 | AB13: =IF(H13="","",VALUE(LEFT(TEXT(H13,"yyyy-mm-dd"),4))) -> 2025 | AC13: 10649 | AD13: =IF(U13="","",LEN(U13)-LEN(SUBSTITUTE(U13,",",""))+1) -> 10 | AE13: =ROUND((COUNTIF(J13,"<>") + COUNTIF(K13,"<>") + COUNTIF(L13,"<>") + COUNTIF(M13,"<>") + COUNTIF(N13,"<>") + COUNTIF(O13,"<>") + COUNTIF(P13,"<>") + COUNTIF(Q13,"<>") + COUNTIF(R13,"<>") + COUNTIF(S13,"<>") + COUNTIF(T13,"<>") + COUNTIF(U13,"<>") + COUNTIF(V13,"<>") + COUNTIF(W13,"<>") + COUNTIF(X13,"<>") + COUNTIF(Y13,"<>") + COUNTIF(Z13,"<>"))/17,3) -> 0.647 | AF13: =COUNTBLANK(M13:Q13)+IF(OR(T13="",T13="----"),1,0)+IF(U13="",1,0) -> 5 | AG13: =IF(AF13=0,"Completo",IF(AF13<=2,"Parcial","Crítico")) -> Crítico
A14: 10 | B14: PR-SS-SSC | C14: Salud y Seguridad Comunitaria | D14: v06 | E14: Vigente | F14: SALUD Y SEGURIDAD COMUNITARIA | G14: v01 | H14: 45812 | I14: 4 | J14: Apoyar al Ministerio de la Niñez y Adolescencia en la prevención de la violencia hacia la niñez y la adolescencia, en las comunidades del área de influencia de Paracel. | K14: 1. Planificar las acciones considerando el marco de cooperación | selección de las comunidades. 2. Implementación de las actividades planificadas. | L14: - Número de personas formadas como facilitadoras. - Número de instituciones representadas. - Número de personas alcanzadas en espacios de sensibilización clasificadas por edad y sexo. - Número de materiales entregados. | R14: Informe final. | S14: Personas formadas y sensibilizadas en prevencion de violencia hacia niñez y la adolescencia. | T14: . 30.000 | U14: Mar, Abr, May, Jun, Jul, Ago, Sep, Oct, Nov | V14: Implementar un programa eficiente para promover el cuidado de la higiene, la seguridad y la salud de la población con énfasis en la prevención de enfermedades que pudieran relacionarse con el aumento | W14: Poco acceso a servicios de salud por parte de los miembros de las comunidades y falta de conocimiento sobre planificación familiar y ETS. | X14: Implementar un programa eficiente para promover el cuidado de la higiene, la seguridad y la salud de la población con énfasis en la prevención de enfermedades que pudieran relacionarse con el aumento | Y14: El programa de Salud y Seguridad Comunitaria tiene el siguiente alcance: DEFINICIONES Área de Influencia Directa (AID) del componente industrial: incluyen 5 distritos cercanos al sitio de la Planta In | AA14: =B14&"-T"&TEXT(I14,"00") -> PR-SS-SSC-T04 | AB14: =IF(H14="","",VALUE(LEFT(TEXT(H14,"yyyy-mm-dd"),4))) -> 2025 | AC14: 30000 | AD14: =IF(U14="","",LEN(U14)-LEN(SUBSTITUTE(U14,",",""))+1) -> 9 | AE14: =ROUND((COUNTIF(J14,"<>") + COUNTIF(K14,"<>") + COUNTIF(L14,"<>") + COUNTIF(M14,"<>") + COUNTIF(N14,"<>") + COUNTIF(O14,"<>") + COUNTIF(P14,"<>") + COUNTIF(Q14,"<>") + COUNTIF(R14,"<>") + COUNTIF(S14,"<>") + COUNTIF(T14,"<>") + COUNTIF(U14,"<>") + COUNTIF(V14,"<>") + COUNTIF(W14,"<>") + COUNTIF(X14,"<>") + COUNTIF(Y14,"<>") + COUNTIF(Z14,"<>"))/17,3) -> 0.647 | AF14: =COUNTBLANK(M14:Q14)+IF(OR(T14="",T14="----"),1,0)+IF(U14="",1,0) -> 5 | AG14: =IF(AF14=0,"Completo",IF(AF14<=2,"Parcial","Crítico")) -> Crítico
A15: 11 | B15: PR-SS-MSC | C15: Manejo Social | D15: v05 | E15: Vigente | F15: MANEJO SOCIAL | G15: v01 | H15: 45813 | I15: 1 | J15: Realizar espacios informativos en el año, en las comunidades del área de influencia directa de Paracel. | K15: 1. Reuniones semestrales con pobladores del ADA, AID y con las comunidades indígena para transferir información sobre Paracel, acompañar y monitorear la percepción de los mismos con relación a Paracel. 2. Toma de datos acerca de la percepción de las personas y datos sobre migración. | L15: 1. Número de personas participantes por comunidad clasificadas, por edad, sexo, franja etaria, comunidad, etnia. 2. Índice de percepción. 3. Datos sobre migración 4. Materiales desarrollados. 5. Número de personas de las diferentes áreas de Paracel participantes. | R15: - Informe de percepción. - Materiales informativos | educativos desarrollados. | S15: - Miembros de las comunidades informados. - Mejora continua en nuestros procesos con relación a expectativas de los miembros de las comunidades. | T15: 8.442 | U15: Jul, Nov | V15: Identificar las afectaciones generadas por la empresa, buscando minimizarlas, con foco en las comunidades del área de influencia de Paracel. | W15: Contar con información sobre la percepción y expectativas de los miembros de las comunidades con relación a desempeño de Paracel, a fin de establacer acciones de mejora. | X15: Identificar las afectaciones generadas por la empresa, buscando minimizarlas, con foco en las comunidades del área de influencia de Paracel. | [FSC-STD-PRY-01-2022] Normas de Desempeño IFC REGISTROS Y | Y15: El programa de Manejo Social tiene el siguiente alcance: DEFINICIONES Área Directamente Afectada (ADA) del componente industrial: unidades sociales y comunidades situadas en el entorno inmediato de la | AA15: =B15&"-T"&TEXT(I15,"00") -> PR-SS-MSC-T01 | AB15: =IF(H15="","",VALUE(LEFT(TEXT(H15,"yyyy-mm-dd"),4))) -> 2025 | AC15: 8442 | AD15: =IF(U15="","",LEN(U15)-LEN(SUBSTITUTE(U15,",",""))+1) -> 2 | AE15: =ROUND((COUNTIF(J15,"<>") + COUNTIF(K15,"<>") + COUNTIF(L15,"<>") + COUNTIF(M15,"<>") + COUNTIF(N15,"<>") + COUNTIF(O15,"<>") + COUNTIF(P15,"<>") + COUNTIF(Q15,"<>") + COUNTIF(R15,"<>") + COUNTIF(S15,"<>") + COUNTIF(T15,"<>") + COUNTIF(U15,"<>") + COUNTIF(V15,"<>") + COUNTIF(W15,"<>") + COUNTIF(X15,"<>") + COUNTIF(Y15,"<>") + COUNTIF(Z15,"<>"))/17,3) -> 0.647 | AF15: =COUNTBLANK(M15:Q15)+IF(OR(T15="",T15="----"),1,0)+IF(U15="",1,0) -> 5 | AG15: =IF(AF15=0,"Completo",IF(AF15<=2,"Parcial","Crítico")) -> Crítico
A16: 12 | B16: PR-SS-MSC | C16: Manejo Social | D16: v05 | E16: Vigente | F16: MANEJO SOCIAL | G16: v01 | H16: 45813 | I16: 2 | J16: Alinear expectativas de miembros de las comunidades y otros grupos de interés acerca del funcionamiento de Paracel e inversiones sociales. | K16: 1. Reuniones semestrales con los líderes y lideresas de las comunidades rurales e indígenas del área de influencia de Paracel, para la socialización y actualización de las actividades desarrolladas en el marco de los programas sociales de la empresa. 2. Alinear expectativas de líderes y líderesas d | L16: 1. Número de personas participantes por comunidad clasificadas, por edad, sexo, franja etaria, comunidad, etnia. 2. Índice de percepción. 3. Materiales desarrollados. 4. Número de personas de las diferentes áreas de Paracel participantes. | R16: - Informe de percepción. - Materiales informativos | educativos desarrollados. | S16: - Líderes y lideresas de las comunidades informados/as. - Mejora continua en nuestros procesos con relación a expectativas de los miembros de las comunidades. | T16: 6.044 | U16: Jul, Nov | V16: Identificar las afectaciones generadas por la empresa, buscando minimizarlas, con foco en las comunidades del área de influencia de Paracel. | W16: Contar con información sobre la percepción y expectativas de los miembros de las comunidades con relación a desempeño de Paracel, a fin de establacer acciones de mejora. | X16: Identificar las afectaciones generadas por la empresa, buscando minimizarlas, con foco en las comunidades del área de influencia de Paracel. | [FSC-STD-PRY-01-2022] Normas de Desempeño IFC REGISTROS Y | Y16: El programa de Manejo Social tiene el siguiente alcance: DEFINICIONES Área Directamente Afectada (ADA) del componente industrial: unidades sociales y comunidades situadas en el entorno inmediato de la | AA16: =B16&"-T"&TEXT(I16,"00") -> PR-SS-MSC-T02 | AB16: =IF(H16="","",VALUE(LEFT(TEXT(H16,"yyyy-mm-dd"),4))) -> 2025 | AC16: 6044 | AD16: =IF(U16="","",LEN(U16)-LEN(SUBSTITUTE(U16,",",""))+1) -> 2 | AE16: =ROUND((COUNTIF(J16,"<>") + COUNTIF(K16,"<>") + COUNTIF(L16,"<>") + COUNTIF(M16,"<>") + COUNTIF(N16,"<>") + COUNTIF(O16,"<>") + COUNTIF(P16,"<>") + COUNTIF(Q16,"<>") + COUNTIF(R16,"<>") + COUNTIF(S16,"<>") + COUNTIF(T16,"<>") + COUNTIF(U16,"<>") + COUNTIF(V16,"<>") + COUNTIF(W16,"<>") + COUNTIF(X16,"<>") + COUNTIF(Y16,"<>") + COUNTIF(Z16,"<>"))/17,3) -> 0.647 | AF16: =COUNTBLANK(M16:Q16)+IF(OR(T16="",T16="----"),1,0)+IF(U16="",1,0) -> 5 | AG16: =IF(AF16=0,"Completo",IF(AF16<=2,"Parcial","Crítico")) -> Crítico
A17: 13 | B17: PR-SS-PCS | C17: Prevención y Gestión de Contingencias Sociales | D17: v05 | E17: Vigente | F17: PREVENCIÓN CONTINGENCIAS SOCIALES | G17: v01 | H17: 45817 | I17: 1 | J17: Fortalecer la prevención de incendios forestales en 8 comunidades del área de influencia de Paracel mediante acciones de concientización y capacitación. Además, lograr la conformación de una brigada comunitaria. | K17: 1- Contratar a la empresa consultora para el desarrollo de los talleres, y/o generar alianzas. 2- Identificación y selección de comunidades a intervenir con el desarrollo de los espacios de concientización y capacitación de prevención de incendios forestales. 3- Desarrollo de talleres rurales partic | L17: 1. N° de talleres realizados. 2. N° de personas participantes. 3. N° de personas que conforman la brigada. 4. N° de personas entrenadas. 5. N° de reuniones y acuerdos realizados. | R17: - Informe final de actividades. - Materiales informativos - educativos desarrollados. - Informe de datos acerca de conocimientos adquiridos. | S17: - Prevención de incendios forestales. - Mejora en los procesos de respuesta e intervención en casos de incendios forestales. | T17: 5.887 | U17: Jun, Jul, Ago, Sep, Oct | V17: Prevenir y dar una pronta respuesta ante contingencias sociales, tanto en las etapas constructiva y operativa de Paracel en su componente industrial, como en las etapas de instalación, operación y man | W17: Gestionar de forma adecuada las respuestas ante las contingencias sociales que pudieran ser generadas a raíz de las intervenciones operacionales de Paracel con los diferentes grupos de interés. | X17: Prevenir y dar una pronta respuesta ante contingencias sociales, tanto en las etapas constructiva y operativa de Paracel en su componente industrial, como en las etapas de instalación, operación y man | Y17: El programa de Prevención y Gestión de Contingencias Sociales tiene el siguiente alcance: DEFINICIONES Área de Influencia Directa (AID) del componente industrial: incluyen 5 distritos cercanos al siti | AA17: =B17&"-T"&TEXT(I17,"00") -> PR-SS-PCS-T01 | AB17: =IF(H17="","",VALUE(LEFT(TEXT(H17,"yyyy-mm-dd"),4))) -> 2025 | AC17: 5887 | AD17: =IF(U17="","",LEN(U17)-LEN(SUBSTITUTE(U17,",",""))+1) -> 5 | AE17: =ROUND((COUNTIF(J17,"<>") + COUNTIF(K17,"<>") + COUNTIF(L17,"<>") + COUNTIF(M17,"<>") + COUNTIF(N17,"<>") + COUNTIF(O17,"<>") + COUNTIF(P17,"<>") + COUNTIF(Q17,"<>") + COUNTIF(R17,"<>") + COUNTIF(S17,"<>") + COUNTIF(T17,"<>") + COUNTIF(U17,"<>") + COUNTIF(V17,"<>") + COUNTIF(W17,"<>") + COUNTIF(X17,"<>") + COUNTIF(Y17,"<>") + COUNTIF(Z17,"<>"))/17,3) -> 0.647 | AF17: =COUNTBLANK(M17:Q17)+IF(OR(T17="",T17="----"),1,0)+IF(U17="",1,0) -> 5 | AG17: =IF(AF17=0,"Completo",IF(AF17<=2,"Parcial","Crítico")) -> Crítico
A18: 14 | B18: PR-SS-PCS | C18: Prevención y Gestión de Contingencias Sociales | D18: v05 | E18: Vigente | F18: PREVENCIÓN CONTINGENCIAS SOCIALES | G18: v01 | H18: 45817 | I18: 1 | J18: Además, lograr la conformación de una brigada comunitaria. | K18: 1. Selección de organización con experiencia para la conformación de la brigada comunitaria en la comunidad indígena Takuarita. 2. Taller rural participativo para la conformación de brigada comunitaria con la comunidad indígena Takuarita. 3. Desarrollo del entrenamiento de la brigada comunitaria, a | L18: 1. N° de talleres realizados. 2. N° de personas participantes. 3. N° de personas que conforman la brigada. 4. N° de personas entrenadas. 5. N° de reuniones y acuerdos realizados. | R18: - Brigada comunitaria conformada. | S18: - Prevención de incendios forestales y capacidad de respuesta ante situaciones críticas. | T18: 821 | U18: Jun, Jul, Ago, Sep | V18: Prevenir y dar una pronta respuesta ante contingencias sociales, tanto en las etapas constructiva y operativa de Paracel en su componente industrial, como en las etapas de instalación, operación y man | W18: Gestionar de forma adecuada las respuestas ante las contingencias sociales que pudieran ser generadas a raíz de las intervenciones operacionales de Paracel con los diferentes grupos de interés. | X18: Prevenir y dar una pronta respuesta ante contingencias sociales, tanto en las etapas constructiva y operativa de Paracel en su componente industrial, como en las etapas de instalación, operación y man | Y18: El programa de Prevención y Gestión de Contingencias Sociales tiene el siguiente alcance: DEFINICIONES Área de Influencia Directa (AID) del componente industrial: incluyen 5 distritos cercanos al siti | AA18: =B18&"-T"&TEXT(I18,"00") -> PR-SS-PCS-T01 | AB18: =IF(H18="","",VALUE(LEFT(TEXT(H18,"yyyy-mm-dd"),4))) -> 2025 | AC18: 821 | AD18: =IF(U18="","",LEN(U18)-LEN(SUBSTITUTE(U18,",",""))+1) -> 4 | AE18: =ROUND((COUNTIF(J18,"<>") + COUNTIF(K18,"<>") + COUNTIF(L18,"<>") + COUNTIF(M18,"<>") + COUNTIF(N18,"<>") + COUNTIF(O18,"<>") + COUNTIF(P18,"<>") + COUNTIF(Q18,"<>") + COUNTIF(R18,"<>") + COUNTIF(S18,"<>") + COUNTIF(T18,"<>") + COUNTIF(U18,"<>") + COUNTIF(V18,"<>") + COUNTIF(W18,"<>") + COUNTIF(X18,"<>") + COUNTIF(Y18,"<>") + COUNTIF(Z18,"<>"))/17,3) -> 0.647 | AF18: =COUNTBLANK(M18:Q18)+IF(OR(T18="",T18="----"),1,0)+IF(U18="",1,0) -> 5 | AG18: =IF(AF18=0,"Completo",IF(AF18<=2,"Parcial","Crítico")) -> Crítico
A19: 15 | B19: PR-SS-AAE | C19: Manejo Interno por Afectación de Tierras y Riesgos por Agentes Externos | D19: v05 | E19: Vigente | F19: MANEJO INTERNO POR AFECTACIÓN DE TIERRAS Y RIESGO POR AGENTES EXTERNOS | G19: v00 | H19: 45819 | I19: 1 | J19: Contar con acuerdos de servidumbre de paso con el 100% de las estancias vecinas de las propiedades forestales con el fin de garantizar el libre tránsito de los miembros de Paracel y empresas contratistas. | K19: 1.Actualización del mapeo de las propiedades utilizadas como acceso y salida (componente forestal e indígena), [con el área de Seguridad Corporativa para el diseño del corredor de accesos y/o caminos alternativos a ser utilizados por personas externas a Paracel y empresas contratistas. 2. Elaboració | L19: 1- N° de propiedades a ser utilizadas como servidumbre de paso 2- N° de documentos elaborados 3- N° de comunicados elaborados 4- N° de comunicados emitidos 5- N° de reuniones 6- N° de personas participantes 7- N° de acuerdos firmados | R19: Acuerdos de servidumbre de paso. | S19: Granatizar el libre tránsito de los miembros de Paracel y empresas contratistas. | U19: Jun, Jul, Ago, Sep, Oct, Nov, Dic | V19: Prevenir conflictos con terceros (propietarios/as de inmuebles utilizados como servidumbre) y delinear protocolos internos para garantizar la seguridad de las personas que conforman los equipos de Par | W19: Formalizar los acuerdos con propietarios/as de inmuebles vecinos y con miembros de las comunidades en caso de que aplique con relación al uso de caminos. Reducir los riesgos de conflictos. | X19: Prevenir conflictos con terceros ([propietarios/as] de inmuebles utilizados como servidumbre) y delinear protocolos internos para garantizar la seguridad de las personas que conforman los equipos de P | Y19: [El alcance del programa se presenta a continuación]: DEFINICIONES Área de Influencia Directa (AID) del componente forestal: incluye a [6] distritos en los que se localizan las áreas de las plantacion | AA19: =B19&"-T"&TEXT(I19,"00") -> PR-SS-AAE-T01 | AB19: =IF(H19="","",VALUE(LEFT(TEXT(H19,"yyyy-mm-dd"),4))) -> 2025 | AC19: 0 | AD19: =IF(U19="","",LEN(U19)-LEN(SUBSTITUTE(U19,",",""))+1) -> 7 | AE19: =ROUND((COUNTIF(J19,"<>") + COUNTIF(K19,"<>") + COUNTIF(L19,"<>") + COUNTIF(M19,"<>") + COUNTIF(N19,"<>") + COUNTIF(O19,"<>") + COUNTIF(P19,"<>") + COUNTIF(Q19,"<>") + COUNTIF(R19,"<>") + COUNTIF(S19,"<>") + COUNTIF(T19,"<>") + COUNTIF(U19,"<>") + COUNTIF(V19,"<>") + COUNTIF(W19,"<>") + COUNTIF(X19,"<>") + COUNTIF(Y19,"<>") + COUNTIF(Z19,"<>"))/17,3) -> 0.588 | AF19: =COUNTBLANK(M19:Q19)+IF(OR(T19="",T19="----"),1,0)+IF(U19="",1,0) -> 6 | AG19: =IF(AF19=0,"Completo",IF(AF19<=2,"Parcial","Crítico")) -> Crítico
A20: 16 | B20: PR-SS-AAE | C20: Manejo Interno por Afectación de Tierras y Riesgos por Agentes Externos | D20: v05 | E20: Vigente | F20: MANEJO INTERNO POR AFECTACIÓN DE TIERRAS Y RIESGO POR AGENTES EXTERNOS | G20: v00 | H20: 45819 | I20: 2 | J20: Velar porque el 100% de colaboradores/as de empresas proveedoras de servicio de seguridad corporativa se encuentren sensibilizados/as en materia de Derechos Humanos. | K20: 1. Solicitar al área de Compras/Seguridad Corporativa un informe trimestral sobre registros de entrenamiento en temas de Derechos Humanos a colaboradores/as de empresas proveedoras de servicios de seguridad y control de acceso. Paracel resguardará que estas personas no ejerzan “abusos de poder”. 2. | L20: 1- N° de personas trabajando en el área de seguridad y control de acceso (clasificadas, edad, sexo, comunidad, etnia, región, etc.). 2- N° de personas formadas en materia de Derechos Humanos clasificados por edad, sexo, empresa, carga horaria, temas. 3- N° de verificaciones realizadas en campo clasificadas por empresas. 4- N° de hallazgos en las verificaciones de campo. 5- N° de cierre de hallazgos resultantes de las verificaciones en campo. | R20: Informes | S20: Reducir la probabilidad de que existan desvíos en la conducta del equipo de seguridad con relación a temas de Derechos Humanos. | U20: Jun, Sep, Dic | V20: Prevenir conflictos con terceros (propietarios/as de inmuebles utilizados como servidumbre) y delinear protocolos internos para garantizar la seguridad de las personas que conforman los equipos de Par | W20: Formalizar los acuerdos con propietarios/as de inmuebles vecinos y con miembros de las comunidades en caso de que aplique con relación al uso de caminos. Reducir los riesgos de conflictos. | X20: Prevenir conflictos con terceros ([propietarios/as] de inmuebles utilizados como servidumbre) y delinear protocolos internos para garantizar la seguridad de las personas que conforman los equipos de P | Y20: [El alcance del programa se presenta a continuación]: DEFINICIONES Área de Influencia Directa (AID) del componente forestal: incluye a [6] distritos en los que se localizan las áreas de las plantacion | AA20: =B20&"-T"&TEXT(I20,"00") -> PR-SS-AAE-T02 | AB20: =IF(H20="","",VALUE(LEFT(TEXT(H20,"yyyy-mm-dd"),4))) -> 2025 | AC20: 0 | AD20: =IF(U20="","",LEN(U20)-LEN(SUBSTITUTE(U20,",",""))+1) -> 3 | AE20: =ROUND((COUNTIF(J20,"<>") + COUNTIF(K20,"<>") + COUNTIF(L20,"<>") + COUNTIF(M20,"<>") + COUNTIF(N20,"<>") + COUNTIF(O20,"<>") + COUNTIF(P20,"<>") + COUNTIF(Q20,"<>") + COUNTIF(R20,"<>") + COUNTIF(S20,"<>") + COUNTIF(T20,"<>") + COUNTIF(U20,"<>") + COUNTIF(V20,"<>") + COUNTIF(W20,"<>") + COUNTIF(X20,"<>") + COUNTIF(Y20,"<>") + COUNTIF(Z20,"<>"))/17,3) -> 0.588 | AF20: =COUNTBLANK(M20:Q20)+IF(OR(T20="",T20="----"),1,0)+IF(U20="",1,0) -> 6 | AG20: =IF(AF20=0,"Completo",IF(AF20<=2,"Parcial","Crítico")) -> Crítico
A21: 17 | B21: PR-SS-QRI | C21: Gestión de Quejas, Consultas y Sugerencias | D21: v05 | E21: Vigente | F21: GESTIÓN DE QUEJAS, CONSULTAS Y SUGERENCIAS | G21: v01 | H21: 45826 | I21: 1 | J21: El 100% de casos ingresados a través de los diferentes canales establecidos por Paracel atendidos/gestionados. | K21: 1. Funcionamiento del canal externo de atención de quejas. 2. Socializar el procedimiento de gestión de quejas, sugerencias y consultas con todas las partes interesadas de Paracel y los canales correspondientes. 3. Seguimiento y verificación del funcionamiento del sistema de gestión de quejas, suger | L21: - Número de quejas, consultas y sugerencias clasificadas por tipo y origen interno (nómina) y externo (contratistas y comunidad). - Número de actividades/acciones de socialización. - Número de personas alcanzadas en medios digitales en procesos de socialización. - Número de capacitaciones realizadas, número de personas alcanzadas clasificadas por edad, sexo, comunidad, etnia, empresa. - Horas de capacitación. - Número de quejas relacionadas al Código de Ética clasificadas por origen. - Porcentaje de procesos cerrados. - Porcentaje de uso del presupuesto de manera mensual. - Porcentaje de satifacción con el canal (proceso). | R21: - Sistema de gestión de quejas, sugerencias y consultas. - Informe de seguimientiento a las quejas consultas y sugerencias de las comunidades indígenas. | S21: Canalización, atención y direccionamiento, de las quejas, consultas y sugerencias de la población y las comunidades indígenas. | U21: Ene, Feb, Mar, Abr, May, Jun, Jul, Ago, Sep, Oct, Nov, Dic | V21: Garantizar atención a las quejas, sugerencias y consultas de la población de las áreas de influencia de Paracel, colaboradores/as propios/as y de empresas proveedoras, pueblos indígenas y de la poblac | W21: Temores y expectativas generadas en la población y las comunidades indígenas, afectación de la red social y comunitaria, de los servicios ecosistémicos, cambio en la calidad de vida, usos y costumbres | X21: Garantizar atención a las quejas, sugerencias y consultas de la población de las áreas de influencia de Paracel, [colaboradores/as propios/as y de empresas proveedoras], pueblos indígenas y de la pobl | Y21: Este programa es transversal a: DEFINICIONES Área de Influencia Directa (AID) del componente industrial: incluyen 5 distritos cercanos al sitio de la Planta Industrial, incluyendo a 18 comunidades que | AA21: =B21&"-T"&TEXT(I21,"00") -> PR-SS-QRI-T01 | AB21: =IF(H21="","",VALUE(LEFT(TEXT(H21,"yyyy-mm-dd"),4))) -> 2025 | AC21: 0 | AD21: =IF(U21="","",LEN(U21)-LEN(SUBSTITUTE(U21,",",""))+1) -> 12 | AE21: =ROUND((COUNTIF(J21,"<>") + COUNTIF(K21,"<>") + COUNTIF(L21,"<>") + COUNTIF(M21,"<>") + COUNTIF(N21,"<>") + COUNTIF(O21,"<>") + COUNTIF(P21,"<>") + COUNTIF(Q21,"<>") + COUNTIF(R21,"<>") + COUNTIF(S21,"<>") + COUNTIF(T21,"<>") + COUNTIF(U21,"<>") + COUNTIF(V21,"<>") + COUNTIF(W21,"<>") + COUNTIF(X21,"<>") + COUNTIF(Y21,"<>") + COUNTIF(Z21,"<>"))/17,3) -> 0.588 | AF21: =COUNTBLANK(M21:Q21)+IF(OR(T21="",T21="----"),1,0)+IF(U21="",1,0) -> 6 | AG21: =IF(AF21=0,"Completo",IF(AF21<=2,"Parcial","Crítico")) -> Crítico
A22: 18 | B22: PR-SS-QRI | C22: Gestión de Quejas, Consultas y Sugerencias | D22: v05 | E22: Vigente | F22: GESTIÓN DE QUEJAS, CONSULTAS Y SUGERENCIAS | G22: v01 | H22: 45826 | I22: 2 | J22: 100% de los buzones de Quejas, Consultas y Sugerencias ubicados en las comunidades y en las instalaciones de Paracel revisados y gestionados. | K22: 1. Revisión y reubicación de los buzones en las comunidades e instalaciones de Paracel en caso de necesidad. 2. Comunicación de las ubicaciones de los buzones. 3. Monitoreo de los registros recolectados en los buzones (internos cada 15 días y comunitarios mensual). 4. Planificación de visitas del an | L22: - Número de buzones instalados en las comunidades e instalaciones de Paracel. - Número de quejas, consultas y sugerencias recibidas en cada buzón, clasificadas por tipo y zona geográfica. - Número de procesos cerrados. - Número de comunicaciones realizadas para la difusión de los buzones de quejas, consultas y sugerencias. - Porcentaje de satifacción con el canal (proceso). - Número de visitas realizadas. - Número de quejas, consultas, sugerencias registradas. - Número de comunidades visitadas. | R22: - Sistema de gestión de quejas, sugerencias y consultas en funcionamiento. - Informe de seguimientiento a las quejas consultas y sugerencias de las comunidades indígenas. | S22: Canalización, atención y direccionamiento, de las quejas, consultas y sugerencias de la población y las comunidades indígenas. | U22: Ene, Feb, Mar, Abr, May, Jun, Jul, Ago, Sep, Oct, Nov, Dic | V22: Garantizar atención a las quejas, sugerencias y consultas de la población de las áreas de influencia de Paracel, colaboradores/as propios/as y de empresas proveedoras, pueblos indígenas y de la poblac | W22: Temores y expectativas generadas en la población y las comunidades indígenas, afectación de la red social y comunitaria, de los servicios ecosistémicos, cambio en la calidad de vida, usos y costumbres | X22: Garantizar atención a las quejas, sugerencias y consultas de la población de las áreas de influencia de Paracel, [colaboradores/as propios/as y de empresas proveedoras], pueblos indígenas y de la pobl | Y22: Este programa es transversal a: DEFINICIONES Área de Influencia Directa (AID) del componente industrial: incluyen 5 distritos cercanos al sitio de la Planta Industrial, incluyendo a 18 comunidades que | AA22: =B22&"-T"&TEXT(I22,"00") -> PR-SS-QRI-T02 | AB22: =IF(H22="","",VALUE(LEFT(TEXT(H22,"yyyy-mm-dd"),4))) -> 2025 | AC22: 0 | AD22: =IF(U22="","",LEN(U22)-LEN(SUBSTITUTE(U22,",",""))+1) -> 12 | AE22: =ROUND((COUNTIF(J22,"<>") + COUNTIF(K22,"<>") + COUNTIF(L22,"<>") + COUNTIF(M22,"<>") + COUNTIF(N22,"<>") + COUNTIF(O22,"<>") + COUNTIF(P22,"<>") + COUNTIF(Q22,"<>") + COUNTIF(R22,"<>") + COUNTIF(S22,"<>") + COUNTIF(T22,"<>") + COUNTIF(U22,"<>") + COUNTIF(V22,"<>") + COUNTIF(W22,"<>") + COUNTIF(X22,"<>") + COUNTIF(Y22,"<>") + COUNTIF(Z22,"<>"))/17,3) -> 0.588 | AF22: =COUNTBLANK(M22:Q22)+IF(OR(T22="",T22="----"),1,0)+IF(U22="",1,0) -> 6 | AG22: =IF(AF22=0,"Completo",IF(AF22<=2,"Parcial","Crítico")) -> Crítico
A23: 19 | B23: PR-SS-PCU | C23: Gestión del Patrimonio Cultural | D23: v05 | E23: Vigente | F23: PATRIMONIO CULTURAL | G23: v01 | H23: 45826 | I23: 1 | J23: Monitoreo de la aplicación del Protocolo de Hallazgos Fortuitos por parte de empresas contratistas de Paracel | K23: 1.Seguimiento en campo de la aplicación del protocolo de hallazgos fortuitos, por parte de las empresas contratistas. 2.Registro y monitoreo de socialización del contenido del Protocolo de Hallazgos Fortuitos. | L23: N.º de visitas de monitoreo realizadas en campo. N.º de empresas contratistas alcanzadas. N.º de colaboradores/as alcanzados/as. N.º de personas referentes identificadas y registradas para el reporte de hallazgos. N.º de reportes de hallazgos generados. | R23: 1. Registros de monitoreo en campo sobre la aplicación del protocolo. 2. Informe de cumplimiento y avances en la implementación del protocolo | S23: Aplicación efectiva del Protocolo de Hallazgos Fortuitos por parte de empresas contratistas. | T23: ---- | U23: Jun, Ago, Oct, Dic | V23: Velar por la gestión adecuada del Patrimonio Cultural de las Áreas de Influencia Directa de Paracel. | W23: Desconocimiento y falta de comunicación en la comunidad de la zona de influencia de Paracel, sobre el significado e implicancias del Patrimonio Cultural, sus posibles pérdidas y/o daños. | X23: Velar por la gestión adecuada del Patrimonio Cultural de las áreas de Influencia Directa de Paracel. | [FSC-STD-PRY-01-2022] Normas de Desempeño IFC REGISTROS Y/O ANEXO [Minuta de reunión] [Informe de | Y23: El programa de tiene el siguiente alcance: DEFINICIONES Área de Influencia Directa (AID) del componente industrial: incluyen 5 distritos cercanos al sitio de la Planta Industrial, incluyendo a 18 comu | AA23: =B23&"-T"&TEXT(I23,"00") -> PR-SS-PCU-T01 | AB23: =IF(H23="","",VALUE(LEFT(TEXT(H23,"yyyy-mm-dd"),4))) -> 2025 | AC23: 0 | AD23: =IF(U23="","",LEN(U23)-LEN(SUBSTITUTE(U23,",",""))+1) -> 4 | AE23: =ROUND((COUNTIF(J23,"<>") + COUNTIF(K23,"<>") + COUNTIF(L23,"<>") + COUNTIF(M23,"<>") + COUNTIF(N23,"<>") + COUNTIF(O23,"<>") + COUNTIF(P23,"<>") + COUNTIF(Q23,"<>") + COUNTIF(R23,"<>") + COUNTIF(S23,"<>") + COUNTIF(T23,"<>") + COUNTIF(U23,"<>") + COUNTIF(V23,"<>") + COUNTIF(W23,"<>") + COUNTIF(X23,"<>") + COUNTIF(Y23,"<>") + COUNTIF(Z23,"<>"))/17,3) -> 0.647 | AF23: =COUNTBLANK(M23:Q23)+IF(OR(T23="",T23="----"),1,0)+IF(U23="",1,0) -> 6 | AG23: =IF(AF23=0,"Completo",IF(AF23<=2,"Parcial","Crítico")) -> Crítico
A24: 20 | B24: PR-SS-PCU | C24: Gestión del Patrimonio Cultural | D24: v05 | E24: Vigente | F24: PATRIMONIO CULTURAL | G24: v01 | H24: 45826 | I24: 2 | J24: Lograr el rescate, promoción y comercialización de artesanías de la comunidad indígena Redención | K24: 1. Creación de un catálogo de las artesanías de la comunidad indígena. 2. Soporte logístico para obtención de materia prima para la elaboración de los productos artesanales. 3. Identificación de puntos de venta y generación de alianzas para la comercialización de productos artesanales. 4. Participac | L24: N.º de ferias y/o exposiciones en las que se participó N.º de emprendedores/as participantes por evento Volumen de ventas alcanzado por feria/exposición N.º de catálogos de artesanías creados y distribuidos N.º de productos artesanales incluidos en el catálogo N.º de asistencias logísticas brindadas para traslado de materia prima Costo logístico total asumido N.º de puntos de venta identificados y/o habilitados | R24: 1.Catálogo artesanal elaborado. 2.Participación en ferias y exposiciones. 3.Puntos de ventas identificados. 4.Informe final de actividades realizadas | S24: Rescate, promoción y fortalecimiento de la comercialización de artesanías de la comunidad indígena Redención, incrementando su visibilidad y acceso a mercados. | T24: ---- | U24: Jun, Jul, Ago, Sep, Oct, Nov, Dic | V24: Velar por la gestión adecuada del Patrimonio Cultural de las Áreas de Influencia Directa de Paracel. | W24: Desconocimiento y falta de comunicación en la comunidad de la zona de influencia de Paracel, sobre el significado e implicancias del Patrimonio Cultural, sus posibles pérdidas y/o daños. | X24: Velar por la gestión adecuada del Patrimonio Cultural de las áreas de Influencia Directa de Paracel. | [FSC-STD-PRY-01-2022] Normas de Desempeño IFC REGISTROS Y/O ANEXO [Minuta de reunión] [Informe de | Y24: El programa de tiene el siguiente alcance: DEFINICIONES Área de Influencia Directa (AID) del componente industrial: incluyen 5 distritos cercanos al sitio de la Planta Industrial, incluyendo a 18 comu | AA24: =B24&"-T"&TEXT(I24,"00") -> PR-SS-PCU-T02 | AB24: =IF(H24="","",VALUE(LEFT(TEXT(H24,"yyyy-mm-dd"),4))) -> 2025 | AC24: 0 | AD24: =IF(U24="","",LEN(U24)-LEN(SUBSTITUTE(U24,",",""))+1) -> 7 | AE24: =ROUND((COUNTIF(J24,"<>") + COUNTIF(K24,"<>") + COUNTIF(L24,"<>") + COUNTIF(M24,"<>") + COUNTIF(N24,"<>") + COUNTIF(O24,"<>") + COUNTIF(P24,"<>") + COUNTIF(Q24,"<>") + COUNTIF(R24,"<>") + COUNTIF(S24,"<>") + COUNTIF(T24,"<>") + COUNTIF(U24,"<>") + COUNTIF(V24,"<>") + COUNTIF(W24,"<>") + COUNTIF(X24,"<>") + COUNTIF(Y24,"<>") + COUNTIF(Z24,"<>"))/17,3) -> 0.647 | AF24: =COUNTBLANK(M24:Q24)+IF(OR(T24="",T24="----"),1,0)+IF(U24="",1,0) -> 6 | AG24: =IF(AF24=0,"Completo",IF(AF24<=2,"Parcial","Crítico")) -> Crítico
A25: 21 | B25: PR-SS-RCI | C25: Relacionamiento con Comunidades e Inversión Social | D25: v05 | E25: Vigente | F25: INFRAESTRUCTURA SOCIAL | G25: v01 | H25: 45830 | I25: 2 | J25: Mejorar la infraestructura en comunidades rurales e indígenas del Área de Influencia de Paracel a través de intervenciones con foco en: A - Sistemas de acceso y distribución de agua. B -Mejoramiento de los sistemas de accesos y/o distribución de energía eléctrica. | K25: 1. Seleccionar a las comunidades beneficiarias según críterios de elegibilidad. 2. Firma de cartas de compromiso con todas las comunidades seleccionadas (beneficiarias). 3. Toma de datos para establecimiento de la línea de base (comunitaria). 4. Toma de datos para establecimiento de percepción comun | L25: Mejorar la infraestructura en comunidades rurales e indígenas del Área de Influencia de Paracel a través de intervenciones con foco en: A - Sistemas de acceso y distribución de agua. B -Mejoramiento | R25: 1- Criterios de elegibilidad del proyecto / mapa comunidades. 2- Convenios/ acuerdos. 3- Carta de compromiso firmadas por las comunidades beneficiadas. 4- Informe de línea de base. 5- Informe de línea | S25: - Comunidades con sistemas de acceso y distribución de agua. - Comunidades con mejoramiento de los sistemas de accesos y/o distribucion de energía eléctrica. | T25: 255.831 | U25: Feb, Jun, Jul, Ago, Sep, Oct, Nov, Dic | W25: - Mejora la infraestructura existente. | X25: Fomentar el desarrollo local y promover el vínculo cercano entre las comunidades y la empresa. Mejorar la capacidad de producción y de innovación para la agregación de valor a las actividades generado | Y25: DEFINICIONES Área de Influencia Directa (AID) del componente industrial: incluyen 5 distritos cercanos al sitio de la Planta Industrial, incluyendo a 18 comunidades que se encuentran en un radio de 13 | AA25: =B25&"-T"&TEXT(I25,"00") -> PR-SS-RCI-T02 | AB25: =IF(H25="","",VALUE(LEFT(TEXT(H25,"yyyy-mm-dd"),4))) -> 2025 | AC25: 255831 | AD25: =IF(U25="","",LEN(U25)-LEN(SUBSTITUTE(U25,",",""))+1) -> 8 | AE25: =ROUND((COUNTIF(J25,"<>") + COUNTIF(K25,"<>") + COUNTIF(L25,"<>") + COUNTIF(M25,"<>") + COUNTIF(N25,"<>") + COUNTIF(O25,"<>") + COUNTIF(P25,"<>") + COUNTIF(Q25,"<>") + COUNTIF(R25,"<>") + COUNTIF(S25,"<>") + COUNTIF(T25,"<>") + COUNTIF(U25,"<>") + COUNTIF(V25,"<>") + COUNTIF(W25,"<>") + COUNTIF(X25,"<>") + COUNTIF(Y25,"<>") + COUNTIF(Z25,"<>"))/17,3) -> 0.588 | AF25: =COUNTBLANK(M25:Q25)+IF(OR(T25="",T25="----"),1,0)+IF(U25="",1,0) -> 5 | AG25: =IF(AF25=0,"Completo",IF(AF25<=2,"Parcial","Crítico")) -> Crítico
A26: 22 | B26: PR-SS-RCI | C26: Relacionamiento con Comunidades e Inversión Social | D26: v05 | E26: Vigente | F26: INFRAESTRUCTURA SOCIAL | G26: v01 | H26: 45830 | I26: 2 | J26: Mejorar la infraestructura existente de la playa municipal del distrito de Paso Horqueta. | K26: 1. Implementar el proyecto existente 2. Seguimiento a través de la medición de indicadores de proceso. 3. Toma de datos para la medición de impacto del proyecto. 4. Desarrollo del informe final. | L26: Mejorar la infraestructura existente de la playa municipal del distrito de Paso Horqueta. | R26: 1- Proyectos Sistematizados 2- Informes mensuales de monitoreo. 3- Informe final del proyecto. | S26: Playa Municipal de Paso Horqueta con mejoras en infraestructura y aumento de la percepción positiva de la población. | T26: 20.000 | U26: Jun, Jul, Ago, Sep | W26: - Mejora la infraestructura existente. | X26: Fomentar el desarrollo local y promover el vínculo cercano entre las comunidades y la empresa. Mejorar la capacidad de producción y de innovación para la agregación de valor a las actividades generado | Y26: DEFINICIONES Área de Influencia Directa (AID) del componente industrial: incluyen 5 distritos cercanos al sitio de la Planta Industrial, incluyendo a 18 comunidades que se encuentran en un radio de 13 | AA26: =B26&"-T"&TEXT(I26,"00") -> PR-SS-RCI-T02 | AB26: =IF(H26="","",VALUE(LEFT(TEXT(H26,"yyyy-mm-dd"),4))) -> 2025 | AC26: 20000 | AD26: =IF(U26="","",LEN(U26)-LEN(SUBSTITUTE(U26,",",""))+1) -> 4 | AE26: =ROUND((COUNTIF(J26,"<>") + COUNTIF(K26,"<>") + COUNTIF(L26,"<>") + COUNTIF(M26,"<>") + COUNTIF(N26,"<>") + COUNTIF(O26,"<>") + COUNTIF(P26,"<>") + COUNTIF(Q26,"<>") + COUNTIF(R26,"<>") + COUNTIF(S26,"<>") + COUNTIF(T26,"<>") + COUNTIF(U26,"<>") + COUNTIF(V26,"<>") + COUNTIF(W26,"<>") + COUNTIF(X26,"<>") + COUNTIF(Y26,"<>") + COUNTIF(Z26,"<>"))/17,3) -> 0.588 | AF26: =COUNTBLANK(M26:Q26)+IF(OR(T26="",T26="----"),1,0)+IF(U26="",1,0) -> 5 | AG26: =IF(AF26=0,"Completo",IF(AF26<=2,"Parcial","Crítico")) -> Crítico
A27: 23 | B27: PR-SS-PDP | C27: Promoción y Desarrollo de Empresas Proveedoras Locales | D27: v05 | E27: Vigente | F27: ASOCIACIÓN DE PESCADORES | G27: v01 | H27: 45831 | I27: 1 | J27: Propiciar la formalización y mejora de la infraestructura de pescadores/as, con el fin de lograr el comercio optimo a través de la instalación de capacidades y el acceso a mercado. | K27: 1. Identificación de asociaciones y registro de pescadores. 2.Capacitaciones (formalización, comercialización, gestión). 3. Apoyo a la formalización y acceso a mercados. 4. Creación de alianzas y nuevos canales de venta. 5. Evaluación, contratacion de consultores e inversión. 6. Evaluación inicial d | L27: N° de asociaciones de pescadores beneficiadas N° de pescadores/as beneficiados/as, clasificados por edad, sexo, barrio y etnia N° de capacitación realizadas por asociación N° de participantes en cada taller, clasificados por edad, sexo, barrio, localidad, asociación, etnia % del nivel de conocimientos adquiridos N° de acuerdos firmados con instituciones y/o organizaciones claves % de incremento en ventas de productos pesqueros N° de asociaciones participantes en jornada de formalización con el MADES N° de pescadores/as formalizados/as, clasificados por asociación N° de empresas consultoras contratadas (Clasificados por edad, sexo, distrito, departamento) Valor de inversión en guaraníes por Paracel y organizaciones aliadas N° de puntos de venta evaluados y diagnosticados Cantidad de alianzas estratégicas formalizadas N° de intervenciones ejecutadas en infraestructura y logística Cantidad de equipamientos entregados a puntos de venta Medición del impacto en ventas Valor de inversión en guaraníes por Paracel y organizaciones aliadas N° de asociaciones identificadas y evaluadas Cantidad de documentos tramitados para la formalización N° de asociaciones con personería jurídica obtenida % de asociaciones formalizadas con éxito | R27: 1.Base de datos de asociaciones y pescadores registrados 2.Listado de participantes capacitados 3.Documentación presentada para la formalización 4.Convenios o acuerdos firmados con aliados comerciales | S27: Fortalecimiento en la profesionalización y formalización de pescadores, con mejoras en su gestión, acceso a mercados y comercialización de productos. | U27: Jun, Jul, Ago, Sep, Oct, Nov | V27: Fortalecer la profesionalización y formalización de pescadores/as. | W27: - Falta de canales formales para la comercialización de productos derivados de la pesca. - Falta de formalización de los miembros de las asociaciones y de las asociaciones. | X27: Impulsar el desarrollo y crecimiento de la economía local a través de la promoción de empresas locales y nacionales como posibles [empresas proveedoras]. | [FSC-STD-PRY-01-2022] Normas de Desempeño IF | Y27: El alcance del programa de detalla a continuación: DEFINICIONES Área de Influencia Directa (AID) del componente industrial: incluyen 5 distritos cercanos al sitio de la Planta Industrial, incluyendo a | AA27: =B27&"-T"&TEXT(I27,"00") -> PR-SS-PDP-T01 | AB27: =IF(H27="","",VALUE(LEFT(TEXT(H27,"yyyy-mm-dd"),4))) -> 2025 | AC27: 0 | AD27: =IF(U27="","",LEN(U27)-LEN(SUBSTITUTE(U27,",",""))+1) -> 6 | AE27: =ROUND((COUNTIF(J27,"<>") + COUNTIF(K27,"<>") + COUNTIF(L27,"<>") + COUNTIF(M27,"<>") + COUNTIF(N27,"<>") + COUNTIF(O27,"<>") + COUNTIF(P27,"<>") + COUNTIF(Q27,"<>") + COUNTIF(R27,"<>") + COUNTIF(S27,"<>") + COUNTIF(T27,"<>") + COUNTIF(U27,"<>") + COUNTIF(V27,"<>") + COUNTIF(W27,"<>") + COUNTIF(X27,"<>") + COUNTIF(Y27,"<>") + COUNTIF(Z27,"<>"))/17,3) -> 0.588 | AF27: =COUNTBLANK(M27:Q27)+IF(OR(T27="",T27="----"),1,0)+IF(U27="",1,0) -> 6 | AG27: =IF(AF27=0,"Completo",IF(AF27<=2,"Parcial","Crítico")) -> Crítico
A28: 24 | B28: PR-SS-PDP | C28: Promoción y Desarrollo de Empresas Proveedoras Locales | D28: v05 | E28: Vigente | F28: DESARROLLO DE PROVEEDORES LOCALES | G28: v01 | H28: 45831 | I28: 1 | J28: Implementar el Programa Ñañoty, de fomento forestal dirigido a [pequeños/as productores/as], situados en un radio de 50 km alrededor de algún emprendimiento (forestal e industrial) de Paracel. | K28: 1. Desarrollar un proyecto piloto de valor compartido con foco en la estrategia 2: inclusión en la cadena de valor de Paracel a [pequeños/as productores/as] forestales (vinculado a los plazos del área de Fomento Forestal. 2. Generar alianzas con organizaciones vinculadas al trabajo con [pequeños/as | L28: - Número de plantines donados/entregados como capital semilla. - Número de alianzas alcanzadas. - Número de personas vinculadas al proyecto externas a Paracel (por actividad). - Monto de inversión directa o indirecta por parte de las organizaciones aliadas (por actividad). - Número de contratos firmados con las personas participantes del proyecto. - Número de plantines donados/entregados como capital semilla. - Cantidad de insumos, equipos y herramientas entregados (también en guaraníes). - Cantidad de horas de asesoramiento técnico destinadas a cada beneficiario/a (visitas). - Cantidad de asesoramiento técnico a través de visitas destinadas a cada beneficiario/a. - Cantidad de horas de capacitación destinada a cada beneficiario/a. - Número de servicios alcanzados con el proyecto (también en guaraníes - mano de obra, flete, traslado, maquinaria). - Porcentaje de uso del presupuesto de manera mensual. - Número de mano de obra contratada clasificada por región (local, departamental, nacional). - Cantidad de guaraníes invertidos en el departamento de Concepción. - Observación: (todos los datos deben ser clasificados por edad, sexo, tipo de comunidad, las comunidades deben ser clasificadas utilizando el nombre las mismas y las etnias si aplica). | R28: 1- Criterios de elegibilidad del proyecto / mapa de familias (organizaciones). 2- Convenios/ acuerdos. 3- Carta de compromiso / interés firmadas por las personas/familias/organizaciones beneficiadas ( | S28: 50 hectáreas dentro del programa de fomento forestal social con resultados óptimos en el primer año. | U28: Feb, Mar, Abr, May, Jun, Jul, Ago, Sep, Oct, Nov, Dic | V28: Impulsar el desarrollo y crecimiento de la economía local a través de la promoción de empresas locales y nacionales como posibles empresas proveedoras. | W28: Diversificación de ingresos de pequeños productores y capital semilla para el desarrollo de plantaciones. | X28: Impulsar el desarrollo y crecimiento de la economía local a través de la promoción de empresas locales y nacionales como posibles [empresas proveedoras]. | [FSC-STD-PRY-01-2022] Normas de Desempeño IF | Y28: El alcance del programa de detalla a continuación: DEFINICIONES Área de Influencia Directa (AID) del componente industrial: incluyen 5 distritos cercanos al sitio de la Planta Industrial, incluyendo a | AA28: =B28&"-T"&TEXT(I28,"00") -> PR-SS-PDP-T01 | AB28: =IF(H28="","",VALUE(LEFT(TEXT(H28,"yyyy-mm-dd"),4))) -> 2025 | AC28: 0 | AD28: =IF(U28="","",LEN(U28)-LEN(SUBSTITUTE(U28,",",""))+1) -> 11 | AE28: =ROUND((COUNTIF(J28,"<>") + COUNTIF(K28,"<>") + COUNTIF(L28,"<>") + COUNTIF(M28,"<>") + COUNTIF(N28,"<>") + COUNTIF(O28,"<>") + COUNTIF(P28,"<>") + COUNTIF(Q28,"<>") + COUNTIF(R28,"<>") + COUNTIF(S28,"<>") + COUNTIF(T28,"<>") + COUNTIF(U28,"<>") + COUNTIF(V28,"<>") + COUNTIF(W28,"<>") + COUNTIF(X28,"<>") + COUNTIF(Y28,"<>") + COUNTIF(Z28,"<>"))/17,3) -> 0.588 | AF28: =COUNTBLANK(M28:Q28)+IF(OR(T28="",T28="----"),1,0)+IF(U28="",1,0) -> 6 | AG28: =IF(AF28=0,"Completo",IF(AF28<=2,"Parcial","Crítico")) -> Crítico
A29: 25 | B29: PR-SS-PDP | C29: Promoción y Desarrollo de Empresas Proveedoras Locales | D29: v05 | E29: Vigente | F29: DESARROLLO DE PROVEEDORES LOCALES | G29: v01 | H29: 45831 | I29: 2 | J29: Generar alianzas para el desarrollo de espacios de networking y/o capacitación (virtual o presencial) dirigidos a Mipymes, con el objetivo de fortalecer su motivación, creatividad y visión de negocio. | K29: 1. Búsqueda y generación de alianzas y/o acuerdos para el desarrollo de espacios de networking y/o capacitación. 2. Planificación de la jornada de networking y/o espacios de capacitación. 3. Coordinación logística (lugar, insumos, convocatoria). 4. Realización del primer espacio. 5. Realización del | L29: N° de emprendedores inscritos y asistentes (Clasificados por edad, sexo, etnia, localidad, departamento). N° de rubros presentes en el evento. Cantidad de empresas por tamaño (micro, pequeña, mediana y grande). N° de empresas vinculadas con Paracel (participantes del Programa 2023, 2024). % de satisfacción de los/las participantes. N° de necesidades identificadas para futuras capacitaciones. N° de consultores contratados (Clasificados por edad, sexo, distrito, departamento). Valor de inversión en guaraníes por Paracel y organizaciones aliadas. EVALUACIÓN DE IMPACTO MÉTODO DE EVALUACIÓN No Experimental (Antes y Después) (Facturación, número de personas contratadas, número de clientes, cantidad de documentos legales disponibles, volumen de producción, modalidad del negocio, etc.) | R29: 1. Alianzas logradas. 2. Materiales y metodologías de trabajo desarrolladas. 3. Plan logístico y registro de participantes. 4. Primer espacio realizado. 5. Segundo espacio realizado. 6. Resultados de | S29: Espacios de networking y/o capacitaciones ejecutados con éxito, fortaleciendo las capacidades de los participantes y fomentando la creación de redes de colaboración entre emprendedores, facilitando el | U29: Jun, Jul, Ago, Sep, Oct, Nov | V29: Impulsar el desarrollo y crecimiento de la economía local a través de la promoción de empresas locales y nacionales como posibles empresas proveedoras. | W29: Diversificación de ingresos de pequeños productores y capital semilla para el desarrollo de plantaciones. | X29: Impulsar el desarrollo y crecimiento de la economía local a través de la promoción de empresas locales y nacionales como posibles [empresas proveedoras]. | [FSC-STD-PRY-01-2022] Normas de Desempeño IF | Y29: El alcance del programa de detalla a continuación: DEFINICIONES Área de Influencia Directa (AID) del componente industrial: incluyen 5 distritos cercanos al sitio de la Planta Industrial, incluyendo a | AA29: =B29&"-T"&TEXT(I29,"00") -> PR-SS-PDP-T02 | AB29: =IF(H29="","",VALUE(LEFT(TEXT(H29,"yyyy-mm-dd"),4))) -> 2025 | AC29: 0 | AD29: =IF(U29="","",LEN(U29)-LEN(SUBSTITUTE(U29,",",""))+1) -> 6 | AE29: =ROUND((COUNTIF(J29,"<>") + COUNTIF(K29,"<>") + COUNTIF(L29,"<>") + COUNTIF(M29,"<>") + COUNTIF(N29,"<>") + COUNTIF(O29,"<>") + COUNTIF(P29,"<>") + COUNTIF(Q29,"<>") + COUNTIF(R29,"<>") + COUNTIF(S29,"<>") + COUNTIF(T29,"<>") + COUNTIF(U29,"<>") + COUNTIF(V29,"<>") + COUNTIF(W29,"<>") + COUNTIF(X29,"<>") + COUNTIF(Y29,"<>") + COUNTIF(Z29,"<>"))/17,3) -> 0.588 | AF29: =COUNTBLANK(M29:Q29)+IF(OR(T29="",T29="----"),1,0)+IF(U29="",1,0) -> 6 | AG29: =IF(AF29=0,"Completo",IF(AF29<=2,"Parcial","Crítico")) -> Crítico
A30: 26 | B30: PR-SS-RPI | C30: Relacionamiento con Comunidades Indígenas | D30: v05 | E30: Vigente | F30: COMUNIDADES INDÍGENAS | G30: v01 | H30: 45831 | I30: 1 | J30: Garantizar el cumplimiento del 100% de los procesos CLPI, en el marco del cumplimiento del Decreto 1039/18, la norma IFC, los criterios de la norma FSC® y el respeto de los Derechos de los Pueblos Indígenas para las comunidades indígenas del Área de Influencia Directa del proyecto Paracel para el añ | K30: 1- Realizar encuentros de socialización de avances de Paracel y los programas socioambientales en las comunidades indígenas dentro del AID. 2- Convenir con las comunidades indígenas el cumplimiento del proceso de “Consulta y Consentimiento, Libre, Previo e Informado” (CCLPI), conforme al Decreto 103 | L30: A01- Número de personas participantes del proceso de consulta prevía, libre e informada por comunidad y clasificada por franja etaria, sexo, grado de instrucción, etc. A02- Proporción participación de familias en función al número total de familias de la comunidad (Calculado con miembros adultos representantes de familia) A03- Número de reuniones de socialización. A04- Número de personas de otras instituciones que acompañan el proceso. A05- Inversión de otras instituciones en el proceso de consultas. A06- Lista de comentarios, percepción, expectativas de los miembros de las comunidades. A07- Tiempo invertido en el desarrollo de los procesos de consulta. A08- Número de materiales de socialización desarrollados. | R30: Procesos de CPLI realizados | S30: Activar el proceso de CCPLI para todas las comunidades del AID de Paracel incluyendo zonas nuevas de expansión forestal. | T30: 3.896 | U30: Jun, Nov | X30: Establecer y mantener una relación continua con los Pueblos Indígenas fomentando el pleno respeto a los derechos humanos, dignidad, aspiraciones, cultura y medios de subsistencia dependientes de los r | Y30: El programa de Relacionamiento con Comunidades Indígenas tiene el siguiente alcance: DEFINICIONES Área de Influencia Directa (AID) del componente indígena: está compuesta por las comunidades indígena | AA30: =B30&"-T"&TEXT(I30,"00") -> PR-SS-RPI-T01 | AB30: =IF(H30="","",VALUE(LEFT(TEXT(H30,"yyyy-mm-dd"),4))) -> 2025 | AC30: 3896 | AD30: =IF(U30="","",LEN(U30)-LEN(SUBSTITUTE(U30,",",""))+1) -> 2 | AE30: =ROUND((COUNTIF(J30,"<>") + COUNTIF(K30,"<>") + COUNTIF(L30,"<>") + COUNTIF(M30,"<>") + COUNTIF(N30,"<>") + COUNTIF(O30,"<>") + COUNTIF(P30,"<>") + COUNTIF(Q30,"<>") + COUNTIF(R30,"<>") + COUNTIF(S30,"<>") + COUNTIF(T30,"<>") + COUNTIF(U30,"<>") + COUNTIF(V30,"<>") + COUNTIF(W30,"<>") + COUNTIF(X30,"<>") + COUNTIF(Y30,"<>") + COUNTIF(Z30,"<>"))/17,3) -> 0.529 | AF30: =COUNTBLANK(M30:Q30)+IF(OR(T30="",T30="----"),1,0)+IF(U30="",1,0) -> 5 | AG30: =IF(AF30=0,"Completo",IF(AF30<=2,"Parcial","Crítico")) -> Crítico
A31: 27 | B31: PR-SS-RPI | C31: Relacionamiento con Comunidades Indígenas | D31: v05 | E31: Vigente | F31: COMUNIDADES INDÍGENAS | G31: v01 | H31: 45831 | I31: 2 | J31: Desarrollo un plan de uso de servicios ecosistémicos con las comunidades indígenas que hacen uso de estos dentro de propiedades de Paracel. | K31: 1. Desarrollo de Plan de uso de servicios ecosistemicos 2. Socializacion del Plan de Uso de Servicios con los lideres y lideresas de las comunidades indígenas 3. Socialización del Plan de Uso de Servicios ecosistémicos con la comunidades indígenas 4. Evaluacion y seguimiento | L31: A01- Usos de servicios ecosistémicos identificados (tipo, superficie, estancias, personas que hacen uso, distancias de recorrido para uso, metodología de uso) A02- Plan de manejo de servicios ecosistémicos (cantidad de planes desarrollados e implementados, ubicación) A03- Evaluaciones y socializaciones de planes de uso de servicios ecosistémicos A04- Implementación de planes de uso de servicios ecosistémicos La desagregaciones se dan por comunidad, sexo, edad, número de personas | R31: - Base de datos de uso de serivios ecosistémicos actualizados. - Mapas actualizados de uso de servicios ecosistémicos. - Planes de manejo de servicios ecosistémicos | S31: Informe de plan de manejo de uso de servicios ecosistémicos de tres comunidades indígenas. | T31: 0 | U31: Ago, Sep, Oct, Nov, Dic | X31: Establecer y mantener una relación continua con los Pueblos Indígenas fomentando el pleno respeto a los derechos humanos, dignidad, aspiraciones, cultura y medios de subsistencia dependientes de los r | Y31: El programa de Relacionamiento con Comunidades Indígenas tiene el siguiente alcance: DEFINICIONES Área de Influencia Directa (AID) del componente indígena: está compuesta por las comunidades indígena | AA31: =B31&"-T"&TEXT(I31,"00") -> PR-SS-RPI-T02 | AB31: =IF(H31="","",VALUE(LEFT(TEXT(H31,"yyyy-mm-dd"),4))) -> 2025 | AC31: 0 | AD31: =IF(U31="","",LEN(U31)-LEN(SUBSTITUTE(U31,",",""))+1) -> 5 | AE31: =ROUND((COUNTIF(J31,"<>") + COUNTIF(K31,"<>") + COUNTIF(L31,"<>") + COUNTIF(M31,"<>") + COUNTIF(N31,"<>") + COUNTIF(O31,"<>") + COUNTIF(P31,"<>") + COUNTIF(Q31,"<>") + COUNTIF(R31,"<>") + COUNTIF(S31,"<>") + COUNTIF(T31,"<>") + COUNTIF(U31,"<>") + COUNTIF(V31,"<>") + COUNTIF(W31,"<>") + COUNTIF(X31,"<>") + COUNTIF(Y31,"<>") + COUNTIF(Z31,"<>"))/17,3) -> 0.529 | AF31: =COUNTBLANK(M31:Q31)+IF(OR(T31="",T31="----"),1,0)+IF(U31="",1,0) -> 5 | AG31: =IF(AF31=0,"Completo",IF(AF31<=2,"Parcial","Crítico")) -> Crítico
A32: 28 | B32: PR-SS-RPI | C32: Relacionamiento con Comunidades Indígenas | D32: v05 | E32: Vigente | F32: COMUNIDADES INDÍGENAS | G32: v01 | H32: 45831 | I32: 3 | J32: Mantener la vinculación con las comunidades Ita Jeguaka, Cerro Akangue y Arroyo Ka’a a través de actividades específicas coordinadas con lideres comunitarios. | K32: 1. Mantener comunicación con líderes comunitarios. 2. Coordinar la participación de líderes y/o lideresas en las actividades abiertas (capacitaciones, espacios de vinculación con entidades estatales, etc.) desarrolladas por Paracel. 3. Invitar y monitorear la participación de miembros de estás comun | L32: A01- Número de materiales entregados. A02- Número de vinculaciones por tipo (reuniones, invitaciones, contacto telefónico, etc). A02- Número de personas alcanzadas. A02- Número de consultas, expectativas, sugerencias. A03- Número de actividades en las que participaron. La desagregaciones se dan por comunidad, sexo, edad. | R32: - Materiales de comunicación desarrollados. - Reuniones desarrolladas. - Informe de vinculación | S32: Matener la vinculación con las comunidades Ita Jeguaka, Cerro Akangue y Arroyo Ka’a | T32: 2.727 | U32: Jul, Oct, Nov | X32: Establecer y mantener una relación continua con los Pueblos Indígenas fomentando el pleno respeto a los derechos humanos, dignidad, aspiraciones, cultura y medios de subsistencia dependientes de los r | Y32: El programa de Relacionamiento con Comunidades Indígenas tiene el siguiente alcance: DEFINICIONES Área de Influencia Directa (AID) del componente indígena: está compuesta por las comunidades indígena | AA32: =B32&"-T"&TEXT(I32,"00") -> PR-SS-RPI-T03 | AB32: =IF(H32="","",VALUE(LEFT(TEXT(H32,"yyyy-mm-dd"),4))) -> 2025 | AC32: 2727 | AD32: =IF(U32="","",LEN(U32)-LEN(SUBSTITUTE(U32,",",""))+1) -> 3 | AE32: =ROUND((COUNTIF(J32,"<>") + COUNTIF(K32,"<>") + COUNTIF(L32,"<>") + COUNTIF(M32,"<>") + COUNTIF(N32,"<>") + COUNTIF(O32,"<>") + COUNTIF(P32,"<>") + COUNTIF(Q32,"<>") + COUNTIF(R32,"<>") + COUNTIF(S32,"<>") + COUNTIF(T32,"<>") + COUNTIF(U32,"<>") + COUNTIF(V32,"<>") + COUNTIF(W32,"<>") + COUNTIF(X32,"<>") + COUNTIF(Y32,"<>") + COUNTIF(Z32,"<>"))/17,3) -> 0.529 | AF32: =COUNTBLANK(M32:Q32)+IF(OR(T32="",T32="----"),1,0)+IF(U32="",1,0) -> 5 | AG32: =IF(AF32=0,"Completo",IF(AF32<=2,"Parcial","Crítico")) -> Crítico
A33: 29 | B33: PR-SS-RPI | C33: Relacionamiento con Comunidades Indígenas | D33: v05 | E33: Vigente | F33: COMUNIDADES INDÍGENAS | G33: v01 | H33: 45831 | I33: 4 | J33: Desarrollar jornadas de gestión documental vinculados a la identidad de los miembros de comunidades indígenas (cédulas de identidad, carnet indígena, partidas de nacimiento, inscripciones en el Registro Civil), etc. | K33: 1- Planificar las jornadas de cedulación con las instituciones del estado y las comunidades. 2- Activar las jornadas de cedulación. 3- Reporte del proceso. | L33: A01 - Cantidad de cédulas (Primera vez). A02 - Actas de nacimiento por edad (Niños menores de 0 a 4 años). A03 - Cantidad de documentaciones gestionados y obtenidos según tipo (Clasificado por edad, edad, sexo, comunidad, etc). La desagregaciones se dan por persona, edad, sexo, comunidad, etc. | R33: - Cédulas entregadas a los miembros de las comunidades. | S33: - Personas de comunidades indígenas con registro de identidad (por primera vez). - Personas con cédula de identidad renovadas. | T33: 6.753 | U33: Jun, Jul, Ago, Sep, Oct, Nov | X33: Establecer y mantener una relación continua con los Pueblos Indígenas fomentando el pleno respeto a los derechos humanos, dignidad, aspiraciones, cultura y medios de subsistencia dependientes de los r | Y33: El programa de Relacionamiento con Comunidades Indígenas tiene el siguiente alcance: DEFINICIONES Área de Influencia Directa (AID) del componente indígena: está compuesta por las comunidades indígena | AA33: =B33&"-T"&TEXT(I33,"00") -> PR-SS-RPI-T04 | AB33: =IF(H33="","",VALUE(LEFT(TEXT(H33,"yyyy-mm-dd"),4))) -> 2025 | AC33: 6753 | AD33: =IF(U33="","",LEN(U33)-LEN(SUBSTITUTE(U33,",",""))+1) -> 6 | AE33: =ROUND((COUNTIF(J33,"<>") + COUNTIF(K33,"<>") + COUNTIF(L33,"<>") + COUNTIF(M33,"<>") + COUNTIF(N33,"<>") + COUNTIF(O33,"<>") + COUNTIF(P33,"<>") + COUNTIF(Q33,"<>") + COUNTIF(R33,"<>") + COUNTIF(S33,"<>") + COUNTIF(T33,"<>") + COUNTIF(U33,"<>") + COUNTIF(V33,"<>") + COUNTIF(W33,"<>") + COUNTIF(X33,"<>") + COUNTIF(Y33,"<>") + COUNTIF(Z33,"<>"))/17,3) -> 0.529 | AF33: =COUNTBLANK(M33:Q33)+IF(OR(T33="",T33="----"),1,0)+IF(U33="",1,0) -> 5 | AG33: =IF(AF33=0,"Completo",IF(AF33<=2,"Parcial","Crítico")) -> Crítico
A34: 30 | B34: PR-SS-RPI | C34: Relacionamiento con Comunidades Indígenas | D34: v05 | E34: Vigente | F34: COMUNIDADES INDÍGENAS | G34: v01 | H34: 45831 | I34: 5 | J34: Apoyar a la seguridad alimentaria escolar en comunidades del AID. | K34: 1. Analizar el alcance actual de programas de gobierno para provision de alimento escolar 2. Monitorear la entrega de alimento escolar complementaria 3. Proveer alimento complementario según resultados del análisis desarrollado 4. Encuesta respecto a la provisión de alimentos | L34: A01 - Instituciones alcanzadas (distrito y tipo de comunidad). A02 - Número de niños alcanzados según RUE. A03 - Número de niños alcanzados (real). A04 - Kg de alimentos entregados. A05 - Proporción de alimentos por tipo. Datos desagregados por sexo, edad y grado. | R34: - Informe de alcance de programas de gobierno para provisión de alimento escolar - Informe de entrega de almuerzo escolar | S34: - Estudiantes de escuelas con provisión de alimentos complementarios | T34: 15.909 | U34: Feb, Mar, Abr, May, Jun, Jul, Ago, Sep, Oct, Nov | X34: Establecer y mantener una relación continua con los Pueblos Indígenas fomentando el pleno respeto a los derechos humanos, dignidad, aspiraciones, cultura y medios de subsistencia dependientes de los r | Y34: El programa de Relacionamiento con Comunidades Indígenas tiene el siguiente alcance: DEFINICIONES Área de Influencia Directa (AID) del componente indígena: está compuesta por las comunidades indígena | AA34: =B34&"-T"&TEXT(I34,"00") -> PR-SS-RPI-T05 | AB34: =IF(H34="","",VALUE(LEFT(TEXT(H34,"yyyy-mm-dd"),4))) -> 2025 | AC34: 15909 | AD34: =IF(U34="","",LEN(U34)-LEN(SUBSTITUTE(U34,",",""))+1) -> 10 | AE34: =ROUND((COUNTIF(J34,"<>") + COUNTIF(K34,"<>") + COUNTIF(L34,"<>") + COUNTIF(M34,"<>") + COUNTIF(N34,"<>") + COUNTIF(O34,"<>") + COUNTIF(P34,"<>") + COUNTIF(Q34,"<>") + COUNTIF(R34,"<>") + COUNTIF(S34,"<>") + COUNTIF(T34,"<>") + COUNTIF(U34,"<>") + COUNTIF(V34,"<>") + COUNTIF(W34,"<>") + COUNTIF(X34,"<>") + COUNTIF(Y34,"<>") + COUNTIF(Z34,"<>"))/17,3) -> 0.529 | AF34: =COUNTBLANK(M34:Q34)+IF(OR(T34="",T34="----"),1,0)+IF(U34="",1,0) -> 5 | AG34: =IF(AF34=0,"Completo",IF(AF34<=2,"Parcial","Crítico")) -> Crítico
A35: 31 | B35: PR-SS-RPI | C35: Relacionamiento con Comunidades Indígenas | D35: v05 | E35: Vigente | F35: COMUNIDADES INDÍGENAS | G35: v01 | H35: 45831 | I35: 6 | J35: Apoyar a referentes de comunidades indígenas en el relacionamiento con instituciones del estado a fin de autogestionar los temas relacionados a su organización comunitaria o política (identidad, vivienda, salud, educación, etc.). | K35: 1. Analisis y registro de solicitudes. 2. Gestión de apoyo a solicitudes ingresadas. 3. Informe de gestiones realizadas. | L35: A01 - Número de gestiones clasificadas por documentación de identidad, documentación comunitaria, salud, seguridad, acceso a servicios básicos, etc. A02 - Número de instituciones (desagregadas). A03 - Valor invertido. | R35: Informe de relacionamiento institucional | S35: Autogestión comunitaria reflejada en número de trámites o procesos ejecutados con instituciones. | T35: 5.065 | U35: Ene, Feb, Mar, Abr, May, Jun, Jul, Ago, Sep, Oct, Nov, Dic | X35: Establecer y mantener una relación continua con los Pueblos Indígenas fomentando el pleno respeto a los derechos humanos, dignidad, aspiraciones, cultura y medios de subsistencia dependientes de los r | Y35: El programa de Relacionamiento con Comunidades Indígenas tiene el siguiente alcance: DEFINICIONES Área de Influencia Directa (AID) del componente indígena: está compuesta por las comunidades indígena | AA35: =B35&"-T"&TEXT(I35,"00") -> PR-SS-RPI-T06 | AB35: =IF(H35="","",VALUE(LEFT(TEXT(H35,"yyyy-mm-dd"),4))) -> 2025 | AC35: 5065 | AD35: =IF(U35="","",LEN(U35)-LEN(SUBSTITUTE(U35,",",""))+1) -> 12 | AE35: =ROUND((COUNTIF(J35,"<>") + COUNTIF(K35,"<>") + COUNTIF(L35,"<>") + COUNTIF(M35,"<>") + COUNTIF(N35,"<>") + COUNTIF(O35,"<>") + COUNTIF(P35,"<>") + COUNTIF(Q35,"<>") + COUNTIF(R35,"<>") + COUNTIF(S35,"<>") + COUNTIF(T35,"<>") + COUNTIF(U35,"<>") + COUNTIF(V35,"<>") + COUNTIF(W35,"<>") + COUNTIF(X35,"<>") + COUNTIF(Y35,"<>") + COUNTIF(Z35,"<>"))/17,3) -> 0.529 | AF35: =COUNTBLANK(M35:Q35)+IF(OR(T35="",T35="----"),1,0)+IF(U35="",1,0) -> 5 | AG35: =IF(AF35=0,"Completo",IF(AF35<=2,"Parcial","Crítico")) -> Crítico

Sheet 03_INDICADORES_NORMALIZADOS
A1: 03. INDICADORES NORMALIZADOS
A2: Cada indicador se descompone en una fila para facilitar filtrado, conteo, clasificación y explotación analítica.
A4: ID INDICADOR | B4: CÓDIGO PROGRAMA | C4: NOMBRE PROGRAMA | D4: FICHA | E4: TARGET | F4: ORDEN | G4: INDICADOR INDIVIDUAL | H4: TIPO | I4: RESPONSABLE | J4: ORIGEN
A5: PR-SS-MDO-Target 2-01 | B5: PR-SS-MDO | C5: Programa de Desarrollo y Vinculación de Mano de Obra Local | D5: PROGRAMA DE DESARROLLO Y VINCULACIÓN CON LA MANO DE OBRA LOCAL | E5: Target 2 | F5: 1 | G5: Indicadores socioeconómicos. | H5: Mixto / descriptivo | J5: Indicadores
A6: PR-SS-MDO-Target 2-02 | B6: PR-SS-MDO | C6: Programa de Desarrollo y Vinculación de Mano de Obra Local | D6: PROGRAMA DE DESARROLLO Y VINCULACIÓN CON LA MANO DE OBRA LOCAL | E6: Target 2 | F6: 2 | G6: Número de personas beneficiadas clasificadas por edad, sexo, comunidad, etnía. | H6: Conteo | J6: Indicadores
A7: PR-SS-MDO-Target 2-03 | B7: PR-SS-MDO | C7: Programa de Desarrollo y Vinculación de Mano de Obra Local | D7: PROGRAMA DE DESARROLLO Y VINCULACIÓN CON LA MANO DE OBRA LOCAL | E7: Target 2 | F7: 3 | G7: Nivel academico alcanzado por los padres/tutores | H7: Mixto / descriptivo | J7: Indicadores
A8: PR-SS-MDO-Target 2-04 | B8: PR-SS-MDO | C8: Programa de Desarrollo y Vinculación de Mano de Obra Local | D8: PROGRAMA DE DESARROLLO Y VINCULACIÓN CON LA MANO DE OBRA LOCAL | E8: Target 2 | F8: 4 | G8: hermanos/as mayores. | H8: Mixto / descriptivo | J8: Indicadores
A9: PR-SS-MDO-Target 2-05 | B9: PR-SS-MDO | C9: Programa de Desarrollo y Vinculación de Mano de Obra Local | D9: PROGRAMA DE DESARROLLO Y VINCULACIÓN CON LA MANO DE OBRA LOCAL | E9: Target 2 | F9: 5 | G9: Número de instituciones alidas y especialidades. | H9: Conteo | J9: Indicadores
A10: PR-SS-MDO-Target 2-06 | B10: PR-SS-MDO | C10: Programa de Desarrollo y Vinculación de Mano de Obra Local | D10: PROGRAMA DE DESARROLLO Y VINCULACIÓN CON LA MANO DE OBRA LOCAL | E10: Target 2 | F10: 6 | G10: Inversión mensual (seguimiento del presupuesto). | H10: Presupuesto | J10: Indicadores
A11: PR-SS-MDO-Target 2-07 | B11: PR-SS-MDO | C11: Programa de Desarrollo y Vinculación de Mano de Obra Local | D11: PROGRAMA DE DESARROLLO Y VINCULACIÓN CON LA MANO DE OBRA LOCAL | E11: Target 2 | F11: 7 | G11: Horas al mes destinada por parte de padrinos/madrinas en el acompañamiento de las personas. | H11: Mixto / descriptivo | J11: Indicadores
A12: PR-SS-MDO-Target 2-08 | B12: PR-SS-MDO | C12: Programa de Desarrollo y Vinculación de Mano de Obra Local | D12: PROGRAMA DE DESARROLLO Y VINCULACIÓN CON LA MANO DE OBRA LOCAL | E12: Target 2 | F12: 8 | G12: Reporte de calificaciones por período académico y por estudiante. | H12: Evidencia | J12: Indicadores
A13: PR-SS-MDO-Target 1-01 | B13: PR-SS-MDO | C13: Programa de Desarrollo y Vinculación de Mano de Obra Local | D13: PROGRAMA DE DESARROLLO Y VINCULACIÓN CON LA MANO DE OBRA LOCAL | E13: Target 1 | F13: 1 | G13: Indicadores de Educación | H13: Mixto / descriptivo | J13: Indicadores
A14: PR-SS-MDO-Target 1-02 | B14: PR-SS-MDO | C14: Programa de Desarrollo y Vinculación de Mano de Obra Local | D14: PROGRAMA DE DESARROLLO Y VINCULACIÓN CON LA MANO DE OBRA LOCAL | E14: Target 1 | F14: 2 | G14: Indicadores de Empleo | H14: Mixto / descriptivo | J14: Indicadores
A15: PR-SS-EMU-Target 1-01 | B15: PR-SS-EMU | C15: Programa de Empoderamiento de la Mujer | D15: EMPODERAMIENTO DE LA MUJER | E15: Target 1 | F15: 1 | G15: Número de personas alcanzadas clasificadas sexo, edad, etnia, comunidad, institución, etc. | H15: Conteo | J15: Indicadores
A16: PR-SS-EMU-Target 1-02 | B16: PR-SS-EMU | C16: Programa de Empoderamiento de la Mujer | D16: EMPODERAMIENTO DE LA MUJER | E16: Target 1 | F16: 2 | G16: N° de materiales desarrollados y difundidos. | H16: Conteo | J16: Indicadores
... A230: PR-SS-RPI-Target 6 : Apoyar a referentes de comunidades indígenas en el relacionamiento con instituciones del estado a fin de autogestionar los temas relacionados a su organización comunitaria o política (identidad, vivienda, salud, educación, etc.).-06 | B230: PR-SS-RPI | C230: Programa de Relacionamiento con Comunidades Indígenas | D230: COMUNIDADES INDÍGENAS | E230: Target 6 : Apoyar a referentes de comunidades indígenas en el relacionamiento con instituciones del estado a fin de autogestionar los temas relacionados a su organización comunitaria o política (identidad, vivienda, salud, educación, etc.). | F230: 6 | G230: Valor invertido. | H230: Mixto / descriptivo | J230: Indicadores

Sheet 04_CRONOGRAMA_TARGETS
A1: 04. CRONOGRAMA DE TARGETS
A2: Vista mensual de activación por target, a partir del campo Meses Activos de la hoja original.
A4: CÓDIGO PROGRAMA | B4: NOMBRE PROGRAMA | C4: FICHA | D4: TARGET N° | E4: DESCRIPCIÓN | F4: MESES ACTIVOS (RAW) | G4: ENE | H4: FEB | I4: MAR | J4: ABR | K4: MAY | L4: JUN | M4: JUL | N4: AGO | O4: SEP | P4: OCT | Q4: NOV | R4: DIC | S4: TOTAL MESES
A5: PR-SS-MDO | B5: Programa de Desarrollo y Vinculación de Mano de Obra Local | C5: PROGRAMA DE DESARROLLO Y VINCULACIÓN CON LA MANO DE OBRA LOCAL | D5: 1 | E5: Contribuir para aumentar el número de jóvenes y adultos con competencias técnicas y profesionales, para acceder al empleo (el trabajo decente) a través del desarrollo de [10] cursos de capacitación, y [8] jornadas de certificación laboral por compet | F5: May, Jun, Jul, Ago, Sep, Oct, Nov, Dic | G5: =--ISNUMBER(SEARCH("Ene",$F5)) -> 0 | H5: =--ISNUMBER(SEARCH("Feb",$F5)) -> 0 | I5: =--ISNUMBER(SEARCH("Mar",$F5)) -> 0 | J5: =--ISNUMBER(SEARCH("Abr",$F5)) -> 0 | K5: =--ISNUMBER(SEARCH("May",$F5)) -> 1 | L5: =--ISNUMBER(SEARCH("Jun",$F5)) -> 1 | M5: =--ISNUMBER(SEARCH("Jul",$F5)) -> 1 | N5: =--ISNUMBER(SEARCH("Ago",$F5)) -> 1 | O5: =--ISNUMBER(SEARCH("Sep",$F5)) -> 1 | P5: =--ISNUMBER(SEARCH("Oct",$F5)) -> 1 | Q5: =--ISNUMBER(SEARCH("Nov",$F5)) -> 1 | R5: =--ISNUMBER(SEARCH("Dic",$F5)) -> 1 | S5: =SUM(G5:R5) -> 8
A6: PR-SS-MDO | B6: Programa de Desarrollo y Vinculación de Mano de Obra Local | C6: PROGRAMA DE DESARROLLO Y VINCULACIÓN CON LA MANO DE OBRA LOCAL | D6: 2 | E6: Becar a jóvenes de las comunidades del área e influencia de Paracel: - 10 jóvenes para educación en Bachiller Técnico. - 11 jóvenes para educación Terciaria. | F6: Feb, Mar, Abr, May, Jun, Jul, Ago, Sep, Oct, Nov, Dic | G6: =--ISNUMBER(SEARCH("Ene",$F6)) -> 0 | H6: =--ISNUMBER(SEARCH("Feb",$F6)) -> 1 | I6: =--ISNUMBER(SEARCH("Mar",$F6)) -> 1 | J6: =--ISNUMBER(SEARCH("Abr",$F6)) -> 1 | K6: =--ISNUMBER(SEARCH("May",$F6)) -> 1 | L6: =--ISNUMBER(SEARCH("Jun",$F6)) -> 1 | M6: =--ISNUMBER(SEARCH("Jul",$F6)) -> 1 | N6: =--ISNUMBER(SEARCH("Ago",$F6)) -> 1 | O6: =--ISNUMBER(SEARCH("Sep",$F6)) -> 1 | P6: =--ISNUMBER(SEARCH("Oct",$F6)) -> 1 | Q6: =--ISNUMBER(SEARCH("Nov",$F6)) -> 1 | R6: =--ISNUMBER(SEARCH("Dic",$F6)) -> 1 | S6: =SUM(G6:R6) -> 11
A7: PR-SS-EMU | B7: Programa de Empoderamiento de la Mujer | C7: EMPODERAMIENTO DE LA MUJER | D7: 1 | E7: Difundir la Ruta de Auxilio desarrollada en el año 2024 con foco en los siguientes municipios: Concepción, Paso Barreto, Sargento José Felix López, Paso Horqueta, alcanzando como mínimo al 80% de las comunidades del área de influencia de Paracel. | F7: Jun, Jul, Oct, Nov, Dic | G7: =--ISNUMBER(SEARCH("Ene",$F7)) -> 0 | H7: =--ISNUMBER(SEARCH("Feb",$F7)) -> 0 | I7: =--ISNUMBER(SEARCH("Mar",$F7)) -> 0 | J7: =--ISNUMBER(SEARCH("Abr",$F7)) -> 0 | K7: =--ISNUMBER(SEARCH("May",$F7)) -> 0 | L7: =--ISNUMBER(SEARCH("Jun",$F7)) -> 1 | M7: =--ISNUMBER(SEARCH("Jul",$F7)) -> 1 | N7: =--ISNUMBER(SEARCH("Ago",$F7)) -> 0 | O7: =--ISNUMBER(SEARCH("Sep",$F7)) -> 0 | P7: =--ISNUMBER(SEARCH("Oct",$F7)) -> 1 | Q7: =--ISNUMBER(SEARCH("Nov",$F7)) -> 1 | R7: =--ISNUMBER(SEARCH("Dic",$F7)) -> 1 | S7: =SUM(G7:R7) -> 5
A8: PR-SS-EMU | B8: Programa de Empoderamiento de la Mujer | C8: EMPODERAMIENTO DE LA MUJER | D8: 2 | E8: Fortalecer la red de apoyo para las mujeres de la Región de Concepción desarrollando como mínimo 3 espacios. | F8: Jul, Sep, Nov, Dic | G8: =--ISNUMBER(SEARCH("Ene",$F8)) -> 0 | H8: =--ISNUMBER(SEARCH("Feb",$F8)) -> 0 | I8: =--ISNUMBER(SEARCH("Mar",$F8)) -> 0 | J8: =--ISNUMBER(SEARCH("Abr",$F8)) -> 0 | K8: =--ISNUMBER(SEARCH("May",$F8)) -> 0 | L8: =--ISNUMBER(SEARCH("Jun",$F8)) -> 0 | M8: =--ISNUMBER(SEARCH("Jul",$F8)) -> 1 | N8: =--ISNUMBER(SEARCH("Ago",$F8)) -> 0 | O8: =--ISNUMBER(SEARCH("Sep",$F8)) -> 1 | P8: =--ISNUMBER(SEARCH("Oct",$F8)) -> 0 | Q8: =--ISNUMBER(SEARCH("Nov",$F8)) -> 1 | R8: =--ISNUMBER(SEARCH("Dic",$F8)) -> 1 | S8: =SUM(G8:R8) -> 4
A9: PR-SS-CON | B9: Programa de Sensibilización y Seguimiento a Contratistas y Trabajadores | C9: GESTIÓN DE EMPRESAS CONTRATISTAS | D9: 1 | E9: Auditar de forma trimestral a empresas contratistas del componente Forestal e Industrial (si aplica) en materia de sustentabilidad social considerando las normativas nacionales e internacionales adoptadas por Paracel, en el marco del respeto de los d | F9: Ene, Feb, Mar, Abr, May, Jun, Jul, Ago, Sep, Oct, Nov, Dic | G9: =--ISNUMBER(SEARCH("Ene",$F9)) -> 1 | H9: =--ISNUMBER(SEARCH("Feb",$F9)) -> 1 | I9: =--ISNUMBER(SEARCH("Mar",$F9)) -> 1 | J9: =--ISNUMBER(SEARCH("Abr",$F9)) -> 1 | K9: =--ISNUMBER(SEARCH("May",$F9)) -> 1 | L9: =--ISNUMBER(SEARCH("Jun",$F9)) -> 1 | M9: =--ISNUMBER(SEARCH("Jul",$F9)) -> 1 | N9: =--ISNUMBER(SEARCH("Ago",$F9)) -> 1 | O9: =--ISNUMBER(SEARCH("Sep",$F9)) -> 1 | P9: =--ISNUMBER(SEARCH("Oct",$F9)) -> 1 | Q9: =--ISNUMBER(SEARCH("Nov",$F9)) -> 1 | R9: =--ISNUMBER(SEARCH("Dic",$F9)) -> 1 | S9: =SUM(G9:R9) -> 12
A10: PR-SS-CON | B10: Programa de Sensibilización y Seguimiento a Contratistas y Trabajadores | C10: GESTIÓN DE EMPRESAS CONTRATISTAS | D10: 2 | E10: Sensibilizar al 100% de las empresas contratistas del componente forestal e industrial [(si aplica)] en temas relacionados [a las normas nacionales, estándares internacionales y procesos documentales adoptados de Paracel]. | F10: Mar, Jun, Jul, Ago, Sep, Nov, Dic | G10: =--ISNUMBER(SEARCH("Ene",$F10)) -> 0 | H10: =--ISNUMBER(SEARCH("Feb",$F10)) -> 0 | I10: =--ISNUMBER(SEARCH("Mar",$F10)) -> 1 | J10: =--ISNUMBER(SEARCH("Abr",$F10)) -> 0 | K10: =--ISNUMBER(SEARCH("May",$F10)) -> 0 | L10: =--ISNUMBER(SEARCH("Jun",$F10)) -> 1 | M10: =--ISNUMBER(SEARCH("Jul",$F10)) -> 1 | N10: =--ISNUMBER(SEARCH("Ago",$F10)) -> 1 | O10: =--ISNUMBER(SEARCH("Sep",$F10)) -> 1 | P10: =--ISNUMBER(SEARCH("Oct",$F10)) -> 0 | Q10: =--ISNUMBER(SEARCH("Nov",$F10)) -> 1 | R10: =--ISNUMBER(SEARCH("Dic",$F10)) -> 1 | S10: =SUM(G10:R10) -> 7
A11: PR-SS-SSC | B11: Programa de Salud y Seguridad Comunitaria | C11: SALUD Y SEGURIDAD COMUNITARIA | D11: 1 | E11: Posibilitar la asistencia médica a aproximadamente 1.500 personas de comunidades del área de influencia de Paracel reduciendo la brecha de acceso a los programas y servicios nacionales de salud en el período 2025. | F11: Ene, Feb, Mar, Abr, May, Jun, Jul, Ago, Sep, Oct, Nov, Dic | G11: =--ISNUMBER(SEARCH("Ene",$F11)) -> 1 | H11: =--ISNUMBER(SEARCH("Feb",$F11)) -> 1 | I11: =--ISNUMBER(SEARCH("Mar",$F11)) -> 1 | J11: =--ISNUMBER(SEARCH("Abr",$F11)) -> 1 | K11: =--ISNUMBER(SEARCH("May",$F11)) -> 1 | L11: =--ISNUMBER(SEARCH("Jun",$F11)) -> 1 | M11: =--ISNUMBER(SEARCH("Jul",$F11)) -> 1 | N11: =--ISNUMBER(SEARCH("Ago",$F11)) -> 1 | O11: =--ISNUMBER(SEARCH("Sep",$F11)) -> 1 | P11: =--ISNUMBER(SEARCH("Oct",$F11)) -> 1 | Q11: =--ISNUMBER(SEARCH("Nov",$F11)) -> 1 | R11: =--ISNUMBER(SEARCH("Dic",$F11)) -> 1 | S11: =SUM(G11:R11) -> 12
A12: PR-SS-SSC | B12: Programa de Salud y Seguridad Comunitaria | C12: SALUD Y SEGURIDAD COMUNITARIA | D12: 2 | E12: Distribuir 10.000 kilos de leche del Programa Alimentario Nutricional Integral (PANI) con un alcance de 5.000 personas en el período 2025. | F12: Ene, Feb, Mar, Abr, May, Jun, Jul, Ago, Sep, Oct, Nov, Dic | G12: =--ISNUMBER(SEARCH("Ene",$F12)) -> 1 | H12: =--ISNUMBER(SEARCH("Feb",$F12)) -> 1 | I12: =--ISNUMBER(SEARCH("Mar",$F12)) -> 1 | J12: =--ISNUMBER(SEARCH("Abr",$F12)) -> 1 | K12: =--ISNUMBER(SEARCH("May",$F12)) -> 1 | L12: =--ISNUMBER(SEARCH("Jun",$F12)) -> 1 | M12: =--ISNUMBER(SEARCH("Jul",$F12)) -> 1 | N12: =--ISNUMBER(SEARCH("Ago",$F12)) -> 1 | O12: =--ISNUMBER(SEARCH("Sep",$F12)) -> 1 | P12: =--ISNUMBER(SEARCH("Oct",$F12)) -> 1 | Q12: =--ISNUMBER(SEARCH("Nov",$F12)) -> 1 | R12: =--ISNUMBER(SEARCH("Dic",$F12)) -> 1 | S12: =SUM(G12:R12) -> 12
A13: PR-SS-SSC | B13: Programa de Salud y Seguridad Comunitaria | C13: SALUD Y SEGURIDAD COMUNITARIA | D13: 3 | E13: Sensibilizar a miembros de las comunidades de la zona de influencia de Paracel sobre educación sexual, planificación familiar y prevención de VIH/SIDA, a través de talleres, entrega de insumos, la aplicación de las pruebas de detección de VIH y la vi | F13: Mar, Abr, May, Jun, Jul, Ago, Sep, Oct, Nov, Dic | G13: =--ISNUMBER(SEARCH("Ene",$F13)) -> 0 | H13: =--ISNUMBER(SEARCH("Feb",$F13)) -> 0 | I13: =--ISNUMBER(SEARCH("Mar",$F13)) -> 1 | J13: =--ISNUMBER(SEARCH("Abr",$F13)) -> 1 | K13: =--ISNUMBER(SEARCH("May",$F13)) -> 1 | L13: =--ISNUMBER(SEARCH("Jun",$F13)) -> 1 | M13: =--ISNUMBER(SEARCH("Jul",$F13)) -> 1 | N13: =--ISNUMBER(SEARCH("Ago",$F13)) -> 1 | O13: =--ISNUMBER(SEARCH("Sep",$F13)) -> 1 | P13: =--ISNUMBER(SEARCH("Oct",$F13)) -> 1 | Q13: =--ISNUMBER(SEARCH("Nov",$F13)) -> 1 | R13: =--ISNUMBER(SEARCH("Dic",$F13)) -> 1 | S13: =SUM(G13:R13) -> 10
A14: PR-SS-SSC | B14: Programa de Salud y Seguridad Comunitaria | C14: SALUD Y SEGURIDAD COMUNITARIA | D14: 4 | E14: Apoyar al Ministerio de la Niñez y Adolescencia en la prevención de la violencia hacia la niñez y la adolescencia, en las comunidades del área de influencia de Paracel. | F14: Mar, Abr, May, Jun, Jul, Ago, Sep, Oct, Nov | G14: =--ISNUMBER(SEARCH("Ene",$F14)) -> 0 | H14: =--ISNUMBER(SEARCH("Feb",$F14)) -> 0 | I14: =--ISNUMBER(SEARCH("Mar",$F14)) -> 1 | J14: =--ISNUMBER(SEARCH("Abr",$F14)) -> 1 | K14: =--ISNUMBER(SEARCH("May",$F14)) -> 1 | L14: =--ISNUMBER(SEARCH("Jun",$F14)) -> 1 | M14: =--ISNUMBER(SEARCH("Jul",$F14)) -> 1 | N14: =--ISNUMBER(SEARCH("Ago",$F14)) -> 1 | O14: =--ISNUMBER(SEARCH("Sep",$F14)) -> 1 | P14: =--ISNUMBER(SEARCH("Oct",$F14)) -> 1 | Q14: =--ISNUMBER(SEARCH("Nov",$F14)) -> 1 | R14: =--ISNUMBER(SEARCH("Dic",$F14)) -> 0 | S14: =SUM(G14:R14) -> 9
A15: PR-SS-MSC | B15: Programa de Manejo Social | C15: MANEJO SOCIAL | D15: 1 | E15: Realizar espacios informativos en el año, en las comunidades del área de influencia directa de Paracel. | F15: Jul, Nov | G15: =--ISNUMBER(SEARCH("Ene",$F15)) -> 0 | H15: =--ISNUMBER(SEARCH("Feb",$F15)) -> 0 | I15: =--ISNUMBER(SEARCH("Mar",$F15)) -> 0 | J15: =--ISNUMBER(SEARCH("Abr",$F15)) -> 0 | K15: =--ISNUMBER(SEARCH("May",$F15)) -> 0 | L15: =--ISNUMBER(SEARCH("Jun",$F15)) -> 0 | M15: =--ISNUMBER(SEARCH("Jul",$F15)) -> 1 | N15: =--ISNUMBER(SEARCH("Ago",$F15)) -> 0 | O15: =--ISNUMBER(SEARCH("Sep",$F15)) -> 0 | P15: =--ISNUMBER(SEARCH("Oct",$F15)) -> 0 | Q15: =--ISNUMBER(SEARCH("Nov",$F15)) -> 1 | R15: =--ISNUMBER(SEARCH("Dic",$F15)) -> 0 | S15: =SUM(G15:R15) -> 2
A16: PR-SS-MSC | B16: Programa de Manejo Social | C16: MANEJO SOCIAL | D16: 2 | E16: Alinear expectativas de miembros de las comunidades y otros grupos de interés acerca del funcionamiento de Paracel e inversiones sociales. | F16: Jul, Nov | G16: =--ISNUMBER(SEARCH("Ene",$F16)) -> 0 | H16: =--ISNUMBER(SEARCH("Feb",$F16)) -> 0 | I16: =--ISNUMBER(SEARCH("Mar",$F16)) -> 0 | J16: =--ISNUMBER(SEARCH("Abr",$F16)) -> 0 | K16: =--ISNUMBER(SEARCH("May",$F16)) -> 0 | L16: =--ISNUMBER(SEARCH("Jun",$F16)) -> 0 | M16: =--ISNUMBER(SEARCH("Jul",$F16)) -> 1 | N16: =--ISNUMBER(SEARCH("Ago",$F16)) -> 0 | O16: =--ISNUMBER(SEARCH("Sep",$F16)) -> 0 | P16: =--ISNUMBER(SEARCH("Oct",$F16)) -> 0 | Q16: =--ISNUMBER(SEARCH("Nov",$F16)) -> 1 | R16: =--ISNUMBER(SEARCH("Dic",$F16)) -> 0 | S16: =SUM(G16:R16) -> 2
... A35: PR-SS-RPI | B35: Programa de Relacionamiento con Comunidades Indígenas | C35: COMUNIDADES INDÍGENAS | D35: 6 | E35: Apoyar a referentes de comunidades indígenas en el relacionamiento con instituciones del estado a fin de autogestionar los temas relacionados a su organización comunitaria o política (identidad, vivienda, salud, educación, etc.). | F35: Ene, Feb, Mar, Abr, May, Jun, Jul, Ago, Sep, Oct, Nov, Dic | G35: =--ISNUMBER(SEARCH("Ene",$F35)) -> 1 | H35: =--ISNUMBER(SEARCH("Feb",$F35)) -> 1 | I35: =--ISNUMBER(SEARCH("Mar",$F35)) -> 1 | J35: =--ISNUMBER(SEARCH("Abr",$F35)) -> 1 | K35: =--ISNUMBER(SEARCH("May",$F35)) -> 1 | L35: =--ISNUMBER(SEARCH("Jun",$F35)) -> 1 | M35: =--ISNUMBER(SEARCH("Jul",$F35)) -> 1 | N35: =--ISNUMBER(SEARCH("Ago",$F35)) -> 1 | O35: =--ISNUMBER(SEARCH("Sep",$F35)) -> 1 | P35: =--ISNUMBER(SEARCH("Oct",$F35)) -> 1 | Q35: =--ISNUMBER(SEARCH("Nov",$F35)) -> 1 | R35: =--ISNUMBER(SEARCH("Dic",$F35)) -> 1 | S35: =SUM(G35:R35) -> 12

Sheet 06_DICCIONARIO
A1: 06. DICCIONARIO Y GOBIERNO DE DATOS
A2: Guía mínima para mantener consistencia, trazabilidad y calidad documental en el registro maestro.
A4: Hoja | B4: Rol | C4: Nivel | D4: Llave sugerida | E4: Campos clave | F4: Uso recomendado | G4: Observaciones
A5: Programas Vigentes | B5: Catálogo maestro de programas | C5: Programa | D5: Código | E5: Nombre, versión, estado, ficha | F5: Actualizar cuando cambie el programa vigente | G5: No usar para registrar targets
A6: Historial Versiones | B6: Inventario documental por versión | C6: Documento | D6: Código + Versión + Idioma + Formato | E6: Fecha, estado, archivo | F6: Trazabilidad documental | G6: Permite auditoría de cambios
A7: Fichas Técnicas | B7: Metadatos de fichas técnicas | C7: Ficha | D7: Código Programa + Versión | E7: Propósito, necesidad, objetivo, alcance | F7: Base conceptual del programa | G7: Debe existir una fila por ficha
A8: Targets por Ficha | B8: Plan operativo por target | C8: Target | D8: Código Programa + Target Nº | E8: Descripción, actividades, presupuesto, meses activos | F8: Planeación y seguimiento | G8: Completar fórmula, fuente, periodicidad, responsable
A9: Indicadores | B9: Indicadores agregados por target | C9: Indicador agregado | D9: Código Programa + Target | E9: Indicador, evidencia | F9: Repositorio original | G9: Utilizar 03_INDICADORES_NORMALIZADOS para análisis
A10: 02_MATRIZ_EJECUTIVA | B10: Vista analítica integrada | C10: Registro analítico | D10: ID REGISTRO | E10: Presupuesto normalizado, completitud, incidencias | F10: Seguimiento ejecutivo | G10: Hoja recomendada para reportes
A11: 03_INDICADORES_NORMALIZADOS | B11: Descomposición de indicadores | C11: Indicador individual | D11: ID INDICADOR | E11: Indicador individual, tipo | F11: Filtrado y análisis | G11: Facilita tableros y conteos
A12: 04_CRONOGRAMA_TARGETS | B12: Calendario mensual | C12: Target-Mes | D12: Código + Target Nº | E12: Meses activos | F12: Planeación temporal | G12: Derivado del texto de meses activos
A13: 05_CONTROL_CALIDAD | B13: Control y brechas | C13: Incidencia | D13: Código + Target Nº | E13: Brechas documentales | F13: Priorización de saneamiento | G13: Actualizar tras mejorar campos faltantes

Sheet Programas Vigentes
A1: Código | B1: Nombre | C1: Nombre Corto | D1: Versión | E1: Fecha Act. | F1: Nº Versiones | G1: Tiene PDF | H1: Tiene EN | I1: Tiene Ficha | J1: Estado | K1: Objetivo | L1: Alcance | M1: Marco Legal | N1: Responsable | O1: Metodología
A2: PR-SS-AAE | B2: Programa de Manejo Interno por Afectación de Tierras y Riesgos por Agentes Externos | C2: Manejo Interno por Afectación de Tierras y Riesgos por Agentes Externos | D2: v05 | E2: 2025-07-21 | F2: 4 | G2: Sí | H2: Sí | I2: Sí | J2: Vigente | K2: Prevenir conflictos con terceros ([propietarios/as] de inmuebles utilizados como servidumbre) y delinear protocolos internos para garantizar la seguridad de las personas que conforman los equipos de Paracel y sus [empresas contratistas]. | [FSC-STD-PRY-01-2022] Normas de Desempeño IFC REGISTROS Y/O | L2: [El alcance del programa se presenta a continuación]: DEFINICIONES Área de Influencia Directa (AID) del componente forestal: incluye a [6] distritos en los que se localizan las áreas de las plantacion
A3: PR-SS-CON | B3: Programa de Sensibilización y Seguimiento a Contratistas y Trabajadores | C3: Sensibilización y Seguimiento a Contratistas y Trabajadores | D3: v05 | E3: 2025-07-21 | F3: 4 | G3: Sí | H3: Sí | I3: Sí | J3: Vigente | K3: Acompañar y monitorear a [empresas contratistas y trabajadores/as] para asegurar el cumplimiento de las normativas nacionales y [estándares de sostenibilidad internacionales en materia social]. Monitorear el cumplimiento de buenas prácticas de inclusión indígena en la cadena de valor de Paracel. | [ | L3: [Este programa tiene el siguiente alcance]: DEFINICIONES Área de Influencia Directa (AID) del componente forestal: incluye a [6] distritos en los que se localizan las áreas de las plantaciones foresta
A4: PR-SS-EMU | B4: Programa de Empoderamiento de la Mujer | C4: Empoderamiento de la Mujer | D4: v04 | E4: 2025-07-21 | F4: 4 | G4: Sí | H4: Sí | I4: Sí | J4: Vigente | K4: Empoderar a las mujeres para acortar las brechas de desigualdad étnicas y de género. | [FSC-STD-PRY-01-2022] Normas de Desempeño IFC REGISTROS Y/O ANEXO [Registro del Plan de Comunicación [Registro de Asistencia] Informe de Resultados | L4: El programa de Empoderamiento de la Mujer tiene el siguiente alcance: DEFINICIONES Área de Influencia Directa (AID) del componente indígena: está compuesta por las comunidades indígenas ubicadas entr
A5: PR-SS-MDO | B5: Programa de Desarrollo y Vinculación de Mano de Obra Local | C5: Desarrollo y Vinculación de Mano de Obra Local | D5: v05 | E5: 2025-07-21 | F5: 4 | G5: Sí | H5: Sí | I5: Sí | J5: Vigente | K5: Promover la generación de empleo local a través de la vinculación de mano de obra calificada y no calificada, [además del desarrollo e instalación de capacidades, en el área de influencia de Paracel]. Promover la inclusión laboral de personas de comunidades indígenas en Paracel y [en las empresas] d | L5: DEFINICIONES Área de Influencia Directa (AID) del componente industrial: incluyen 5 distritos cercanos al sitio de la Planta Industrial, incluyendo a 18 comunidades que se encuentran en un radio de 13
A6: PR-SS-MSC | B6: Programa de Manejo Social | C6: Manejo Social | D6: v05 | E6: 2025-07-21 | F6: 4 | G6: Sí | H6: Sí | I6: Sí | J6: Vigente | K6: Identificar las afectaciones generadas por la empresa, buscando minimizarlas, con foco en las comunidades del área de influencia de Paracel. | [FSC-STD-PRY-01-2022] Normas de Desempeño IFC REGISTROS Y/O ANEXO Informe de Visitas Registro de Asistencia [Encuestas] [Acta de Reunión Encuesta de Percepci | L6: El programa de Manejo Social tiene el siguiente alcance: DEFINICIONES Área Directamente Afectada (ADA) del componente industrial: unidades sociales y comunidades situadas en el entorno inmediato de la
A7: PR-SS-MSO | B7: Programa de Monitoreo Social | C7: Monitoreo Social | D7: v05 | E7: 2025-07-21 | F7: 4 | G7: Sí | H7: Sí | I7: No | J7: Vigente | K7: Realizar el monitoreo de la implementación de las medidas y los programas [desarrollados por Paracel] a través de la definición y seguimiento de indicadores de desempeño. Este programa contiene a su vez un subcomponente de monitoreo de la percepción social mediante el cual se podrá contar con inform | L7: El programa de Monitoreo Social tiene el siguiente alcance: DEFINICIONES Área de Influencia Directa (AID) del componente industrial: incluyen 5 distritos cercanos al sitio de la Planta Industrial, inc
A8: PR-SS-PCS | B8: Programa de Prevención y Gestión de Contingencias Sociales | C8: Prevención y Gestión de Contingencias Sociales | D8: v05 | E8: 2025-07-21 | F8: 4 | G8: Sí | H8: Sí | I8: Sí | J8: Vigente | K8: Prevenir y dar una pronta respuesta ante contingencias sociales, tanto en las etapas constructiva y operativa de Paracel en su componente industrial, como en las etapas de instalación, operación y mantenimiento del componente forestal. | [FSC-STD-PRY-01-2022] Normas de Desempeño IFC REGISTROS Y/O AN | L8: El programa de Prevención y Gestión de Contingencias Sociales tiene el siguiente alcance: DEFINICIONES Área de Influencia Directa (AID) del componente industrial: incluyen 5 distritos cercanos al siti
A9: PR-SS-PCU | B9: Programa de Gestión del Patrimonio Cultural | C9: Gestión del Patrimonio Cultural | D9: v05 | E9: 2025-07-21 | F9: 4 | G9: Sí | H9: Sí | I9: Sí | J9: Vigente | K9: Velar por la gestión adecuada del Patrimonio Cultural de las áreas de Influencia Directa de Paracel. | [FSC-STD-PRY-01-2022] Normas de Desempeño IFC REGISTROS Y/O ANEXO [Minuta de reunión] [Informe de trabajo de campo] [Materiales elaborados] [Catálogos elaborados] [Informe] [Reporte de actividades] | L9: El programa de tiene el siguiente alcance: DEFINICIONES Área de Influencia Directa (AID) del componente industrial: incluyen 5 distritos cercanos al sitio de la Planta Industrial, incluyendo a 18 comu
A10: PR-SS-PDP | B10: Programa de Promoción y Desarrollo de Empresas Proveedoras Locales | C10: Promoción y Desarrollo de Empresas Proveedoras Locales | D10: v05 | E10: 2025-07-21 | F10: 4 | G10: Sí | H10: Sí | I10: Sí | J10: Vigente | K10: Impulsar el desarrollo y crecimiento de la economía local a través de la promoción de empresas locales y nacionales como posibles [empresas proveedoras]. | [FSC-STD-PRY-01-2022] Normas de Desempeño IFC Estudio Social del Componente Forestal Estudio Social del Componente Industrial Estudio del Compon | L10: El alcance del programa de detalla a continuación: DEFINICIONES Área de Influencia Directa (AID) del componente industrial: incluyen 5 distritos cercanos al sitio de la Planta Industrial, incluyendo a
A11: PR-SS-QRI | B11: Programa de Gestión de Quejas, Consultas y Sugerencias | C11: Gestión de Quejas, Consultas y Sugerencias | D11: v05 | E11: 2025-07-21 | F11: 4 | G11: Sí | H11: Sí | I11: Sí | J11: Vigente | K11: Garantizar atención a las quejas, sugerencias y consultas de la población de las áreas de influencia de Paracel, [colaboradores/as propios/as y de empresas proveedoras], pueblos indígenas y de la población en general, estableciendo canales de comunicación permanentes. | [FSC-STD-PRY-01-2022] Normas | L11: Este programa es transversal a: DEFINICIONES Área de Influencia Directa (AID) del componente industrial: incluyen 5 distritos cercanos al sitio de la Planta Industrial, incluyendo a 18 comunidades que
A12: PR-SS-RCI | B12: Programa de Relacionamiento con Comunidades e Inversión Social | C12: Relacionamiento con Comunidades e Inversión Social | D12: v05 | E12: 2025-07-21 | F12: 4 | G12: Sí | H12: Sí | I12: Sí | J12: Vigente | K12: Fomentar el desarrollo local y promover el vínculo cercano entre las comunidades y la empresa. Mejorar la capacidad de producción y de innovación para la agregación de valor a las actividades generadoras de ingresos de las familias indígenas y de las áreas de influencia de Paracel. Apoyar la mejora | L12: DEFINICIONES Área de Influencia Directa (AID) del componente industrial: incluyen 5 distritos cercanos al sitio de la Planta Industrial, incluyendo a 18 comunidades que se encuentran en un radio de 13
A13: PR-SS-RPI | B13: Programa de Relacionamiento con Comunidades Indígenas | C13: Relacionamiento con Comunidades Indígenas | D13: v05 | E13: 2025-07-21 | F13: 4 | G13: Sí | H13: Sí | I13: Sí | J13: Vigente | K13: Establecer y mantener una relación continua con los Pueblos Indígenas fomentando el pleno respeto a los derechos humanos, dignidad, aspiraciones, cultura y medios de subsistencia dependientes de los recursos naturales de los Pueblos Indígenas. | [FSC-STD-PRY-01-2022] Normas de Desempeño IFC REGISTRO | L13: El programa de Relacionamiento con Comunidades Indígenas tiene el siguiente alcance: DEFINICIONES Área de Influencia Directa (AID) del componente indígena: está compuesta por las comunidades indígena
... A15: PR-SS-SSC | B15: Programa de Salud y Seguridad Comunitaria | C15: Salud y Seguridad Comunitaria | D15: v06 | E15: 2025-12-09 | F15: 5 | G15: Sí | H15: Sí | I15: Sí | J15: Vigente | K15: Implementar un programa eficiente para promover el cuidado de la higiene, la seguridad y la salud de la población con énfasis en la prevención de enfermedades que pudieran relacionarse con el aumento de la población de trabajadores/as. Prevenir y mitigar los impactos negativos en salud y seguridad q | L15: El programa de Salud y Seguridad Comunitaria tiene el siguiente alcance: DEFINICIONES Área de Influencia Directa (AID) del componente industrial: incluyen 5 distritos cercanos al sitio de la Planta In

Sheet Historial Versiones
A1: Código | B1: Nombre | C1: Versión | D1: Versión Nº | E1: Fecha | F1: Estado | G1: Idioma | H1: Formato | I1: Archivo
A2: PR-SS-AAE | B2: Programa de Manejo Interno por Afectación de Tierras y Riesgos por Agentes Externos | C2: v01 | D2: 1 | E2: 2021-04-15 | F2: Obsoleto | G2: Español | H2: DOCX | I2: 210415 PR-SS-AAE - Programa de Manejo Interno por Afectación de Tierras y Riesgos por Agentes Externos v01.docx
A3: PR-SS-AAE | B3: Internal Management Program for Land Affection and Risks by External Agents | C3: v01 | D3: 1 | E3: 2021-04-15 | F3: Obsoleto | G3: Inglés | H3: DOCX | I3: 210415 PR-SS-AAE - Internal Management Program for Land Affection and Risks by External Agents v01.docx
A4: PR-SS-AAE | B4: Programa de Manejo Interno por Afectación de Tierras y Riesgos por Agentes Externos | C4: v02 | D4: 2 | E4: 2022-01-04 | F4: Obsoleto | G4: Inglés | H4: DOCX | I4: 220104 PR-SS-AAE - Programa de Manejo Interno por Afectación de Tierras y Riesgos por Agentes Externos v02.docx
A5: PR-SS-AAE | B5: Programa de Manejo Interno por Afectación de Tierras y Riesgos por Agentes Externos | C5: v03 | D5: 3 | E5: 2023-05-28 | F5: Vigente | G5: Español | H5: PDF | I5: 230528 PR-SS-AAE - Programa de Manejo Interno por Afectación de Tierras y Riesgos por Agentes Externos v03.pdf
A6: PR-SS-AAE | B6: Programa de Manejo Interno por Afectación de Tierras y Riesgos por Agentes Externos | C6: v03 | D6: 3 | E6: 2023-05-28 | F6: Obsoleto | G6: Español | H6: DOCX | I6: 230528 PR-SS-AAE - Programa de Manejo Interno por Afectación de Tierras y Riesgos por Agentes Externos v03.docx
A7: PR-SS-AAE | B7: Programa de Manejo Interno por Afectación de Tierras y Riesgos por Agentes Externos | C7: v04 | D7: 4 | E7: 2024-04-04 | F7: Obsoleto | G7: Español | H7: DOCX | I7: 240404 PR-SS-AAE - Programa de Manejo Interno por Afectación de Tierras y Riesgos por Agentes Externos v04.docx
A8: PR-SS-AAE | B8: Programa de Manejo Interno por Afectación de Tierras y Riesgos por Agentes Externos | C8: v05 | D8: 5 | E8: 2025-07-21 | F8: Vigente | G8: Español | H8: DOCX | I8: 250721 PR-SS-AAE - Programa de Manejo Interno por Afectación de Tierras y Riesgos por Agentes Externos v05.docx
A9: PR-SS-CON | B9: Programa de Sensibilización y Seguimiento a Contratistas y Trabajadores | C9: v01 | D9: 1 | E9: 2021-04-15 | F9: Obsoleto | G9: Español | H9: DOCX | I9: 210415 PR-SS-CON - Programa de Sensibilización y Seguimiento a Contratistas y Trabajadores v01.docx
A10: PR-SS-CON | B10: Awareness and Follow-Up Program for Contractors and Workers Regarding Compliance with Regulations | C10: v01 | D10: 1 | E10: 2021-04-15 | F10: Obsoleto | G10: Inglés | H10: DOCX | I10: 210415 PR-SS-CON - Awareness and Follow-Up Program for Contractors and Workers Regarding Compliance with Regulations v01.docx
A11: PR-SS-CON | B11: Programa de Sensibilización y Seguimiento a Contratistas y Trabajadores | C11: v02 | D11: 2 | E11: 2022-01-04 | F11: Obsoleto | G11: Inglés | H11: DOCX | I11: 220104 PR-SS-CON - Programa de Sensibilización y Seguimiento a Contratistas y Trabajadores v02.docx
A12: PR-SS-CON | B12: Programa de Sensibilización y Seguimiento a Contratistas y Trabajadores | C12: v03 | D12: 3 | E12: 2023-05-28 | F12: Vigente | G12: Español | H12: PDF | I12: 230528 PR-SS-CON - Programa de Sensibilización y Seguimiento a Contratistas y Trabajadores v03.pdf
A13: PR-SS-CON | B13: Programa de Sensibilización y Seguimiento a Contratistas y Trabajadores | C13: v03 | D13: 3 | E13: 2023-05-28 | F13: Obsoleto | G13: Español | H13: DOCX | I13: 230528 PR-SS-CON - Programa de Sensibilización y Seguimiento a Contratistas y Trabajadores v03.docx
... A101: PR-SS-SSC | B101: Programa de Salud y Seguridad Comunitaria | C101: v06 | D101: 6 | E101: 2025-12-09 | F101: Vigente | G101: Español | H101: DOCX | I101: 251209 PR-SS-SSC - Programa de Salud y Seguridad Comunitaria v06.docx

Sheet Fichas Técnicas
A1: Nombre Ficha | B1: Código Programa | C1: Versión | D1: Fecha | E1: Propósito | F1: Necesidad | G1: Objetivo | H1: Alcance | I1: Responsable | J1: Nº Targets | K1: Presupuesto Total USD | L1: Archivo
A2: PROGRAMA DE DESARROLLO Y VINCULACIÓN CON LA MANO DE OBRA LOCAL | B2: PR-SS-MDO | C2: v01 | D2: 2025-06-04 | E2: Desarrollar e instalar competencias y capacidades técnicas y profesionales en el área de influencia de Paracel | F2: - Falta de competencias técnicas y profesionales en la mano de obra local y departamental. - Centralización en la ciudad Concepción de los servicios de educación técnico y profesional. - Población | J2: 2 | K2: 14851 | L2: 250604 - FICHA TÉCNICA - PROGRAMA DE DESARROLLO Y VINCULACIÓN CON LA MANO DE OBRA LOCAL v01.xlsx
A3: EMPODERAMIENTO DE LA MUJER | B3: PR-SS-EMU | C3: v01 | D3: 2025-06-04 | E3: Empoderar a las mujeres para acortar las brechas de desigualdad étnicas y de género. | F3: Las mujeres no participan plenamente de todos los sectores y todos los niveles de la actividad económica, y por ende no se construyen economías fuertes, y esto conlleva a no cumplir los objetivos de | J3: 2 | K3: 0 | L3: 250604 - FICHA TÉCNICA - EMPODERAMIENTO DE LA MUJER v01.xlsx
A4: GESTIÓN DE EMPRESAS CONTRATISTAS | B4: PR-SS-CON | C4: v00 | D4: 2025-06-04 | E4: Acompañar y monitorear a [empresas contratistas y trabajadores/as] para asegurar el cumplimiento de las normativas nacionales y [estándares de sostenibilidad internacionales en materia social]. Monitorear el cumplimiento de buenas prácticas de inclusión indígena en la cadena de valor de Paracel. | F4: Incumplimiento de normativas nacionales e estándares internacionales, y de los requisitos establecidos por Paracel a las empresas proveedoras por falta de conocimineto y experiencia por parte de empre | J4: 2 | K4: 0 | L4: 250604- FICHA TÉCNICA - GESTIÓN DE EMPRESAS CONTRATISTAS v00.xlsx
A5: SALUD Y SEGURIDAD COMUNITARIA | B5: PR-SS-SSC | C5: v01 | D5: 2025-06-04 | E5: Implementar un programa eficiente para promover el cuidado de la higiene, la seguridad y la salud de la población con énfasis en la prevención de enfermedades que pudieran relacionarse con el aumento de la población trabajadora. Prevenir y mitigar impactos negativos en la salud y seguridad que podr | F5: Poco acceso a servicios de salud por parte de los miembros de las comunidades y falta de conocimiento sobre planificación familiar y ETS. | J5: 4 | K5: 1115565001895 | L5: 250604- FICHA TÉCNICA - SALUD Y SEGURIDAD COMUNITARIA v01.xlsx
A6: MANEJO SOCIAL | B6: PR-SS-MSC | C6: v01 | D6: 2025-06-05 | E6: Identificar las afectaciones generadas por la empresa, buscando minimizarlas, con foco en las comunidades del área de influencia de Paracel. | F6: Contar con información sobre la percepción y expectativas de los miembros de las comunidades con relación a desempeño de Paracel, a fin de establacer acciones de mejora. | J6: 2 | K6: 14486 | L6: 250605- FICHA TÉCNICA - MANEJO SOCIAL v01.xlsx
A7: PREVENCIÓN CONTINGENCIAS SOCIALES | B7: PR-SS-PCS | C7: v01 | D7: 2025-06-09 | E7: Prevenir y dar una pronta respuesta ante contingencias sociales, tanto en las etapas constructiva y operativa de Paracel en su componente industrial, como en las etapas de instalación, operación y mantenimiento del componente forestal. | F7: Gestionar de forma adecuada las respuestas ante las contingencias sociales que pudieran ser generadas a raíz de las intervenciones operacionales de Paracel con los diferentes grupos de interés. | J7: 2 | K7: 6708 | L7: 250609 - FICHA TÉCNICA - PREVENCIÓN CONTINGENCIAS SOCIALES v01.xlsx
A8: MANEJO INTERNO POR AFECTACIÓN DE TIERRAS Y RIESGO POR AGENTES EXTERNOS | B8: PR-SS-AAE | C8: v00 | D8: 2025-06-11 | E8: Prevenir conflictos con terceros (propietarios/as de inmuebles utilizados como servidumbre) y delinear protocolos internos para garantizar la seguridad de las personas que conforman los equipos de Paracel y sus empresas contratistas. | F8: Formalizar los acuerdos con propietarios/as de inmuebles vecinos y con miembros de las comunidades en caso de que aplique con relación al uso de caminos. Reducir los riesgos de conflictos. | J8: 2 | K8: 0 | L8: 250611 - FICHA TÉCNICA - MANEJO INTERNO POR AFECTACIÓN DE TIERRAS Y RIESGO POR AGENTES EXTERNOS v00.xlsx
A9: GESTIÓN DE QUEJAS, CONSULTAS Y SUGERENCIAS | B9: PR-SS-QRI | C9: v01 | D9: 2025-06-18 | E9: Garantizar atención a las quejas, sugerencias y consultas de la población de las áreas de influencia de Paracel, colaboradores/as propios/as y de empresas proveedoras, pueblos indígenas y de la población en general, estableciendo canales de comunicación permanentes. | F9: Temores y expectativas generadas en la población y las comunidades indígenas, afectación de la red social y comunitaria, de los servicios ecosistémicos, cambio en la calidad de vida, usos y costumbres | J9: 2 | K9: 0 | L9: 250618- FICHA TÉCNICA - GESTIÓN DE QUEJAS, CONSULTAS Y SUGERENCIAS v01.xlsx
A10: PATRIMONIO CULTURAL | B10: PR-SS-PCU | C10: v01 | D10: 2025-06-18 | E10: Velar por la gestión adecuada del Patrimonio Cultural de las Áreas de Influencia Directa de Paracel. | F10: Desconocimiento y falta de comunicación en la comunidad de la zona de influencia de Paracel, sobre el significado e implicancias del Patrimonio Cultural, sus posibles pérdidas y/o daños. | J10: 2 | K10: 0 | L10: 250618- FICHA TÉCNICA - PATRIMONIO CULTURAL v01.xlsx
A11: APICULTURA | B11: PR-SS-PDP | C11: v00 | D11: 2025-06-22 | F11: - Falta de diversificación de rubros en seguridad alimentaria de las familias indígenas. - Técnicas apícolas desactualizadas que afectan y ponen en peligro al medio ambiente. - Dificultad en producc | J11: 0 | K11: 0 | L11: 250622 - FICHA TÉCNICA - APICULTURA.xlsx
A12: INFRAESTRUCTURA SOCIAL | B12: PR-SS-RCI | C12: v01 | D12: 2025-06-22 | F12: - Mejora la infraestructura existente. | J12: 2 | K12: 275831 | L12: 250622 - FICHA TÉCNICA -INFRAESTRUCTURA SOCIAL v01.xlsx
A13: ASOCIACIÓN DE PESCADORES | B13: PR-SS-PDP | C13: v01 | D13: 2025-06-23 | E13: Fortalecer la profesionalización y formalización de pescadores/as. | F13: - Falta de canales formales para la comercialización de productos derivados de la pesca. - Falta de formalización de los miembros de las asociaciones y de las asociaciones. | J13: 1 | K13: 0 | L13: 250623 - FICHA TÉCNICA - ASOCIACIÓN DE PESCADORES v01.xlsx
A14: DESARROLLO DE PROVEEDORES LOCALES | B14: PR-SS-PDP | C14: v01 | D14: 2025-06-23 | E14: Impulsar el desarrollo y crecimiento de la economía local a través de la promoción de empresas locales y nacionales como posibles empresas proveedoras. | F14: Diversificación de ingresos de pequeños productores y capital semilla para el desarrollo de plantaciones. | J14: 2 | K14: 0 | L14: 250623 - FICHA TÉCNICA - DESARROLLO DE PROVEEDORES LOCALES v01.xlsx
A15: PEQUEÑOS PRODUCTORES | B15: PR-SS-PDP | C15: v01 | D15: 2025-06-23 | F15: - Falta de seguridad alimentaria de las familias rurales e indígenas. - Dificultad en producción debido a la falta de conocimiento técnico, del cambios climaticos y acceso a recursos (agua, semillas | J15: 0 | K15: 0 | L15: 250623 - FICHA TÉCNICA -PEQUEÑOS PRODUCTORES v01.xlsx
A16: COMUNIDADES INDÍGENAS | B16: PR-SS-RPI | C16: v01 | D16: 2025-06-23 | J16: 6 | K16: 34350 | L16: 250623- FICHA TÉCNICA - COMUNIDADES INDÍGENAS v01.xlsx

Sheet Targets por Ficha
A1: Ficha | B1: Código Programa | C1: Target Nº | D1: Descripción | E1: Actividades | F1: Indicador | G1: Fórmula | H1: Fuente | I1: Periodicidad | J1: Responsable | K1: Evidencia | L1: Productos | M1: Resultado Final | N1: Presupuesto | O1: Enero | P1: Febrero | Q1: Marzo | R1: Abril | S1: Mayo | T1: Junio | U1: Julio | V1: Agosto | W1: Septiembre | X1: Octubre | Y1: Noviembre | Z1: Diciembre | AA1: Meses Activos
A2: PROGRAMA DE DESARROLLO Y VINCULACIÓN CON LA MANO DE OBRA LOCAL | B2: PR-SS-MDO | C2: 1 | D2: Contribuir para aumentar el número de jóvenes y adultos con competencias técnicas y profesionales, para acceder al empleo (el trabajo decente) a través del desarrollo de [10] cursos de capacitación, y [8] jornadas de certificación laboral por compet | E2: 1. Selección de organizaciones aliadas para el desarrollo de las capacitaciones y las certificaciones. 2. Suscribir convenios con instituciones educativas locales y nacionales con el fin de acordar un marco de cooperación para la formación y capacit | F2: - Indicadores de Educación - Indicadores de Empleo | L2: 1 - Convenios / acuerdos. 2 - Curso de capacitación 3 - Jornadas de certificación. 4 - Base de datos de personas que culminaron los cursos y certificaciones. 4- Informe de línea de base. 5- Proyecto | M2: - Aumento del número de jóvenes y adultos con competencias técnicas y profesionales para acceder al empleo (trabajo decente). - Profesionales certificados para acceder al empleo (trabajo decente o | S2: 4 | T2: 4 | U2: 4 | 6 | V2: 4 | 6 | W2: 4 | 6 | X2: 4 | 6 | Y2: 4 | 6 | Z2: 7 | AA2: May, Jun, Jul, Ago, Sep, Oct, Nov, Dic
A3: PROGRAMA DE DESARROLLO Y VINCULACIÓN CON LA MANO DE OBRA LOCAL | B3: PR-SS-MDO | C3: 2 | D3: Becar a jóvenes de las comunidades del área e influencia de Paracel: - 10 jóvenes para educación en Bachiller Técnico. - 11 jóvenes para educación Terciaria. | E3: 1 - Seleccionar a las personas jóvenes conforme a criterios de elegibilidad. 2 - Medición de la línea de base. 3 - Buscar aliados estratégicos para la implementación del proyecto de becas (si aplica). 4 - Firma de carta compromiso. 5- Llamado inter | F3: 1. Indicadores socioeconómicos. 2. Número de personas beneficiadas clasificadas por edad, sexo, comunidad, etnía. 3. Nivel academico alcanzado por los padres/tutores - hermanos/as mayores. 4. Número d | L3: Jóvenes con estudios técnicos y terciarios finalizados. | M3: Jóvenes con estudios técnicos y terciarios finalizados. | N3: 14.851 | P3: 1 | Q3: 2 | 4 | R3: 6 | S3: 6 | T3: 1 | 5 | 6 | U3: 2 | 4 | 6 | V3: 6 | W3: 6 | X3: 6 | Y3: 6 | Z3: 7 | 8 | AA3: Feb, Mar, Abr, May, Jun, Jul, Ago, Sep, Oct, Nov, Dic
A4: EMPODERAMIENTO DE LA MUJER | B4: PR-SS-EMU | C4: 1 | D4: Difundir la Ruta de Auxilio desarrollada en el año 2024 con foco en los siguientes municipios: Concepción, Paso Barreto, Sargento José Felix López, Paso Horqueta, alcanzando como mínimo al 80% de las comunidades del área de influencia de Paracel. | E4: 1. Selección de las áreas geográficas a ser intervenidas (componentes) y comunidades alcanzadas. 2. Difusión de los materiales. 3. Desarrollo del informe final. | F4: - Número de personas alcanzadas clasificadas sexo, edad, etnia, comunidad, institución, etc. - N° de materiales desarrollados y difundidos. | L4: 1. Materiales difundidos. 2. Informe final. | M4: Personas de las comunidades del área de influencia de Paracel con información la ruta de auxilio ante casos de violencia hacia las mujeres. | N4: 0 | T4: 1 | 2 | U4: 2 | X4: 2 | Y4: 2 | Z4: 3 | AA4: Jun, Jul, Oct, Nov, Dic
A5: EMPODERAMIENTO DE LA MUJER | B5: PR-SS-EMU | C5: 2 | D5: Fortalecer la red de apoyo para las mujeres de la Región de Concepción desarrollando como mínimo 3 espacios. | E5: 1. Propiciar espacios de intercambio de conocimientos, experiencias y aprendizajes con la red de mujeres y referentes invitadas por Paracel. 2. Desarrollo del informe final. | F5: - Número de personas que participaron de los espacios desagregadas por sexo, edad, etnia, organización, etc. - Número de horas de los espacios. - Número de espacios propociados. - Número de temas a | L5: 1. Informe final. | M5: Mujeres de la red de apoyo con mayor conocimiento para afrontar los desafíos de las mujeres en la sociedad. | N5: 0 | U5: 1 | W5: 1 | Y5: 1 | Z5: 2 | AA5: Jul, Sep, Nov, Dic
A6: GESTIÓN DE EMPRESAS CONTRATISTAS | B6: PR-SS-CON | C6: 1 | D6: Auditar de forma trimestral a empresas contratistas del componente Forestal e Industrial (si aplica) en materia de sustentabilidad social considerando las normativas nacionales e internacionales adoptadas por Paracel, en el marco del respeto de los d | E6: 1. Selección de empresas contratistas a ser auditadas (el número de empresas puede aumentar dependiendo de los hallazgos de No Conformidades). 2. Desarrollo de las auditorías trimestrales. 3. Acompañamiento mensual para la revisión de los planes de a | F6: - Número de empresas auditadas. - Proporción de empresas auditadas con relación al número total de empresas. - Número total de hallazgos. - Número total de observaciones y oportunidades de mejora. | L6: Informes de Auditoría Manual de Buenas Prácticas de Manufactura. | M6: - Cumplimiento de las normativas nacionales e internaciones. - Respeto en la vinculación con comunidades indígenas y rurales. | N6: ---- | O6: 1 | P6: 1 | Q6: 2 | 3 | 4 | R6: 3 | S6: 3 | 4 | T6: 2 | 3 | U6: 3 | 4 | 5 | V6: 3 | W6: 2 | 3 | 4 | X6: 3 | Y6: 3 | 4 | Z6: 2 | 3 | AA6: Ene, Feb, Mar, Abr, May, Jun, Jul, Ago, Sep, Oct, Nov, Dic
A7: GESTIÓN DE EMPRESAS CONTRATISTAS | B7: PR-SS-CON | C7: 2 | D7: Sensibilizar al 100% de las empresas contratistas del componente forestal e industrial [(si aplica)] en temas relacionados [a las normas nacionales, estándares internacionales y procesos documentales adoptados de Paracel]. | E7: 1. Desarrollar un plan de capacitación para las áreas administrativas de las empresas contratistas, sobre principios establecidos en los estándares y procesos documentales adoptados por Paracel. 2. Implementar las capacitaciones conforme al plan de | F7: - Número de personas participantes clasificados por organización, cargo, rango etario, sexo, comunidad, etnia. - Número de horas de capacitación. - Número de temas desarrollados. - Datos sobre cono | L7: Plan de Capacitación Capacitaciones | M7: Empresas más sensibilizadas y con conocimiento. | Q7: 3 | 4 | T7: 3 | 4 | U7: 1 | V7: 2 | W7: 3 | 4 | Y7: 2 | Z7: 3| 4 | AA7: Mar, Jun, Jul, Ago, Sep, Nov, Dic
A8: SALUD Y SEGURIDAD COMUNITARIA | B8: PR-SS-SSC | C8: 1 | D8: Posibilitar la asistencia médica a aproximadamente 1.500 personas de comunidades del área de influencia de Paracel reduciendo la brecha de acceso a los programas y servicios nacionales de salud en el período 2025. | E8: 1.Lograr una vinculación cercana con las Unidades de Salud Familiar y los Centros de Salud del ADA y AID y con el Ministerio de Salud Pública y Bienestar Social, [a través de las regionales de salud de Concepción y Amambay]. 2.Selección de las comuni | F8: - Número de alianzas firmadas. - Número de personas que participaron de las asistencia desagregadas por sexo, edad, etnia, comunidad, etc. - Número de USF intervenidas. - Número de especialidades mé | L8: 1. Convenios 2. Informe de línea de base. 3. Registros de servicios. 4. Informe final. | M8: 1.500 personas asistidas | N8: . 16.585 | O8: 1 | P8: 1 | Q8: 1 | 2 | R8: 3 | 4 | S8: 3 | 4 | T8: 3 | 4 | U8: 3 | 4 | V8: 3 | 4 | W8: 3 | 4 | X8: 3 | 4 | Y8: 3 | 4 | Z8: 5 | AA8: Ene, Feb, Mar, Abr, May, Jun, Jul, Ago, Sep, Oct, Nov, Dic
A9: SALUD Y SEGURIDAD COMUNITARIA | B9: PR-SS-SSC | C9: 2 | D9: Distribuir 10.000 kilos de leche del Programa Alimentario Nutricional Integral (PANI) con un alcance de 5.000 personas en el período 2025. | E9: 1. Generar alianzas con la Primera Región Sanitaria. 2. Seleccionar las USF a ser intervenidas (PANI). 3. Distribución y entrega de las leches en las USF seleccionadas. 4. Selección de las USF a ser intervenidas (PAI). 5. Jornadas de inmunización en | F9: - Número de alianzas firmadas. - Número de personas alcanzadas en la distribución de leche desagregadas por sexo, edad, etnia, comunidad, etc. - Número de personas alcanzadas en jornadas de inmunizac | L9: 1. Convenios 2. Informe de línea de base. 3. Registros de servicios. 4. Informe final. | M9: 5.000 personas beneficiadas. | N9: 11.155 = 6.494 + 4.661 | O9: 1 | P9: 1 | Q9: 1 | 2 | 4 | R9: 3 | 5 | 6 | S9: 3 | 5 | 6 | T9: 3 | 5 | 6 | U9: 3 | 5 | 6 | V9: 3 | 5 | 6 | W9: 3 | 5 | 6 | X9: 3 | 5 | 6 | Y9: 3 | 5 | 6 | Z9: 7 | AA9: Ene, Feb, Mar, Abr, May, Jun, Jul, Ago, Sep, Oct, Nov, Dic
A10: SALUD Y SEGURIDAD COMUNITARIA | B10: PR-SS-SSC | C10: 3 | D10: Sensibilizar a miembros de las comunidades de la zona de influencia de Paracel sobre educación sexual, planificación familiar y prevención de VIH/SIDA, a través de talleres, entrega de insumos, la aplicación de las pruebas de detección de VIH y la vi | E10: 1. Generar alianzas con la Cruz Roja Paraguaya, la Primera Región Sanitaria y el PRONASIDA. 2. Desarrollar capacitaciones / talleres sobre salud sexual y reproductiva, incluidos los de planificación familiar. Ayudar a tomar conciencia acerca de enfer | F10: - Número de alianzas generadas. - Número comunidades abordadas. - Número de personas beneficiadas desagregadas por sexo, edad, etnia, comunidad, etc. - Número de personas vinculadas al programa ext | L10: 1. Convenio 2. Sistematización de los talleres (materiales, contenido, etc.). 3. Informe final. | M10: Comunidades sensibilizadas en temas relacionados a Prevención de VIH|SIDA, Planificación Familiar y testeos. | N10: . 10.649 | Q10: 1 | 3 | R10: 4 | S10: 1 | 4 | T10: 1 | 4 | U10: 2 | 4 | 5 | 6 | 7 | V10: 2 | 4 | 5 | 6 | 7 | W10: 2 | 4 | 5 | 6 | 7 | X10: 2 | 4 | 5 | 6 | 7 | Y10: 2 | 4 | 5 | 6 | 7 | Z10: 2 | 5 | 8 | AA10: Mar, Abr, May, Jun, Jul, Ago, Sep, Oct, Nov, Dic
A11: SALUD Y SEGURIDAD COMUNITARIA | B11: PR-SS-SSC | C11: 4 | D11: Apoyar al Ministerio de la Niñez y Adolescencia en la prevención de la violencia hacia la niñez y la adolescencia, en las comunidades del área de influencia de Paracel. | E11: 1. Planificar las acciones considerando el marco de cooperación | selección de las comunidades. 2. Implementación de las actividades planificadas. | F11: - Número de personas formadas como facilitadoras. - Número de instituciones representadas. - Número de personas alcanzadas en espacios de sensibilización clasificadas por edad y sexo. - Número de | L11: Informe final. | M11: Personas formadas y sensibilizadas en prevencion de violencia hacia niñez y la adolescencia. | N11: . 30.000 | Q11: 1 | R11: 2 | S11: 2 | T11: 2 | U11: 2 | V11: 2 | W11: 2 | X11: 2 | Y11: 2 | AA11: Mar, Abr, May, Jun, Jul, Ago, Sep, Oct, Nov
A12: MANEJO SOCIAL | B12: PR-SS-MSC | C12: 1 | D12: Realizar espacios informativos en el año, en las comunidades del área de influencia directa de Paracel. | E12: 1. Reuniones semestrales con pobladores del ADA, AID y con las comunidades indígena para transferir información sobre Paracel, acompañar y monitorear la percepción de los mismos con relación a Paracel. 2. Toma de datos acerca de la percepción de las | F12: 1. Número de personas participantes por comunidad clasificadas, por edad, sexo, franja etaria, comunidad, etnia. 2. Índice de percepción. 3. Datos sobre migración 4. Materiales desarrollados. 5. Núme | L12: - Informe de percepción. - Materiales informativos | educativos desarrollados. | M12: - Miembros de las comunidades informados. - Mejora continua en nuestros procesos con relación a expectativas de los miembros de las comunidades. | N12: 8.442 | U12: 1 | 2 | Y12: 1 | 2 | AA12: Jul, Nov
A13: MANEJO SOCIAL | B13: PR-SS-MSC | C13: 2 | D13: Alinear expectativas de miembros de las comunidades y otros grupos de interés acerca del funcionamiento de Paracel e inversiones sociales. | E13: 1. Reuniones semestrales con los líderes y lideresas de las comunidades rurales e indígenas del área de influencia de Paracel, para la socialización y actualización de las actividades desarrolladas en el marco de los programas sociales de la empresa. | F13: 1. Número de personas participantes por comunidad clasificadas, por edad, sexo, franja etaria, comunidad, etnia. 2. Índice de percepción. 3. Materiales desarrollados. 4. Número de personas de las dife | L13: - Informe de percepción. - Materiales informativos | educativos desarrollados. | M13: - Líderes y lideresas de las comunidades informados/as. - Mejora continua en nuestros procesos con relación a expectativas de los miembros de las comunidades. | N13: 6.044 | U13: 1 | Y13: 1 | 2 | AA13: Jul, Nov
A14: PREVENCIÓN CONTINGENCIAS SOCIALES | B14: PR-SS-PCS | C14: 1 | D14: Fortalecer la prevención de incendios forestales en 8 comunidades del área de influencia de Paracel mediante acciones de concientización y capacitación. Además, lograr la conformación de una brigada comunitaria. | E14: 1- Contratar a la empresa consultora para el desarrollo de los talleres, y/o generar alianzas. 2- Identificación y selección de comunidades a intervenir con el desarrollo de los espacios de concientización y capacitación de prevención de incendios fo | F14: 1. N° de talleres realizados. 2. N° de personas participantes. 3. N° de personas que conforman la brigada. 4. N° de personas entrenadas. 5. N° de reuniones y acuerdos realizados. | L14: - Informe final de actividades. - Materiales informativos - educativos desarrollados. - Informe de datos acerca de conocimientos adquiridos. | M14: - Prevención de incendios forestales. - Mejora en los procesos de respuesta e intervención en casos de incendios forestales. | N14: 5.887 | T14: 1 | U14: 1 | 2 | V14: 2 | 3 | W14: 3 | X14: 3 | AA14: Jun, Jul, Ago, Sep, Oct
A15: PREVENCIÓN CONTINGENCIAS SOCIALES | B15: PR-SS-PCS | C15: 1 | D15: Además, lograr la conformación de una brigada comunitaria. | E15: 1. Selección de organización con experiencia para la conformación de la brigada comunitaria en la comunidad indígena Takuarita. 2. Taller rural participativo para la conformación de brigada comunitaria con la comunidad indígena Takuarita. 3. Desarrol | F15: 1. N° de talleres realizados. 2. N° de personas participantes. 3. N° de personas que conforman la brigada. 4. N° de personas entrenadas. 5. N° de reuniones y acuerdos realizados. | L15: - Brigada comunitaria conformada. | M15: - Prevención de incendios forestales y capacidad de respuesta ante situaciones críticas. | N15: 821 | T15: 1 | U15: 1 | 2 | V15: 2 | 3 | W15: 3 | 4 | AA15: Jun, Jul, Ago, Sep
A16: MANEJO INTERNO POR AFECTACIÓN DE TIERRAS Y RIESGO POR AGENTES EXTERNOS | B16: PR-SS-AAE | C16: 1 | D16: Contar con acuerdos de servidumbre de paso con el 100% de las estancias vecinas de las propiedades forestales con el fin de garantizar el libre tránsito de los miembros de Paracel y empresas contratistas. | E16: 1.Actualización del mapeo de las propiedades utilizadas como acceso y salida (componente forestal e indígena), [con el área de Seguridad Corporativa para el diseño del corredor de accesos y/o caminos alternativos a ser utilizados por personas externa | F16: 1- N° de propiedades a ser utilizadas como servidumbre de paso 2- N° de documentos elaborados 3- N° de comunicados elaborados 4- N° de comunicados emitidos 5- N° de reuniones 6- N° de personas partici | L16: Acuerdos de servidumbre de paso. | M16: Granatizar el libre tránsito de los miembros de Paracel y empresas contratistas. | T16: 1 | U16: 1 | 3 | V16: 1 | 4 | W16: 2 | X16: 2 | 3 | Y16: 4 | 5 | Z16: 5 | AA16: Jun, Jul, Ago, Sep, Oct, Nov, Dic
A17: MANEJO INTERNO POR AFECTACIÓN DE TIERRAS Y RIESGO POR AGENTES EXTERNOS | B17: PR-SS-AAE | C17: 2 | D17: Velar porque el 100% de colaboradores/as de empresas proveedoras de servicio de seguridad corporativa se encuentren sensibilizados/as en materia de Derechos Humanos. | E17: 1. Solicitar al área de Compras/Seguridad Corporativa un informe trimestral sobre registros de entrenamiento en temas de Derechos Humanos a colaboradores/as de empresas proveedoras de servicios de seguridad y control de acceso. Paracel resguardará qu | F17: 1- N° de personas trabajando en el área de seguridad y control de acceso (clasificadas, edad, sexo, comunidad, etnia, región, etc.). 2- N° de personas formadas en materia de Derechos Humanos clasifica | L17: Informes | M17: Reducir la probabilidad de que existan desvíos en la conducta del equipo de seguridad con relación a temas de Derechos Humanos. | T17: 1 | 2 | W17: 1 | 2 | Z17: 1 | 2 | AA17: Jun, Sep, Dic
A18: GESTIÓN DE QUEJAS, CONSULTAS Y SUGERENCIAS | B18: PR-SS-QRI | C18: 1 | D18: El 100% de casos ingresados a través de los diferentes canales establecidos por Paracel atendidos/gestionados. | E18: 1. Funcionamiento del canal externo de atención de quejas. 2. Socializar el procedimiento de gestión de quejas, sugerencias y consultas con todas las partes interesadas de Paracel y los canales correspondientes. 3. Seguimiento y verificación del func | F18: - Número de quejas, consultas y sugerencias clasificadas por tipo y origen interno (nómina) y externo (contratistas y comunidad). - Número de actividades/acciones de socialización. - Número de perso | L18: - Sistema de gestión de quejas, sugerencias y consultas. - Informe de seguimientiento a las quejas consultas y sugerencias de las comunidades indígenas. | M18: Canalización, atención y direccionamiento, de las quejas, consultas y sugerencias de la población y las comunidades indígenas. | O18: 1 | 3 | 4 | 6 | P18: 1 | 3 | 4 | 6 | Q18: 1 | 3 | 4 | 6 | R18: 1 | 3 | 4 | 6 | S18: 1 | 3 | 4 | 6 | T18: 1 | 3 | 4 | 6 | U18: 1 | 3 | 4 | 6 | V18: 1 | 3 | 4 | 6 | W18: 1 | 3 | 4 | 6 | X18: 1 | 3 | 4 | 6 | Y18: 1 | 3 | 4 | 6 | Z18: 1 | 3 | 4 | 6 | AA18: Ene, Feb, Mar, Abr, May, Jun, Jul, Ago, Sep, Oct, Nov, Dic
A19: GESTIÓN DE QUEJAS, CONSULTAS Y SUGERENCIAS | B19: PR-SS-QRI | C19: 2 | D19: 100% de los buzones de Quejas, Consultas y Sugerencias ubicados en las comunidades y en las instalaciones de Paracel revisados y gestionados. | E19: 1. Revisión y reubicación de los buzones en las comunidades e instalaciones de Paracel en caso de necesidad. 2. Comunicación de las ubicaciones de los buzones. 3. Monitoreo de los registros recolectados en los buzones (internos cada 15 días y comunit | F19: - Número de buzones instalados en las comunidades e instalaciones de Paracel. - Número de quejas, consultas y sugerencias recibidas en cada buzón, clasificadas por tipo y zona geográfica. - Número | L19: - Sistema de gestión de quejas, sugerencias y consultas en funcionamiento. - Informe de seguimientiento a las quejas consultas y sugerencias de las comunidades indígenas. | M19: Canalización, atención y direccionamiento, de las quejas, consultas y sugerencias de la población y las comunidades indígenas. | O19: 3 | 4 | 5 | P19: 3 | 4 | 5 | Q19: 3 | 4 | 5 | R19: 3 | 4 | 5 | S19: 3 | 4 | 5 | T19: 3 | 4 | 5 | U19: 3 | 4 | 5 | V19: 3 | 4 | 5 | W19: 3 | 4 | 5 | X19: 3 | 4 | 5 | Y19: 3 | 4 | 5 | Z19: 3 | 4 | 5 | AA19: Ene, Feb, Mar, Abr, May, Jun, Jul, Ago, Sep, Oct, Nov, Dic
A20: PATRIMONIO CULTURAL | B20: PR-SS-PCU | C20: 1 | D20: Monitoreo de la aplicación del Protocolo de Hallazgos Fortuitos por parte de empresas contratistas de Paracel | E20: 1.Seguimiento en campo de la aplicación del protocolo de hallazgos fortuitos, por parte de las empresas contratistas. 2.Registro y monitoreo de socialización del contenido del Protocolo de Hallazgos Fortuitos. | F20: N.º de visitas de monitoreo realizadas en campo. N.º de empresas contratistas alcanzadas. N.º de colaboradores/as alcanzados/as. N.º de personas referentes identificadas y registradas para el reporte | L20: 1. Registros de monitoreo en campo sobre la aplicación del protocolo. 2. Informe de cumplimiento y avances en la implementación del protocolo | M20: Aplicación efectiva del Protocolo de Hallazgos Fortuitos por parte de empresas contratistas. | N20: ---- | T20: 1 | 2 | V20: 1 | 2 | X20: 1 | 2 | Z20: 1 | 2 | AA20: Jun, Ago, Oct, Dic
A21: PATRIMONIO CULTURAL | B21: PR-SS-PCU | C21: 2 | D21: Lograr el rescate, promoción y comercialización de artesanías de la comunidad indígena Redención | E21: 1. Creación de un catálogo de las artesanías de la comunidad indígena. 2. Soporte logístico para obtención de materia prima para la elaboración de los productos artesanales. 3. Identificación de puntos de venta y generación de alianzas para la comerc | F21: N.º de ferias y/o exposiciones en las que se participó N.º de emprendedores/as participantes por evento Volumen de ventas alcanzado por feria/exposición N.º de catálogos de artesanías creados y distri | L21: 1.Catálogo artesanal elaborado. 2.Participación en ferias y exposiciones. 3.Puntos de ventas identificados. 4.Informe final de actividades realizadas | M21: Rescate, promoción y fortalecimiento de la comercialización de artesanías de la comunidad indígena Redención, incrementando su visibilidad y acceso a mercados. | N21: ---- | T21: 1 | U21: 1 | V21: 3 | W21: 3 | X21: 3 | Y21: 3 | Z21: 3 | AA21: Jun, Jul, Ago, Sep, Oct, Nov, Dic
A22: INFRAESTRUCTURA SOCIAL | B22: PR-SS-RCI | C22: 2 | D22: Mejorar la infraestructura en comunidades rurales e indígenas del Área de Influencia de Paracel a través de intervenciones con foco en: A - Sistemas de acceso y distribución de agua. B -Mejoramiento de los sistemas de accesos y/o distribución de en | E22: 1. Seleccionar a las comunidades beneficiarias según críterios de elegibilidad. 2. Firma de cartas de compromiso con todas las comunidades seleccionadas (beneficiarias). 3. Toma de datos para establecimiento de la línea de base (comunitaria). 4. Toma | L22: 1- Criterios de elegibilidad del proyecto / mapa comunidades. 2- Convenios/ acuerdos. 3- Carta de compromiso firmadas por las comunidades beneficiadas. 4- Informe de línea de base. 5- Informe de línea | M22: - Comunidades con sistemas de acceso y distribución de agua. - Comunidades con mejoramiento de los sistemas de accesos y/o distribucion de energía eléctrica. | N22: 255.831 | P22: 1 | 2 | T22: 1 | 2 | 3 | 4 | U22: 1 | 2 | 3 | 4| 5 | 6 | 7 | V22: 3 | 4| 5 | 6 | 7 | W22: 5 | 6 | 7 | X22: 5| 6 |7 | Y22: 5 | 6 | 7| 8 | Z22: 8 | AA22: Feb, Jun, Jul, Ago, Sep, Oct, Nov, Dic
A23: INFRAESTRUCTURA SOCIAL | B23: PR-SS-RCI | C23: 2 | D23: Mejorar la infraestructura existente de la playa municipal del distrito de Paso Horqueta. | E23: 1. Implementar el proyecto existente 2. Seguimiento a través de la medición de indicadores de proceso. 3. Toma de datos para la medición de impacto del proyecto. 4. Desarrollo del informe final. | L23: 1- Proyectos Sistematizados 2- Informes mensuales de monitoreo. 3- Informe final del proyecto. | M23: Playa Municipal de Paso Horqueta con mejoras en infraestructura y aumento de la percepción positiva de la población. | N23: 20.000 | T23: 1 | 2 | U23: 1 | 2 | V23: 3 | W23: 4 | AA23: Jun, Jul, Ago, Sep
A24: ASOCIACIÓN DE PESCADORES | B24: PR-SS-PDP | C24: 1 | D24: Propiciar la formalización y mejora de la infraestructura de pescadores/as, con el fin de lograr el comercio optimo a través de la instalación de capacidades y el acceso a mercado. | E24: 1. Identificación de asociaciones y registro de pescadores. 2.Capacitaciones (formalización, comercialización, gestión). 3. Apoyo a la formalización y acceso a mercados. 4. Creación de alianzas y nuevos canales de venta. 5. Evaluación, contratacion d | F24: N° de asociaciones de pescadores beneficiadas N° de pescadores/as beneficiados/as, clasificados por edad, sexo, barrio y etnia N° de capacitación realizadas por asociación N° de participantes en cada | L24: 1.Base de datos de asociaciones y pescadores registrados 2.Listado de participantes capacitados 3.Documentación presentada para la formalización 4.Convenios o acuerdos firmados con aliados comerciales | M24: Fortalecimiento en la profesionalización y formalización de pescadores, con mejoras en su gestión, acceso a mercados y comercialización de productos. | T24: 1 | 10 | U24: 2 |3 |5 |6 |7 | 8| 11 | V24: 2| 3| 4| 7| 8| 9 | W24: 2 | 3| 4| 7| 8| 9 | X24: 4| 9| 12| 13 | Y24: 13 | AA24: Jun, Jul, Ago, Sep, Oct, Nov
A25: DESARROLLO DE PROVEEDORES LOCALES | B25: PR-SS-PDP | C25: 1 | D25: Implementar el Programa Ñañoty, de fomento forestal dirigido a [pequeños/as productores/as], situados en un radio de 50 km alrededor de algún emprendimiento (forestal e industrial) de Paracel. | E25: 1. Desarrollar un proyecto piloto de valor compartido con foco en la estrategia 2: inclusión en la cadena de valor de Paracel a [pequeños/as productores/as] forestales (vinculado a los plazos del área de Fomento Forestal. 2. Generar alianzas con orga | F25: - Número de plantines donados/entregados como capital semilla. - Número de alianzas alcanzadas. - Número de personas vinculadas al proyecto externas a Paracel (por actividad). - Monto de inversión dir | L25: 1- Criterios de elegibilidad del proyecto / mapa de familias (organizaciones). 2- Convenios/ acuerdos. 3- Carta de compromiso / interés firmadas por las personas/familias/organizaciones beneficiadas ( | M25: 50 hectáreas dentro del programa de fomento forestal social con resultados óptimos en el primer año. | P25: 1 | Q25: 1 | R25: 1 | 3 | S25: 1 | 3 | T25: 1 | 2 | 3 | U25: 1 | 2 | 3 | 4 | V25: 1 | 2 | 4 | W25: 1 | 2 | 4 | X25: 1 | 2 | 4 | Y25: 1 | 2 | 4 | Z25: 1 | 2 | 4 | AA25: Feb, Mar, Abr, May, Jun, Jul, Ago, Sep, Oct, Nov, Dic
A26: DESARROLLO DE PROVEEDORES LOCALES | B26: PR-SS-PDP | C26: 2 | D26: Generar alianzas para el desarrollo de espacios de networking y/o capacitación (virtual o presencial) dirigidos a Mipymes, con el objetivo de fortalecer su motivación, creatividad y visión de negocio. | E26: 1. Búsqueda y generación de alianzas y/o acuerdos para el desarrollo de espacios de networking y/o capacitación. 2. Planificación de la jornada de networking y/o espacios de capacitación. 3. Coordinación logística (lugar, insumos, convocatoria). 4. R | F26: N° de emprendedores inscritos y asistentes (Clasificados por edad, sexo, etnia, localidad, departamento). N° de rubros presentes en el evento. Cantidad de empresas por tamaño (micro, pequeña, mediana | L26: 1. Alianzas logradas. 2. Materiales y metodologías de trabajo desarrolladas. 3. Plan logístico y registro de participantes. 4. Primer espacio realizado. 5. Segundo espacio realizado. 6. Resultados de | M26: Espacios de networking y/o capacitaciones ejecutados con éxito, fortaleciendo las capacidades de los participantes y fomentando la creación de redes de colaboración entre emprendedores, facilitando el | T26: 1 | U26: 1 | 2 | V26: 2 | 3 | 4 | W26: 2 | 3 | X26: 5 | 6 | Y26: 7 | 8 | AA26: Jun, Jul, Ago, Sep, Oct, Nov
A27: COMUNIDADES INDÍGENAS | B27: PR-SS-RPI | C27: 1 | D27: Garantizar el cumplimiento del 100% de los procesos CLPI, en el marco del cumplimiento del Decreto 1039/18, la norma IFC, los criterios de la norma FSC® y el respeto de los Derechos de los Pueblos Indígenas para las comunidades indígenas del Área de | E27: 1- Realizar encuentros de socialización de avances de Paracel y los programas socioambientales en las comunidades indígenas dentro del AID. 2- Convenir con las comunidades indígenas el cumplimiento del proceso de “Consulta y Consentimiento, Libre, Pr | F27: A01- Número de personas participantes del proceso de consulta prevía, libre e informada por comunidad y clasificada por franja etaria, sexo, grado de instrucción, etc. A02- Proporción participación d | L27: Procesos de CPLI realizados | M27: Activar el proceso de CCPLI para todas las comunidades del AID de Paracel incluyendo zonas nuevas de expansión forestal. | N27: 3.896 | T27: 1 | Y27: 1 | AA27: Jun, Nov
A28: COMUNIDADES INDÍGENAS | B28: PR-SS-RPI | C28: 2 | D28: Desarrollo un plan de uso de servicios ecosistémicos con las comunidades indígenas que hacen uso de estos dentro de propiedades de Paracel. | E28: 1. Desarrollo de Plan de uso de servicios ecosistemicos 2. Socializacion del Plan de Uso de Servicios con los lideres y lideresas de las comunidades indígenas 3. Socialización del Plan de Uso de Servicios ecosistémicos con la comunidades indígenas 4. | F28: A01- Usos de servicios ecosistémicos identificados (tipo, superficie, estancias, personas que hacen uso, distancias de recorrido para uso, metodología de uso) A02- Plan de manejo de servicios ecosisté | L28: - Base de datos de uso de serivios ecosistémicos actualizados. - Mapas actualizados de uso de servicios ecosistémicos. - Planes de manejo de servicios ecosistémicos | M28: Informe de plan de manejo de uso de servicios ecosistémicos de tres comunidades indígenas. | N28: 0 | V28: 1 | W28: 1 | 2 | X28: 2 | Y28: 3 | 4 | Z28: 3 | 4 | AA28: Ago, Sep, Oct, Nov, Dic
A29: COMUNIDADES INDÍGENAS | B29: PR-SS-RPI | C29: 3 | D29: Mantener la vinculación con las comunidades Ita Jeguaka, Cerro Akangue y Arroyo Ka’a a través de actividades específicas coordinadas con lideres comunitarios. | E29: 1. Mantener comunicación con líderes comunitarios. 2. Coordinar la participación de líderes y/o lideresas en las actividades abiertas (capacitaciones, espacios de vinculación con entidades estatales, etc.) desarrolladas por Paracel. 3. Invitar y moni | F29: A01- Número de materiales entregados. A02- Número de vinculaciones por tipo (reuniones, invitaciones, contacto telefónico, etc). A02- Número de personas alcanzadas. A02- Número de consultas, expect | L29: - Materiales de comunicación desarrollados. - Reuniones desarrolladas. - Informe de vinculación | M29: Matener la vinculación con las comunidades Ita Jeguaka, Cerro Akangue y Arroyo Ka’a | N29: 2.727 | U29: 1 | X29: 1 | Y29: 5 | AA29: Jul, Oct, Nov
A30: COMUNIDADES INDÍGENAS | B30: PR-SS-RPI | C30: 4 | D30: Desarrollar jornadas de gestión documental vinculados a la identidad de los miembros de comunidades indígenas (cédulas de identidad, carnet indígena, partidas de nacimiento, inscripciones en el Registro Civil), etc. | E30: 1- Planificar las jornadas de cedulación con las instituciones del estado y las comunidades. 2- Activar las jornadas de cedulación. 3- Reporte del proceso. | F30: A01 - Cantidad de cédulas (Primera vez). A02 - Actas de nacimiento por edad (Niños menores de 0 a 4 años). A03 - Cantidad de documentaciones gestionados y obtenidos según tipo (Clasificado por edad, e | L30: - Cédulas entregadas a los miembros de las comunidades. | M30: - Personas de comunidades indígenas con registro de identidad (por primera vez). - Personas con cédula de identidad renovadas. | N30: 6.753 | T30: 1 | U30: 2 | V30: 3 | W30: 1 | X30: 2 | Y30: 3 | AA30: Jun, Jul, Ago, Sep, Oct, Nov
A31: COMUNIDADES INDÍGENAS | B31: PR-SS-RPI | C31: 5 | D31: Apoyar a la seguridad alimentaria escolar en comunidades del AID. | E31: 1. Analizar el alcance actual de programas de gobierno para provision de alimento escolar 2. Monitorear la entrega de alimento escolar complementaria 3. Proveer alimento complementario según resultados del análisis desarrollado 4. Encuesta respecto a | F31: A01 - Instituciones alcanzadas (distrito y tipo de comunidad). A02 - Número de niños alcanzados según RUE. A03 - Número de niños alcanzados (real). A04 - Kg de alimentos entregados. A05 - Proporción d | L31: - Informe de alcance de programas de gobierno para provisión de alimento escolar - Informe de entrega de almuerzo escolar | M31: - Estudiantes de escuelas con provisión de alimentos complementarios | N31: 15.909 | P31: 1 | 2 | 3 | Q31: 2 | 3 | R31: 2 | 3 | S31: 2 | 3 | T31: 2 | 3 | U31: 2 | 3 | V31: 2 | 3 | W31: 2 | 3 | X31: 2 | 3 | Y31: 2 | 3 | 4 | AA31: Feb, Mar, Abr, May, Jun, Jul, Ago, Sep, Oct, Nov
A32: COMUNIDADES INDÍGENAS | B32: PR-SS-RPI | C32: 6 | D32: Apoyar a referentes de comunidades indígenas en el relacionamiento con instituciones del estado a fin de autogestionar los temas relacionados a su organización comunitaria o política (identidad, vivienda, salud, educación, etc.). | E32: 1. Analisis y registro de solicitudes. 2. Gestión de apoyo a solicitudes ingresadas. 3. Informe de gestiones realizadas. | F32: A01 - Número de gestiones clasificadas por documentación de identidad, documentación comunitaria, salud, seguridad, acceso a servicios básicos, etc. A02 - Número de instituciones (desagregadas). A03 | L32: Informe de relacionamiento institucional | M32: Autogestión comunitaria reflejada en número de trámites o procesos ejecutados con instituciones. | N32: 5.065 | O32: 1 | 2 | P32: 1 | 2 | Q32: 1 | 2 | R32: 1 | 2 | S32: 1 | 2 | T32: 1 | 2 | U32: 1 | 2 | V32: 1 | 2 | W32: 1 | 2 | X32: 1 | 2 | Y32: 1 | 2 | 3 | Z32: 3 | AA32: Ene, Feb, Mar, Abr, May, Jun, Jul, Ago, Sep, Oct, Nov, Dic

Sheet Indicadores
A1: Ficha | B1: Código Programa | C1: Target | D1: Indicador | E1: Fórmula de Cálculo | F1: Fuente de Verificación | G1: Periodicidad | H1: Responsable | I1: Evidencia | J1: Raw (original)
A2: PROGRAMA DE DESARROLLO Y VINCULACIÓN CON LA MANO DE OBRA LOCAL | B2: PR-SS-MDO | C2: Target 2 | D2: 1. Indicadores socioeconómicos. 2. Número de personas beneficiadas clasificadas por edad, sexo, comunidad, etnía. 3. Nivel academico alcanzado por los padres/tutores - hermanos/as mayores. 4. Número de instituciones alidas y especialidades. 5. Inversión mensual (seguimiento del presupuesto). 6. Horas al mes destinada por parte de padrinos/madrinas en el acompañamiento de las personas. 7. Reporte de calificaciones por período académico y por estudiante. | J2: 1. Indicadores socioeconómicos. 2. Número de personas beneficiadas clasificadas por edad, sexo, comunidad, etnía. 3. Nivel academico alcanzado por los padres/tutores - hermanos/as mayores. 4. Número de instituciones alidas y especialidades. 5. Inversión mensual (seguimiento del presupuesto). 6
A3: PROGRAMA DE DESARROLLO Y VINCULACIÓN CON LA MANO DE OBRA LOCAL | B3: PR-SS-MDO | C3: Target 1 | D3: - Indicadores de Educación - Indicadores de Empleo | J3: Descripción de Indicadores de Línea de Base Tipo de indicador Global: Se cuenta con datos para la construcción del indicador propuesto para el seguimiento del objetivo. Unidad de medida Tasa expresada en porcentaje Descripción de Indicadores de Proceso - Número de personas beneficarias. - Número d
A4: EMPODERAMIENTO DE LA MUJER | B4: PR-SS-EMU | C4: Target 1 | D4: - Número de personas alcanzadas clasificadas sexo, edad, etnia, comunidad, institución, etc. - N° de materiales desarrollados y difundidos. | J4: - Número de personas alcanzadas clasificadas sexo, edad, etnia, comunidad, institución, etc. - N° de materiales desarrollados y difundidos.
A5: EMPODERAMIENTO DE LA MUJER | B5: PR-SS-EMU | C5: Target 2 | D5: - Número de personas que participaron de los espacios desagregadas por sexo, edad, etnia, organización, etc. - Número de horas de los espacios. - Número de espacios propociados. - Número de temas abordados. - Número de personas invitadas. - Número de personas vinculadas al proyecto externas a Paracel (por actividad). - Inversión. - Conocimiento de las personas antes y despues de la participación de los espacios. | J5: - Número de personas que participaron de los espacios desagregadas por sexo, edad, etnia, organización, etc. - Número de horas de los espacios. - Número de espacios propociados. - Número de temas abordados. - Número de personas invitadas. - Número de personas vinculadas al proyecto externas a
A6: GESTIÓN DE EMPRESAS CONTRATISTAS | B6: PR-SS-CON | C6: Target 1 | D6: - Número de empresas auditadas. - Proporción de empresas auditadas con relación al número total de empresas. - Número total de hallazgos. - Número total de observaciones y oportunidades de mejora. - Porcentaje de cierre de los hallazgos y de manera general. - Porcentaje de cumplimiento de plazos de cierre de los hallazgos y de manera general. - Cantidad de acompañamientos. | J6: - Número de empresas auditadas. - Proporción de empresas auditadas con relación al número total de empresas. - Número total de hallazgos. - Número total de observaciones y oportunidades de mejora. - Porcentaje de cierre de los hallazgos y de manera general. - Porcentaje de cumplimiento de plazo
A7: GESTIÓN DE EMPRESAS CONTRATISTAS | B7: PR-SS-CON | C7: Target 2 | D7: - Número de personas participantes clasificados por organización, cargo, rango etario, sexo, comunidad, etnia. - Número de horas de capacitación. - Número de temas desarrollados. - Datos sobre conocimiento del tema antes de iniciar los talleres y conocimientos adquiridos posterior a los talleres. - Porcentaje de participación con relación al número total de empresas y trabajadores/as. - Porcentaje de uso del presupuesto de manera mensual. | J7: - Número de personas participantes clasificados por organización, cargo, rango etario, sexo, comunidad, etnia. - Número de horas de capacitación. - Número de temas desarrollados. - Datos sobre conocimiento del tema antes de iniciar los talleres y conocimientos adquiridos posterior a los talleres.
A8: SALUD Y SEGURIDAD COMUNITARIA | B8: PR-SS-SSC | C8: Target 1 (Asistencia médica) | D8: - Número de alianzas firmadas. - Número de personas que participaron de las asistencia desagregadas por sexo, edad, etnia, comunidad, etc. - Número de USF intervenidas. - Número de especialidades médicas por asistencia. - Número de personas vinculadas al programa externas a Paracel (por actividad). - Monto de inversión directa o indirecta por parte de las organizaciones aliadas (por actividad). - Porcentaje de uso del presupuesto mensual. | J8: - Número de alianzas firmadas. - Número de personas que participaron de las asistencia desagregadas por sexo, edad, etnia, comunidad, etc. - Número de USF intervenidas. - Número de especialidades médicas por asistencia. - Número de personas vinculadas al programa externas a Paracel (por actividad
A9: SALUD Y SEGURIDAD COMUNITARIA | B9: PR-SS-SSC | C9: Target 2 (PANI | PAI) | D9: - Número de alianzas firmadas. - Número de personas alcanzadas en la distribución de leche desagregadas por sexo, edad, etnia, comunidad, etc. - Número de personas alcanzadas en jornadas de inmunización. - Número de USF intervenidas. - Número de personas vinculadas al programa externas a Paracel (por actividad). - Monto de inversión directa o indirecta por parte de las organizaciones aliadas (por actividad). - Porcentaje de uso del presupuesto mensual. | J9: - Número de alianzas firmadas. - Número de personas alcanzadas en la distribución de leche desagregadas por sexo, edad, etnia, comunidad, etc. - Número de personas alcanzadas en jornadas de inmunización. - Número de USF intervenidas. - Número de personas vinculadas al programa externas a Paracel (
A10: SALUD Y SEGURIDAD COMUNITARIA | B10: PR-SS-SSC | C10: Target 3 (Salud Sexual) | D10: - Número de alianzas generadas. - Número comunidades abordadas. - Número de personas beneficiadas desagregadas por sexo, edad, etnia, comunidad, etc. - Número de personas vinculadas al programa externas a Paracel (por actividad). - Monto de inversión directa o indirecta por parte de las organizaciones aliadas (por actividad). - Porcentaje de uso del presupuesto mensual. - Número de testeos realizados. - Número de colaboradores/as de empresas contratistas abordados/as. | J10: - Número de alianzas generadas. - Número comunidades abordadas. - Número de personas beneficiadas desagregadas por sexo, edad, etnia, comunidad, etc. - Número de personas vinculadas al programa externas a Paracel (por actividad). - Monto de inversión directa o indirecta por parte de las organiza
A11: SALUD Y SEGURIDAD COMUNITARIA | B11: PR-SS-SSC | C11: Target 4 (MINNA) | D11: - Número de personas formadas como facilitadoras. - Número de instituciones representadas. - Número de personas alcanzadas en espacios de sensibilización clasificadas por edad y sexo. - Número de materiales entregados. | J11: - Número de personas formadas como facilitadoras. - Número de instituciones representadas. - Número de personas alcanzadas en espacios de sensibilización clasificadas por edad y sexo. - Número de materiales entregados.
A12: MANEJO SOCIAL | B12: PR-SS-MSC | C12: Target 1 | D12: 1. Número de personas participantes por comunidad clasificadas, por edad, sexo, franja etaria, comunidad, etnia. 2. Índice de percepción. 3. Datos sobre migración 4. Materiales desarrollados. 5. Número de personas de las diferentes áreas de Paracel participantes. | J12: 1. Número de personas participantes por comunidad clasificadas, por edad, sexo, franja etaria, comunidad, etnia. 2. Índice de percepción. 3. Datos sobre migración 4. Materiales desarrollados. 5. Número de personas de las diferentes áreas de Paracel participantes.
A13: MANEJO SOCIAL | B13: PR-SS-MSC | C13: Target 2 | D13: 1. Número de personas participantes por comunidad clasificadas, por edad, sexo, franja etaria, comunidad, etnia. 2. Índice de percepción. 3. Materiales desarrollados. 4. Número de personas de las diferentes áreas de Paracel participantes. | J13: 1. Número de personas participantes por comunidad clasificadas, por edad, sexo, franja etaria, comunidad, etnia. 2. Índice de percepción. 3. Materiales desarrollados. 4. Número de personas de las diferentes áreas de Paracel participantes.
... A22: ASOCIACIÓN DE PESCADORES | B22: PR-SS-PDP | C22: Target 1: Fortalecer la profesionalización y formalización de pescadores | D22: N° de asociaciones de pescadores beneficiadas N° de pescadores/as beneficiados/as, clasificados por edad, sexo, barrio y etnia N° de capacitación realizadas por asociación N° de participantes en cada taller, clasificados por edad, sexo, barrio, localidad, asociación, etnia % del nivel de conocimientos adquiridos N° de acuerdos firmados con instituciones y/o organizaciones claves % de incremento en ventas de productos pesqueros N° de asociaciones participantes en jornada de formalización con el MADES N° de pescadores/as formalizados/as, clasificados por asociación N° de empresas consultoras contratadas (Clasificados por edad, sexo, distrito, departamento) Valor de inversión en guaraníes por Paracel y organizaciones aliadas N° de puntos de venta evaluados y diagnosticados Cantidad de alianzas estratégicas formalizadas N° de intervenciones ejecutadas en infraestructura y logística Cantidad de equipamientos entregados a puntos de venta Medición del impacto en ventas Valor de inversión en guaraníes por Paracel y organizaciones aliadas N° de asociaciones identificadas y evaluadas Cantidad de documentos tramitados para la formalización N° de asociaciones con personería jurídica obtenida % de asociaciones formalizadas con éxito | J22: N° de asociaciones de pescadores beneficiadas N° de pescadores/as beneficiados/as, clasificados por edad, sexo, barrio y etnia N° de capacitación realizadas por asociación N° de participantes en cada taller, clasificados por edad, sexo, barrio, localidad, asociación, etnia % del nivel de conocimient
A23: DESARROLLO DE PROVEEDORES LOCALES | B23: PR-SS-PDP | C23: Target 1 Implementar el Programa Ñañoty, de fomento forestal dirigido a [pequeños/as productores/as], situados en un radio de 50 km alrededor de algún emprendimiento (forestal e industrial) de Paracel. | D23: - Número de plantines donados/entregados como capital semilla. - Número de alianzas alcanzadas. - Número de personas vinculadas al proyecto externas a Paracel (por actividad). - Monto de inversión directa o indirecta por parte de las organizaciones aliadas (por actividad). - Número de contratos firmados con las personas participantes del proyecto. - Número de plantines donados/entregados como capital semilla. - Cantidad de insumos, equipos y herramientas entregados (también en guaraníes). - Cantidad de horas de asesoramiento técnico destinadas a cada beneficiario/a (visitas). - Cantidad de asesoramiento técnico a través de visitas destinadas a cada beneficiario/a. - Cantidad de horas de capacitación destinada a cada beneficiario/a. - Número de servicios alcanzados con el proyecto (también en guaraníes - mano de obra, flete, traslado, maquinaria). - Porcentaje de uso del presupuesto de manera mensual. - Número de mano de obra contratada clasificada por región (local, departamental, nacional). - Cantidad de guaraníes invertidos en el departamento de Concepción. - Observación: (todos los datos deben ser clasificados por edad, sexo, tipo de comunidad, las comunidades deben ser clasificadas utilizando el nombre las mismas y las etnias si aplica).
A24: DESARROLLO DE PROVEEDORES LOCALES | B24: PR-SS-PDP | C24: Target 2 [Generar alianzas para el desarrollo de espacios de networking y/o capacitación (virtual o presencial) dirigidos a Mipymes, con el objetivo de fortalecer su motivación, creatividad y visión de negocio]. | D24: N° de emprendedores inscritos y asistentes (Clasificados por edad, sexo, etnia, localidad, departamento). N° de rubros presentes en el evento. Cantidad de empresas por tamaño (micro, pequeña, mediana y grande). N° de empresas vinculadas con Paracel (participantes del Programa 2023, 2024). % de satisfacción de los/las participantes. N° de necesidades identificadas para futuras capacitaciones. N° de consultores contratados (Clasificados por edad, sexo, distrito, departamento). Valor de inversión en guaraníes por Paracel y organizaciones aliadas. EVALUACIÓN DE IMPACTO MÉTODO DE EVALUACIÓN No Experimental (Antes y Después) (Facturación, número de personas contratadas, número de clientes, cantidad de documentos legales disponibles, volumen de producción, modalidad del negocio, etc.)
A25: COMUNIDADES INDÍGENAS | B25: PR-SS-RPI | C25: Target 1 : Garantizar el cumplimiento del 100% de los procesos CLPI, en el marco del cumplimiento del Decreto 1039/18, la norma IFC, los criterios de la norma FSC y el respeto de los Derechos de los Pueblos Indígenas para las comunidades indígenas del Área de Influencia Directa del proyecto Paracel para el año 2025. | D25: A01- Número de personas participantes del proceso de consulta prevía, libre e informada por comunidad y clasificada por franja etaria, sexo, grado de instrucción, etc. A02- Proporción participación de familias en función al número total de familias de la comunidad (Calculado con miembros adultos representantes de familia) A03- Número de reuniones de socialización. A04- Número de personas de otras instituciones que acompañan el proceso. A05- Inversión de otras instituciones en el proceso de consultas. A06- Lista de comentarios, percepción, expectativas de los miembros de las comunidades. A07- Tiempo invertido en el desarrollo de los procesos de consulta. A08- Número de materiales de socialización desarrollados. | J25: A01- Número de personas participantes del proceso de consulta prevía, libre e informada por comunidad y clasificada por franja etaria, sexo, grado de instrucción, etc. A02- Proporción participación de familias en función al número total de familias de la comunidad (Calculado con miembros adultos re
A26: COMUNIDADES INDÍGENAS | B26: PR-SS-RPI | C26: Target 2 : Desarrollo un plan de uso de servicios ecosistémicos con las comunidades indígenas que hacen uso de estos dentro de propiedades de Paracel. | D26: A01- Usos de servicios ecosistémicos identificados (tipo, superficie, estancias, personas que hacen uso, distancias de recorrido para uso, metodología de uso) A02- Plan de manejo de servicios ecosistémicos (cantidad de planes desarrollados e implementados, ubicación) A03- Evaluaciones y socializaciones de planes de uso de servicios ecosistémicos A04- Implementación de planes de uso de servicios ecosistémicos La desagregaciones se dan por comunidad, sexo, edad, número de personas | J26: A01- Usos de servicios ecosistémicos identificados (tipo, superficie, estancias, personas que hacen uso, distancias de recorrido para uso, metodología de uso) A02- Plan de manejo de servicios ecosistémicos (cantidad de planes desarrollados e implementados, ubicación) A03- Evaluaciones y socializacio
A27: COMUNIDADES INDÍGENAS | B27: PR-SS-RPI | C27: Target 3 : Mantener la vinculación con las comunidades Ita Jeguaka, Cerro Akangue y Arroyo Ka’a a través de actividades específicas coordinadas con lideres comunitarios. | D27: A01- Número de materiales entregados. A02- Número de vinculaciones por tipo (reuniones, invitaciones, contacto telefónico, etc). A02- Número de personas alcanzadas. A02- Número de consultas, expectativas, sugerencias. A03- Número de actividades en las que participaron. La desagregaciones se dan por comunidad, sexo, edad. | J27: A01- Número de materiales entregados. A02- Número de vinculaciones por tipo (reuniones, invitaciones, contacto telefónico, etc). A02- Número de personas alcanzadas. A02- Número de consultas, expectativas, sugerencias. A03- Número de actividades en las que participaron. La desagregaciones se da
A28: COMUNIDADES INDÍGENAS | B28: PR-SS-RPI | C28: Target 4 : Desarrollar jornadas de gestión documental vinculados a la identidad de los miembros de comunidades indígenas (cédulas de identidad, carnet indígena, partidas de nacimiento, inscripciones en el Registro Civil), etc. | D28: A01 - Cantidad de cédulas (Primera vez). A02 - Actas de nacimiento por edad (Niños menores de 0 a 4 años). A03 - Cantidad de documentaciones gestionados y obtenidos según tipo (Clasificado por edad, edad, sexo, comunidad, etc). La desagregaciones se dan por persona, edad, sexo, comunidad, etc. | J28: A01 - Cantidad de cédulas (Primera vez). A02 - Actas de nacimiento por edad (Niños menores de 0 a 4 años). A03 - Cantidad de documentaciones gestionados y obtenidos según tipo (Clasificado por edad, edad, sexo, comunidad, etc). La desagregaciones se dan por persona, edad, sexo, comunidad, etc.
A29: COMUNIDADES INDÍGENAS | B29: PR-SS-RPI | C29: Target 5 : Apoyar a la seguridad alimentaria escolar en comunidades del AID. | D29: A01 - Instituciones alcanzadas (distrito y tipo de comunidad). A02 - Número de niños alcanzados según RUE. A03 - Número de niños alcanzados (real). A04 - Kg de alimentos entregados. A05 - Proporción de alimentos por tipo. Datos desagregados por sexo, edad y grado. | J29: A01 - Instituciones alcanzadas (distrito y tipo de comunidad). A02 - Número de niños alcanzados según RUE. A03 - Número de niños alcanzados (real). A04 - Kg de alimentos entregados. A05 - Proporción de alimentos por tipo. Datos desagregados por sexo, edad y grado.
A30: COMUNIDADES INDÍGENAS | B30: PR-SS-RPI | C30: Target 6 : Apoyar a referentes de comunidades indígenas en el relacionamiento con instituciones del estado a fin de autogestionar los temas relacionados a su organización comunitaria o política (identidad, vivienda, salud, educación, etc.). | D30: A01 - Número de gestiones clasificadas por documentación de identidad, documentación comunitaria, salud, seguridad, acceso a servicios básicos, etc. A02 - Número de instituciones (desagregadas). A03 - Valor invertido. | J30: A01 - Número de gestiones clasificadas por documentación de identidad, documentación comunitaria, salud, seguridad, acceso a servicios básicos, etc. A02 - Número de instituciones (desagregadas). A03 - Valor invertido.

Sheet MATRIZ CONSOLIDADA
A1: N° | B1: CÓDIGO PROGRAMA | C1: NOMBRE PROGRAMA | D1: VERSIÓN PROG. | E1: ESTADO | F1: NOMBRE FICHA | G1: VERSIÓN FICHA | H1: FECHA FICHA | I1: TARGET N° | J1: DESCRIPCIÓN TARGET | K1: ACTIVIDADES | L1: INDICADOR | M1: FÓRMULA DE CÁLCULO | N1: FUENTE DE VERIFICACIÓN | O1: PERIODICIDAD | P1: RESPONSABLE | Q1: EVIDENCIA | R1: PRODUCTOS | S1: RESULTADO ESPERADO | T1: PRESUPUESTO (USD) | U1: MESES ACTIVOS | V1: PROPÓSITO FICHA | W1: NECESIDAD | X1: OBJETIVO PROGRAMA | Y1: ALCANCE PROGRAMA | Z1: MARCO LEGAL
A2: 1 | B2: PR-SS-MDO | C2: Desarrollo y Vinculación de Mano de Obra Local | D2: v05 | E2: Vigente | F2: PROGRAMA DE DESARROLLO Y VINCULACIÓN CON LA MANO DE OBRA LOCAL | G2: v01 | H2: 2025-06-04 | I2: 1 | J2: Contribuir para aumentar el número de jóvenes y adultos con competencias técnicas y profesionales, para acceder al empleo (el trabajo decente) a través del desarrollo de [10] cursos de capacitación, y [8] jornadas de certificación laboral por competencias, en los componentes Forestal Industrial e I | K2: 1. Selección de organizaciones aliadas para el desarrollo de las capacitaciones y las certificaciones. 2. Suscribir convenios con instituciones educativas locales y nacionales con el fin de acordar un marco de cooperación para la formación y capacitación laboral del capital humano local y nacional. | L2: - Indicadores de Educación - Indicadores de Empleo | R2: 1 - Convenios / acuerdos. 2 - Curso de capacitación 3 - Jornadas de certificación. 4 - Base de datos de personas que culminaron los cursos y certificaciones. 4- Informe de línea de base. 5- Proyecto | S2: - Aumento del número de jóvenes y adultos con competencias técnicas y profesionales para acceder al empleo (trabajo decente). - Profesionales certificados para acceder al empleo (trabajo decente o | U2: May, Jun, Jul, Ago, Sep, Oct, Nov, Dic | V2: Desarrollar e instalar competencias y capacidades técnicas y profesionales en el área de influencia de Paracel | W2: - Falta de competencias técnicas y profesionales en la mano de obra local y departamental. - Centralización en la ciudad Concepción de los servicios de educación técnico y profesional. - Población | X2: Promover la generación de empleo local a través de la vinculación de mano de obra calificada y no calificada, [además del desarrollo e instalación de capacidades, en el área de influencia de Paracel]. | Y2: DEFINICIONES Área de Influencia Directa (AID) del componente industrial: incluyen 5 distritos cercanos al sitio de la Planta Industrial, incluyendo a 18 comunidades que se encuentran en un radio de 13
A3: 2 | B3: PR-SS-MDO | C3: Desarrollo y Vinculación de Mano de Obra Local | D3: v05 | E3: Vigente | F3: PROGRAMA DE DESARROLLO Y VINCULACIÓN CON LA MANO DE OBRA LOCAL | G3: v01 | H3: 2025-06-04 | I3: 2 | J3: Becar a jóvenes de las comunidades del área e influencia de Paracel: - 10 jóvenes para educación en Bachiller Técnico. - 11 jóvenes para educación Terciaria. | K3: 1 - Seleccionar a las personas jóvenes conforme a criterios de elegibilidad. 2 - Medición de la línea de base. 3 - Buscar aliados estratégicos para la implementación del proyecto de becas (si aplica). 4 - Firma de carta compromiso. 5- Llamado interno para contar con voluntarios/as para el acompaña | L3: 1. Indicadores socioeconómicos. 2. Número de personas beneficiadas clasificadas por edad, sexo, comunidad, etnía. 3. Nivel academico alcanzado por los padres/tutores - hermanos/as mayores. 4. Número de instituciones alidas y especialidades. 5. Inversión mensual (seguimiento del presupuesto). 6. Horas al mes destinada por parte de padrinos/madrinas en el acompañamiento de las personas. 7. Reporte de calificaciones por período académico y por estudiante. | R3: Jóvenes con estudios técnicos y terciarios finalizados. | S3: Jóvenes con estudios técnicos y terciarios finalizados. | T3: 14.851 | U3: Feb, Mar, Abr, May, Jun, Jul, Ago, Sep, Oct, Nov, Dic | V3: Desarrollar e instalar competencias y capacidades técnicas y profesionales en el área de influencia de Paracel | W3: - Falta de competencias técnicas y profesionales en la mano de obra local y departamental. - Centralización en la ciudad Concepción de los servicios de educación técnico y profesional. - Población | X3: Promover la generación de empleo local a través de la vinculación de mano de obra calificada y no calificada, [además del desarrollo e instalación de capacidades, en el área de influencia de Paracel]. | Y3: DEFINICIONES Área de Influencia Directa (AID) del componente industrial: incluyen 5 distritos cercanos al sitio de la Planta Industrial, incluyendo a 18 comunidades que se encuentran en un radio de 13
A4: 3 | B4: PR-SS-EMU | C4: Empoderamiento de la Mujer | D4: v04 | E4: Vigente | F4: EMPODERAMIENTO DE LA MUJER | G4: v01 | H4: 2025-06-04 | I4: 1 | J4: Difundir la Ruta de Auxilio desarrollada en el año 2024 con foco en los siguientes municipios: Concepción, Paso Barreto, Sargento José Felix López, Paso Horqueta, alcanzando como mínimo al 80% de las comunidades del área de influencia de Paracel. | K4: 1. Selección de las áreas geográficas a ser intervenidas (componentes) y comunidades alcanzadas. 2. Difusión de los materiales. 3. Desarrollo del informe final. | L4: - Número de personas alcanzadas clasificadas sexo, edad, etnia, comunidad, institución, etc. - N° de materiales desarrollados y difundidos. | R4: 1. Materiales difundidos. 2. Informe final. | S4: Personas de las comunidades del área de influencia de Paracel con información la ruta de auxilio ante casos de violencia hacia las mujeres. | T4: 0 | U4: Jun, Jul, Oct, Nov, Dic | V4: Empoderar a las mujeres para acortar las brechas de desigualdad étnicas y de género. | W4: Las mujeres no participan plenamente de todos los sectores y todos los niveles de la actividad económica, y por ende no se construyen economías fuertes, y esto conlleva a no cumplir los objetivos de | X4: Empoderar a las mujeres para acortar las brechas de desigualdad étnicas y de género. | [FSC-STD-PRY-01-2022] Normas de Desempeño IFC REGISTROS Y/O ANEXO [Registro del Plan de Comunicación [Registro de | Y4: El programa de Empoderamiento de la Mujer tiene el siguiente alcance: DEFINICIONES Área de Influencia Directa (AID) del componente indígena: está compuesta por las comunidades indígenas ubicadas entr
A5: 4 | B5: PR-SS-EMU | C5: Empoderamiento de la Mujer | D5: v04 | E5: Vigente | F5: EMPODERAMIENTO DE LA MUJER | G5: v01 | H5: 2025-06-04 | I5: 2 | J5: Fortalecer la red de apoyo para las mujeres de la Región de Concepción desarrollando como mínimo 3 espacios. | K5: 1. Propiciar espacios de intercambio de conocimientos, experiencias y aprendizajes con la red de mujeres y referentes invitadas por Paracel. 2. Desarrollo del informe final. | L5: - Número de personas que participaron de los espacios desagregadas por sexo, edad, etnia, organización, etc. - Número de horas de los espacios. - Número de espacios propociados. - Número de temas abordados. - Número de personas invitadas. - Número de personas vinculadas al proyecto externas a Paracel (por actividad). - Inversión. - Conocimiento de las personas antes y despues de la participación de los espacios. | R5: 1. Informe final. | S5: Mujeres de la red de apoyo con mayor conocimiento para afrontar los desafíos de las mujeres en la sociedad. | T5: 0 | U5: Jul, Sep, Nov, Dic | V5: Empoderar a las mujeres para acortar las brechas de desigualdad étnicas y de género. | W5: Las mujeres no participan plenamente de todos los sectores y todos los niveles de la actividad económica, y por ende no se construyen economías fuertes, y esto conlleva a no cumplir los objetivos de | X5: Empoderar a las mujeres para acortar las brechas de desigualdad étnicas y de género. | [FSC-STD-PRY-01-2022] Normas de Desempeño IFC REGISTROS Y/O ANEXO [Registro del Plan de Comunicación [Registro de | Y5: El programa de Empoderamiento de la Mujer tiene el siguiente alcance: DEFINICIONES Área de Influencia Directa (AID) del componente indígena: está compuesta por las comunidades indígenas ubicadas entr
A6: 5 | B6: PR-SS-CON | C6: Sensibilización y Seguimiento a Contratistas y Trabajadores | D6: v05 | E6: Vigente | F6: GESTIÓN DE EMPRESAS CONTRATISTAS | G6: v00 | H6: 2025-06-04 | I6: 1 | J6: Auditar de forma trimestral a empresas contratistas del componente Forestal e Industrial (si aplica) en materia de sustentabilidad social considerando las normativas nacionales e internacionales adoptadas por Paracel, en el marco del respeto de los derechos de los pueblos indígenas y comunidades rur | K6: 1. Selección de empresas contratistas a ser auditadas (el número de empresas puede aumentar dependiendo de los hallazgos de No Conformidades). 2. Desarrollo de las auditorías trimestrales. 3. Acompañamiento mensual para la revisión de los planes de acciones correctivas para el cierre de los hallazgo | L6: - Número de empresas auditadas. - Proporción de empresas auditadas con relación al número total de empresas. - Número total de hallazgos. - Número total de observaciones y oportunidades de mejora. - Porcentaje de cierre de los hallazgos y de manera general. - Porcentaje de cumplimiento de plazos de cierre de los hallazgos y de manera general. - Cantidad de acompañamientos. | R6: Informes de Auditoría Manual de Buenas Prácticas de Manufactura. | S6: - Cumplimiento de las normativas nacionales e internaciones. - Respeto en la vinculación con comunidades indígenas y rurales. | T6: ---- | U6: Ene, Feb, Mar, Abr, May, Jun, Jul, Ago, Sep, Oct, Nov, Dic | V6: Acompañar y monitorear a [empresas contratistas y trabajadores/as] para asegurar el cumplimiento de las normativas nacionales y [estándares de sostenibilidad internacionales en materia social]. Monito | W6: Incumplimiento de normativas nacionales e estándares internacionales, y de los requisitos establecidos por Paracel a las empresas proveedoras por falta de conocimineto y experiencia por parte de empre | X6: Acompañar y monitorear a [empresas contratistas y trabajadores/as] para asegurar el cumplimiento de las normativas nacionales y [estándares de sostenibilidad internacionales en materia social]. Monito | Y6: [Este programa tiene el siguiente alcance]: DEFINICIONES Área de Influencia Directa (AID) del componente forestal: incluye a [6] distritos en los que se localizan las áreas de las plantaciones foresta
A7: 6 | B7: PR-SS-CON | C7: Sensibilización y Seguimiento a Contratistas y Trabajadores | D7: v05 | E7: Vigente | F7: GESTIÓN DE EMPRESAS CONTRATISTAS | G7: v00 | H7: 2025-06-04 | I7: 2 | J7: Sensibilizar al 100% de las empresas contratistas del componente forestal e industrial [(si aplica)] en temas relacionados [a las normas nacionales, estándares internacionales y procesos documentales adoptados de Paracel]. | K7: 1. Desarrollar un plan de capacitación para las áreas administrativas de las empresas contratistas, sobre principios establecidos en los estándares y procesos documentales adoptados por Paracel. 2. Implementar las capacitaciones conforme al plan de capacitación. 3. Identificar en campo, situacion | L7: - Número de personas participantes clasificados por organización, cargo, rango etario, sexo, comunidad, etnia. - Número de horas de capacitación. - Número de temas desarrollados. - Datos sobre conocimiento del tema antes de iniciar los talleres y conocimientos adquiridos posterior a los talleres. - Porcentaje de participación con relación al número total de empresas y trabajadores/as. - Porcentaje de uso del presupuesto de manera mensual. | R7: Plan de Capacitación Capacitaciones | S7: Empresas más sensibilizadas y con conocimiento. | U7: Mar, Jun, Jul, Ago, Sep, Nov, Dic | V7: Acompañar y monitorear a [empresas contratistas y trabajadores/as] para asegurar el cumplimiento de las normativas nacionales y [estándares de sostenibilidad internacionales en materia social]. Monito | W7: Incumplimiento de normativas nacionales e estándares internacionales, y de los requisitos establecidos por Paracel a las empresas proveedoras por falta de conocimineto y experiencia por parte de empre | X7: Acompañar y monitorear a [empresas contratistas y trabajadores/as] para asegurar el cumplimiento de las normativas nacionales y [estándares de sostenibilidad internacionales en materia social]. Monito | Y7: [Este programa tiene el siguiente alcance]: DEFINICIONES Área de Influencia Directa (AID) del componente forestal: incluye a [6] distritos en los que se localizan las áreas de las plantaciones foresta
